Workbook

Sheet Scoring Format
A1: Category | B1: Pts
A2: Pts per Passing Yard | B2: 0.05
A3: Pts per Rushing Yard | B3: 0.1
A4: Pts per Receiving Yard | B4: 0.1
A5: Pts per Pass TD | B5: 4
A6: Pts per Rush TD | B6: 6
A7: Pts per Rec TD | B7: 6
A8: Pts per Turnover | B8: -1

Sheet ARI
A1: Arizona Cardinals
A3: Team Projections Menu | AD3: Team Projections Menu
I5: RSP Projections: Year 1 | N5: Adjustable Projections: Year 1 | T5: Offense Distribution | AK5: RSP Projections: Year 1 | AP5: Adjustable Projections: Year 1
I6: RSP Projections: Year 2 | N6: Past Run/Pass Performances | T6: Run | U6: Pass | AK6: RSP Projections: Year 2
T7: =(N17+D27+L38+L47)/(N17+D27+L38+D17) -> 0.39219713 | U7: =D17/(D17+N17+D27+L38+L47) -> 0.60780287
A10: RSP Projections: Year 1 | AD10: Adjustable Projections: Year 1
D12: Passing | M12: Rushing | S12: Touches | W12: Fantasy Points | AF12: Passing | AO12: Rushing | AU12: Touches | AY12: Fantasy Points
A13: QB | B13: Age | C13: G | D13: Att | E13: Comp | F13: Pct | G13: Yards | H13: Yds/Att | I13: TDs | J13: TDs/Att | K13: Int | L13: Int/Att | N13: Ratt | O13: Ryds | P13: Ryds/Att | Q13: TDs | R13: Tds/Att | T13: Touch % | U13: Pct Pass | V13: Pct Run | X13: Fpts | Y13: Adjusted | AD13: QB | AE13: G | AF13: Att | AG13: Comp | AH13: Pct | AI13: Yards | AJ13: Yds/Att | AK13: TDs | AL13: TDs/Att | AM13: Int | AN13: Int/Att | AP13: Ratt | AQ13: Ryds | AR13: Ryds/Att | AS13: TDs | AT13: Tds/Att | AV13: Touch % | AW13: Pct Pass | AX13: Pct Run | AZ13: Fpts | BA13: Adjusted
A14: QB*Brissett, Jacoby - ARI | B14: 33 | C14: 17 | D14: 592 | E14: 403 | F14: =E14/D14 -> 0.68074324 | G14: 4542 | H14: =G14/D14 -> 7.6722973 | I14: 28 | J14: =I14/D14 -> 0.047297297 | K14: 11 | L14: =K14/D14 -> 0.018581081 | N14: 46 | O14: 195 | P14: =O14/N14 -> 4.2391304 | Q14: 2 | R14: =Q14/N14 -> 0.043478261 | T14: =(D14+N14)/($D$17+$N$17) -> 1 | U14: =D14/($D$17) -> 1 | V14: =N14/($N$17) -> 1 | X14: =($G14*('Scoring Format'!$B$2))+($I14*('Scoring Format'!$B$5))+($K14*('Scoring Format'!$B$8))+($O14*('Scoring Format'!$B$3))+($Q14*('Scoring Format'!$B$6)) -> 359.6 | Y14: =(($G14*('Scoring Format'!$B$2))+($I14*('Scoring Format'!$B$5))+($K14*('Scoring Format'!$B$8))+($O14*('Scoring Format'!$B$3))+($Q14*('Scoring Format'!$B$6)))*0.4 -> 143.84 | AD14: Murray, Kyler - ARI | AF14: 583 | AG14: 378 | AH14: =AG14/AF14 -> 0.6483705 | AI14: 4072 | AJ14: =AI14/AF14 -> 6.9845626 | AK14: 27 | AL14: =AK14/AF14 -> 0.046312178 | AM14: 11 | AN14: =AM14/AF14 -> 0.018867925 | AP14: 100 | AQ14: 590 | AR14: =AQ14/AP14 -> 5.9 | AS14: 5 | AT14: =AS14/AP14 -> 0.05 | AV14: =(AF14+AP14)/(AF17+AP17) -> 1 | AW14: =AF14/(AP14+AF14) -> 0.85358712 | AX14: =AP14/(AF14+AP14) -> 0.14641288 | AZ14: =((AI14*0.05)+(AK14*4)+(AM14*-1)+(AQ14*0.1)+(AS14*6))*0.55 -> 214.28 | BA14: =((AI14*0.05)+(AK14*4)+(AM14*-1)+(AQ14*0.1)+(AS14*6))*0.4 -> 155.84
A15: QB*Minshew, Gardner - ARI | B15: 30 | F15: =E15/D15 -> #DIV/0! | H15: =G15/D15 -> #DIV/0! | J15: =I15/D15 -> #DIV/0! | L15: =K15/D15 -> #DIV/0! | P15: =O15/N15 -> #DIV/0! | R15: =Q15/N15 -> #DIV/0! | T15: =(D15+N15)/($D$17+$N$17) -> 0 | U15: =D15/($D$17) -> 0 | V15: =N15/($N$17) -> 0 | X15: =($G15*('Scoring Format'!$B$2))+($I15*('Scoring Format'!$B$5))+($K15*('Scoring Format'!$B$8))+($O15*('Scoring Format'!$B$3))+($Q15*('Scoring Format'!$B$6)) -> 0 | Y15: =(($G15*('Scoring Format'!$B$2))+($I15*('Scoring Format'!$B$5))+($K15*('Scoring Format'!$B$8))+($O15*('Scoring Format'!$B$3))+($Q15*('Scoring Format'!$B$6)))*0.4 -> 0 | AD15: McCoy, Colt - ARI | AF15: 0 | AG15: 0 | AH15: 0 | AI15: 0 | AK15: 0 | AL15: =AK15/AF15 -> #DIV/0! | AM15: 0 | AN15: =AM15/AF15 -> #DIV/0! | AP15: 0 | AQ15: 0 | AS15: 0 | AT15: =AS15/AP15 -> #DIV/0! | AV15: =(AF15+AP15)/(AE18+AO18) -> #DIV/0! | AW15: =AF15/(AP15+AF15) -> #DIV/0! | AX15: =AP15/(AF15+AP15) -> #DIV/0!
A16: QB*Beck, Carson - ARI | B16: 24 | F16: =E16/D16 -> #DIV/0! | H16: =G16/D16 -> #DIV/0! | J16: =I16/D16 -> #DIV/0! | L16: =K16/D16 -> #DIV/0! | P16: =O16/N16 -> #DIV/0! | R16: =Q16/N16 -> #DIV/0! | T16: =(D16+N16)/($D$17+$N$17) -> 0 | U16: =D16/($D$17) -> 0 | V16: =N16/($N$17) -> 0 | X16: =($G16*('Scoring Format'!$B$2))+($I16*('Scoring Format'!$B$5))+($K16*('Scoring Format'!$B$8))+($O16*('Scoring Format'!$B$3))+($Q16*('Scoring Format'!$B$6)) -> 0 | Y16: =(($G16*('Scoring Format'!$B$2))+($I16*('Scoring Format'!$B$5))+($K16*('Scoring Format'!$B$8))+($O16*('Scoring Format'!$B$3))+($Q16*('Scoring Format'!$B$6)))*0.4 -> 0 | AD16: Streveler, Chris - ARI | AH16: =AG16/AF16 -> #DIV/0! | AJ16: =AI16/AF16 -> #DIV/0! | AL16: =AK16/AF16 -> #DIV/0! | AN16: =AM16/AF16 -> #DIV/0! | AR16: =AQ16/AP16 -> #DIV/0! | AT16: =AS16/AP16 -> #DIV/0! | AV16: =(AF16+AP16)/(AE20+AO20) -> #DIV/0! | AW16: =AF16/(AP16+AF16) -> #DIV/0! | AX16: =AP16/(AF16+AP16) -> #DIV/0! | AZ16: =((AI16*0.05)+(AK16*4)+(AM16*-1)+(AQ16*0.1)+(AS16*6))*0.55 -> 0 | BA16: =((AI16*0.05)+(AK16*4)+(AM16*-1)+(AQ16*0.1)+(AS16*6))*0.4 -> 0
A17: Total | D17: =SUM(D14:D16) -> 592 | E17: =SUM(E14:E16) -> 403 | G17: =SUM(G14:G16) -> 4542 | I17: =SUM(I14:I16) -> 28 | K17: =SUM(K14:K16) -> 11 | N17: =SUM(N14:N16) -> 46 | O17: =SUM(O14:O16) -> 195 | Q17: =SUM(Q14:Q16) -> 2 | T17: =T14+T15+T16 -> 1 | U17: =D17/(D17+N17) -> 0.92789969 | V17: =N17/(N17+D17) -> 0.072100313 | AD17: Total | AF17: =SUM(AF14:AF16) -> 583 | AG17: =SUM(AG14:AG16) -> 378 | AI17: =SUM(AI14:AI16) -> 4072 | AK17: =SUM(AK14:AK16) -> 27 | AM17: =SUM(AM14:AM16) -> 11 | AP17: =SUM(AP14:AP16) -> 100 | AQ17: =SUM(AQ14:AQ16) -> 590 | AS17: =SUM(AS14:AS16) -> 5 | AV17: =AV14+AV15+AV16 -> #DIV/0! | AW17: =AF17/(AF17+AP17) -> 0.85358712 | AX17: =AP17/(AP17+AF17) -> 0.14641288
A20: Rushing | I20: Receiving | S20: Touches | W20: Fantasy Points | AD20: Rushing | AK20: Receiving | AU20: Touches | AY20: Fantasy Points
A21: RB | B21: Age | C21: G | D21: Att | E21: Yards | F21: Yds/Att | G21: TDs | H21: TDs/Att | J21: Catch % | K21: Targets | L21: Rec | M21: Yds | N21: Yds/Rec | O21: TDs | P21: TDs/Rec | S21: RB | T21: Touch % | U21: Pct Pass | V21: Pct Run | X21: Fpts | Y21: PPR Fpts | Z21: .5 PPR | AD21: RB | AE21: G | AF21: Att | AG21: Yards | AH21: Yds/Att | AI21: TDs | AJ21: TDs/Att | AL21: Catch % | AM21: Targets | AN21: Rec | AO21: Yds | AP21: Yds/Rec | AQ21: TDs | AR21: TDs/Rec | AV21: Touch % | AW21: Pct Pass | AX21: Pct Run | AZ21: Fpts | BA21: PPR Fpts
A22: RB*Conner, James - ARI | B22: 31 | F22: =E22/D22 -> #DIV/0! | H22: =G22/D22 -> #DIV/0! | J22: =L22/K22 -> #DIV/0! | N22: =M22/L22 -> #DIV/0! | P22: =O22/L22 -> #DIV/0! | S22: Conner, James - ARI | T22: =(D22+K22)/($D$27+$K$27+$N$17+$E$17+$L$38+$L$47) -> 0 | U22: =K22/($K$27+$F$38+$F$47) -> 0 | V22: =D22/($D$27+$N$17+$L$38+$L$47) -> 0 | X22: =($E22*('Scoring Format'!$B$3))+($G22*('Scoring Format'!$B$6))+($M22*('Scoring Format'!$B$4))+($O22*('Scoring Format'!$B$7)) -> 0 | Y22: =($E22*('Scoring Format'!$B$3))+($G22*('Scoring Format'!$B$6))+(L22*1)+($M22*('Scoring Format'!$B$4))+($O22*('Scoring Format'!$B$7)) -> 0 | Z22: =($E22*('Scoring Format'!$B$3))+($G22*('Scoring Format'!$B$6))+(L22*0.5)+($M22*('Scoring Format'!$B$4))+($O22*('Scoring Format'!$B$7)) -> 0 | AD22: Conner, James - ARI | AF22: 200 | AG22: 1040 | AH22: =AG22/AF22 -> 5.2 | AI22: 7 | AJ22: =AI22/AF22 -> 0.035 | AL22: =AN22/AM22 -> 0.8 | AM22: 70 | AN22: 56 | AO22: 364 | AP22: =AO22/AN22 -> 6.5 | AQ22: 2 | AR22: =AQ22/AN22 -> 0.035714286 | AV22: =(#REF!+AM22)/(#REF!+AM25) -> #REF! | AW22: =#REF!/(AM22+#REF!) -> #REF! | AX22: =AM22/(#REF!+AM22) -> #REF! | AZ22: =(#REF!*0.1)+(AF22*6)+(AL22*0.1)+(AN22*6) -> #REF! | BA22: =(#REF!*0.1)+(AF22*6)+(AK22*1)+(AL22*0.1)+(AN22*6) -> #REF!
A23: RB*Benson, Trey - ARI | B23: 24 | F23: =E23/D23 -> #DIV/0! | H23: =G23/D23 -> #DIV/0! | J23: =L23/K23 -> #DIV/0! | N23: =M23/L23 -> #DIV/0! | P23: =O23/L23 -> #DIV/0! | S23: Benson, Trey - ARI | T23: =(D23+K23)/($D$27+$K$27+$N$17+$E$17+$L$38+$L$47) -> 0 | U23: =K23/($K$27+$F$38+$F$47) -> 0 | V23: =D23/($D$27+$N$17+$L$38+$L$47) -> 0 | X23: =($E23*('Scoring Format'!$B$3))+($G23*('Scoring Format'!$B$6))+($M23*('Scoring Format'!$B$4))+($O23*('Scoring Format'!$B$7)) -> 0 | Y23: =($E23*('Scoring Format'!$B$3))+($G23*('Scoring Format'!$B$6))+(L23*1)+($M23*('Scoring Format'!$B$4))+($O23*('Scoring Format'!$B$7)) -> 0 | Z23: =($E23*('Scoring Format'!$B$3))+($G23*('Scoring Format'!$B$6))+(L23*0.5)+($M23*('Scoring Format'!$B$4))+($O23*('Scoring Format'!$B$7)) -> 0 | AD23: Edmonds, Chase - ARI | AF23: 96 | AG23: 445 | AH23: =AG23/AF23 -> 4.6354167 | AI23: 6 | AJ23: =AI23/AF23 -> 0.0625 | AL23: =AN23/AM23 -> 0.58333333 | AM23: 24 | AN23: 14 | AO23: 110 | AP23: =AO23/AN23 -> 7.8571429 | AQ23: 2 | AR23: =AQ23/AN23 -> 0.14285714 | AV23: =(#REF!+AM23)/(#REF!+AM26) -> #REF! | AW23: =#REF!/(AM23+#REF!) -> #REF! | AX23: =AM23/(#REF!+AM23) -> #REF! | AZ23: =(#REF!*0.1)+(AF23*6)+(AL23*0.1)+(AN23*6) -> #REF! | BA23: =(#REF!*0.1)+(AF23*6)+(AK23*1)+(AL23*0.1)+(AN23*6) -> #REF!
A24: RB*Love, Jeremiyah - ARI | B24: 21 | C24: 17 | D24: 210 | E24: 900 | F24: =E24/D24 -> 4.2857143 | G24: 5 | H24: =G24/D24 -> 0.023809524 | J24: =L24/K24 -> 0.75609756 | K24: 82 | L24: 62 | M24: 482 | N24: =M24/L24 -> 7.7741935 | O24: 2 | P24: =O24/L24 -> 0.032258065 | S24: Love, Jeremiyah - ARI | T24: =(D24+K24)/($D$27+$K$27+$N$17+$E$17+$L$38+$L$47) -> 0.32336656 | U24: =K24/($K$27+$F$38+$F$47) -> 0.18894009 | V24: =D24/($D$27+$N$17+$L$38+$L$47) -> 0.54973822 | X24: =($E24*('Scoring Format'!$B$3))+($G24*('Scoring Format'!$B$6))+($M24*('Scoring Format'!$B$4))+($O24*('Scoring Format'!$B$7)) -> 180.2 | Y24: =($E24*('Scoring Format'!$B$3))+($G24*('Scoring Format'!$B$6))+(L24*1)+($M24*('Scoring Format'!$B$4))+($O24*('Scoring Format'!$B$7)) -> 242.2 | Z24: =($E24*('Scoring Format'!$B$3))+($G24*('Scoring Format'!$B$6))+(L24*0.5)+($M24*('Scoring Format'!$B$4))+($O24*('Scoring Format'!$B$7)) -> 211.2 | AD24: Benjamin, Eno - ARI | AF24: 8 | AG24: 28 | AH24: =AG24/AF24 -> 3.5 | AI24: 0 | AJ24: =AI24/AF24 -> 0 | AL24: =AN24/AM24 -> 0.5 | AM24: 4 | AN24: 2 | AO24: 17 | AP24: =AO24/AN24 -> 8.5 | AQ24: 0 | AR24: =AQ24/AN24 -> 0 | AV24: =(#REF!+AM24)/(#REF!+AL30) -> #REF! | AW24: =#REF!/(AM24+#REF!) -> #REF! | AX24: =AM24/(#REF!+AM24) -> #REF! | AZ24: =(#REF!*0.1)+(AF24*6)+(AL24*0.1)+(AN24*6) -> #REF! | BA24: =(#REF!*0.1)+(AF24*6)+(AK24*1)+(AL24*0.1)+(AN24*6) -> #REF!
A25: RB*Allgeier, Tyler - ARI | B25: 26 | C25: 17 | D25: 100 | E25: 360 | F25: =E25/D25 -> 3.6 | G25: 5 | H25: =G25/D25 -> 0.05 | J25: =L25/K25 -> 0.73333333 | K25: 15 | L25: 11 | M25: 70 | N25: =M25/L25 -> 6.3636364 | O25: 0 | P25: =O25/L25 -> 0 | S25: Allgeier, Tyler - ARI | T25: =(D25+K25)/($D$27+$K$27+$N$17+$E$17+$L$38+$L$47) -> 0.12735327 | U25: =K25/($K$27+$F$38+$F$47) -> 0.034562212 | V25: =D25/($D$27+$N$17+$L$38+$L$47) -> 0.2617801 | X25: =($E25*('Scoring Format'!$B$3))+($G25*('Scoring Format'!$B$6))+($M25*('Scoring Format'!$B$4))+($O25*('Scoring Format'!$B$7)) -> 73 | Y25: =($E25*('Scoring Format'!$B$3))+($G25*('Scoring Format'!$B$6))+(L25*1)+($M25*('Scoring Format'!$B$4))+($O25*('Scoring Format'!$B$7)) -> 84 | Z25: =($E25*('Scoring Format'!$B$3))+($G25*('Scoring Format'!$B$6))+(L25*0.5)+($M25*('Scoring Format'!$B$4))+($O25*('Scoring Format'!$B$7)) -> 78.5 | AD25: Ward, Jonathan - ARI | AH25: =AG25/AF25 -> #DIV/0! | AI25: 0 | AJ25: =AI25/AF25 -> #DIV/0! | AL25: =AN25/AM25 -> #DIV/0! | AP25: =AO25/AN25 -> #DIV/0! | AQ25: 0 | AR25: =AQ25/AN25 -> #DIV/0! | AV25: =(#REF!+AM25)/(#REF!+AM31) -> #REF! | AW25: =#REF!/(AM25+#REF!) -> #REF! | AX25: =AM25/(#REF!+AM25) -> #REF! | AZ25: =(#REF!*0.1)+(AF25*6)+(AL25*0.1)+(AN25*6) -> #REF! | BA25: =(#REF!*0.1)+(AF25*6)+(AK25*1)+(AL25*0.1)+(AN25*6) -> #REF!
A26: RB*Knight, Bam - ARI | B26: 25 | C26: 12 | D26: 21 | E26: 72 | F26: =E26/D26 -> 3.4285714 | G26: 0 | H26: =G26/D26 -> 0 | J26: =L26/K26 -> 0.66666667 | K26: 21 | L26: 14 | M26: 99 | N26: =M26/L26 -> 7.0714286 | O26: 1 | P26: =O26/L26 -> 0.071428571 | S26: Knight, Bam - ARI | T26: =(D26+K26)/($D$27+$K$27+$N$17+$E$17+$L$38+$L$47) -> 0.046511628 | U26: =K26/($K$27+$F$38+$F$47) -> 0.048387097 | V26: =D26/($D$27+$N$17+$L$38+$L$47) -> 0.054973822 | X26: =($E26*('Scoring Format'!$B$3))+($G26*('Scoring Format'!$B$6))+($M26*('Scoring Format'!$B$4))+($O26*('Scoring Format'!$B$7)) -> 23.1 | Y26: =($E26*('Scoring Format'!$B$3))+($G26*('Scoring Format'!$B$6))+(L26*1)+($M26*('Scoring Format'!$B$4))+($O26*('Scoring Format'!$B$7)) -> 37.1 | Z26: =($E26*('Scoring Format'!$B$3))+($G26*('Scoring Format'!$B$6))+(L26*0.5)+($M26*('Scoring Format'!$B$4))+($O26*('Scoring Format'!$B$7)) -> 30.1 | AD26: Feaster, Tavien - ARI | AH26: =AG26/AF26 -> #DIV/0! | AJ26: =AI26/AF26 -> #DIV/0! | AL26: =AN26/AM26 -> #DIV/0! | AQ26: =(AG26*0.1)+(AI26*6)+(AN26*0.1)+(AP26*6) -> 0 | AR26: =AQ26/AN26 -> #DIV/0! | AV26: =(#REF!+AM26)/(#REF!+AM32) -> #REF! | AW26: =#REF!/(AM26+#REF!) -> #REF! | AX26: =AM26/(#REF!+AM26) -> #REF! | AZ26: =(#REF!*0.1)+(AF26*6)+(AJ26*1)+(AK26*0.1)+(AM26*6) -> #REF! | BA26: =(#REF!*0.1)+(AF26*6)+(AK26*1)+(AL26*0.1)+(AN26*6) -> #REF!
A27: Total | D27: =SUM(D22:D26) -> 331 | E27: =SUM(E22:E26) -> 1332 | G27: =SUM(G22:G26) -> 10 | K27: =SUM(K22:K26) -> 118 | L27: =SUM(L22:L26) -> 87 | M27: =SUM(M22:M26) -> 651 | O27: =SUM(O22:O26) -> 3 | AD27: Total | AF27: =SUM(AF22:AF26) -> 304 | AG27: =SUM(AG22:AG26) -> 1513 | AI27: =SUM(AI22:AI26) -> 13 | AM27: =SUM(AM22:AM26) -> 98 | AN27: =SUM(AN22:AN26) -> 72 | AO27: =SUM(AO22:AO26) -> 491 | AQ27: =SUM(AQ22:AQ26) -> 4
B29: 200
A30: Receiving | K30: Rushing | S30: Touches | W30: Fantasy Points | AD30: Receiving | AM30: Rushing | AU30: Touches | AY30: Fantasy Points
A31: WRs | B31: Age | C31: G | D31: Catch % | E31: Targets | F31: Rec | G31: Yds | H31: Yds/Rec | I31: TDs | J31: TDs/Rec | L31: Ratt | M31: Ryds | N31: Ryds/Att | O31: RTds | P31: TDs/Att | S31: WRs | T31: Touch % | U31: Pct Pass | V31: Pct Run | X31: Fpts | Y31: PPR Fpts | Z31: .5PPR | AD31: WRs | AE31: G | AF31: Catch % | AG31: Targets | AH31: Rec | AI31: Yds | AJ31: Yds/Rec | AK31: TDs | AL31: TDs/Rec | AN31: Ratt | AO31: Ryds | AP31: Ryds/Att | AQ31: RTds | AR31: TDs/Att | AV31: Touch % | AW31: Pct Pass | AX31: Pct Run | AZ31: Fpts | BA31: PPR Fpts
A32: WR*Harrison, Marvin - ARI | B32: 24 | C32: 17 | D32: =F32/E32 -> 0.57575758 | E32: 99 | F32: 57 | G32: 837 | H32: =G32/F32 -> 14.684211 | I32: 6 | J32: =I32/F32 -> 0.10526316 | L32: 0 | M32: 0 | N32: =M32/L32 -> #DIV/0! | O32: 0 | P32: =O32/L32 -> #DIV/0! | S32: Harrison, Marvin | T32: =(E32+L32)/($D$27+$L$27+$N$17+$E$47+$L$47) -> 0.15420561 | U32: =E32/($E$17) -> 0.24565757 | V32: =L32/($N$17+$D$27+$L$38+$L$47) -> 0 | X32: =($G32*('Scoring Format'!$B$4))+($I32*'Scoring Format'!$B$7)+($M32*('Scoring Format'!$B$3))+($O32*('Scoring Format'!$B$6)) -> 119.7 | Y32: =(F32*1)+(($G32*('Scoring Format'!$B$4))+($I32*'Scoring Format'!$B$7)+($M32*('Scoring Format'!$B$3))+($O32*('Scoring Format'!$B$6))) -> 176.7 | Z32: =(F32*0.5)+(($G32*('Scoring Format'!$B$4))+($I32*'Scoring Format'!$B$7)+($M32*('Scoring Format'!$B$3))+($O32*('Scoring Format'!$B$6))) -> 148.2 | AD32: Green, A.J. - ARI | AF32: =AH32/AG32 -> 0.60747664 | AG32: 107 | AH32: 65 | AI32: 710 | AJ32: =AI32/AH32 -> 10.923077 | AK32: 6 | AL32: =AK32/AH32 -> 0.092307692 | AN32: 0 | AO32: 0 | AP32: =AO32/AN32 -> #DIV/0! | AQ32: 0 | AR32: =AQ32/AN32 -> #DIV/0! | AV32: =(#REF!+AK32)/(#REF!+AK35) -> #REF! | AW32: =#REF!/(AK32+#REF!) -> #REF! | AX32: =AK32/(#REF!+AK32) -> #REF! | AZ32: =(AI32*0.1)+(AK32*6)+(AO32*0.1)+(AQ32*6) -> 107 | BA32: =(AH32*1)+(AI32*0.1)+(AK32*6)+(AO32*0.1)+(AQ32*6) -> 172
A33: WR*Wilson, Michael - ARI | B33: 26 | C33: 17 | D33: =F33/E33 -> 0.65034965 | E33: 143 | F33: 93 | G33: 1270 | H33: =G33/F33 -> 13.655914 | I33: 8 | J33: =I33/F33 -> 0.086021505 | L33: 0 | M33: 0 | N33: =M33/L33 -> #DIV/0! | O33: 0 | P33: =O33/L33 -> #DIV/0! | S33: Wilson, Michael - ARI | T33: =(E33+L33)/($D$27+$L$27+$N$17+$E$47+$L$47) -> 0.22274143 | U33: =E33/($E$17) -> 0.35483871 | V33: =L33/($N$17+$D$27+$L$38+$L$47) -> 0 | X33: =($G33*('Scoring Format'!$B$4))+($I33*'Scoring Format'!$B$7)+($M33*('Scoring Format'!$B$3))+($O33*('Scoring Format'!$B$6)) -> 175 | Y33: =(F33*1)+(($G33*('Scoring Format'!$B$4))+($I33*'Scoring Format'!$B$7)+($M33*('Scoring Format'!$B$3))+($O33*('Scoring Format'!$B$6))) -> 268 | Z33: =(F33*0.5)+(($G33*('Scoring Format'!$B$4))+($I33*'Scoring Format'!$B$7)+($M33*('Scoring Format'!$B$3))+($O33*('Scoring Format'!$B$6))) -> 221.5 | AD33: Kirk, Christian- ARI | AF33: =AH33/AG33 -> 0.63333333 | AG33: 120 | AH33: 76 | AI33: 892 | AJ33: =AI33/AH33 -> 11.736842 | AK33: 5 | AL33: =AK33/AH33 -> 0.065789474 | AN33: 12 | AO33: 108 | AP33: =AO33/AN33 -> 9 | AQ33: 0 | AR33: =AQ33/AN33 -> 0 | AV33: =(#REF!+AK33)/(#REF!+AK36) -> #REF! | AW33: =#REF!/(AK33+#REF!) -> #REF! | AX33: =AK33/(#REF!+AK33) -> #REF! | AZ33: =(AI33*0.1)+(AK33*6)+(AO33*0.1)+(AQ33*6) -> 130 | BA33: =(AH33*1)+(AI33*0.1)+(AK33*6)+(AO33*0.1)+(AQ33*6) -> 206
A34: WR*Bourne, Kendrick - ARI | B34: 30 | C34: 16 | D34: =F34/E34 -> 0.68292683 | E34: 41 | F34: 28 | G34: 420 | H34: =G34/F34 -> 15 | I34: 2 | J34: =I34/F34 -> 0.071428571 | N34: =M34/L34 -> #DIV/0! | O34: 0 | P34: =O34/L34 -> #DIV/0! | S34: Bourne, Kendrick - ARI | T34: =(E34+L34)/($D$27+$L$27+$N$17+$E$47+$L$47) -> 0.063862928 | U34: =E34/($E$17) -> 0.10173697 | V34: =L34/($N$17+$D$27+$L$38+$L$47) -> 0 | X34: =($G34*('Scoring Format'!$B$4))+($I34*'Scoring Format'!$B$7)+($M34*('Scoring Format'!$B$3))+($O34*('Scoring Format'!$B$6)) -> 54 | Y34: =(F34*1)+(($G34*('Scoring Format'!$B$4))+($I34*'Scoring Format'!$B$7)+($M34*('Scoring Format'!$B$3))+($O34*('Scoring Format'!$B$6))) -> 82 | Z34: =(F34*0.5)+(($G34*('Scoring Format'!$B$4))+($I34*'Scoring Format'!$B$7)+($M34*('Scoring Format'!$B$3))+($O34*('Scoring Format'!$B$6))) -> 68 | AD34: Isabella, Andy - ARI | AF34: =AH34/AG34 -> 0.55 | AG34: 40 | AH34: 22 | AI34: 325 | AJ34: =AI34/AH34 -> 14.772727 | AK34: 2 | AL34: =AK34/AH34 -> 0.090909091 | AN34: 5 | AO34: 20 | AP34: =AO34/AN34 -> 4 | AQ34: 0 | AR34: =AQ34/AN34 -> 0 | AV34: =(#REF!+AK34)/(#REF!+AK37) -> #REF! | AW34: =#REF!/(AK34+#REF!) -> #REF! | AX34: =AK34/(#REF!+AK34) -> #REF! | AZ34: =(AI34*0.1)+(AK34*6)+(AO34*0.1)+(AQ34*6) -> 46.5 | BA34: =(AH34*1)+(AI34*0.1)+(AK34*6)+(AO34*0.1)+(AQ34*6) -> 68.5
A35: WR*Duvernay, Devin - ARI | B35: 28 | C35: 17 | D35: =F35/E35 -> 0.5 | E35: 10 | F35: 5 | G35: 60 | H35: =G35/F35 -> 12 | I35: 0 | J35: =I35/F35 -> 0 | L35: 5 | M35: 18 | N35: =M35/L35 -> 3.6 | O35: 1 | P35: =O35/L35 -> 0.2 | S35: Duvernay, Devin - ARI | T35: =(E35+L35)/($D$27+$L$27+$N$17+$E$47+$L$47) -> 0.023364486 | U35: =E35/($E$17) -> 0.024813896 | V35: =L35/($N$17+$D$27+$L$38+$L$47) -> 0.013089005 | X35: =($G35*('Scoring Format'!$B$4))+($I35*'Scoring Format'!$B$7)+($M35*('Scoring Format'!$B$3))+($O35*('Scoring Format'!$B$6)) -> 13.8 | Y35: =(F35*1)+(($G35*('Scoring Format'!$B$4))+($I35*'Scoring Format'!$B$7)+($M35*('Scoring Format'!$B$3))+($O35*('Scoring Format'!$B$6))) -> 18.8 | Z35: =(F35*0.5)+(($G35*('Scoring Format'!$B$4))+($I35*'Scoring Format'!$B$7)+($M35*('Scoring Format'!$B$3))+($O35*('Scoring Format'!$B$6))) -> 16.3 | AD35: Hopkins, DeAndre - ARI | AF35: =AH35/AG35 -> 0.66206897 | AG35: 145 | AH35: 96 | AI35: 1098 | AJ35: =AI35/AH35 -> 11.4375 | AK35: 7 | AL35: =AK35/AH35 -> 0.072916667 | AN35: 0 | AO35: 0 | AP35: =AO35/AN35 -> #DIV/0! | AQ35: 0 | AR35: =AQ35/AN35 -> #DIV/0! | AV35: =(#REF!+AK35)/(#REF!+AK38) -> #REF! | AW35: =#REF!/(AK35+#REF!) -> #REF! | AX35: =AK35/(#REF!+AK35) -> #REF! | AZ35: =(AI35*0.1)+(AK35*6)+(AO35*0.1)+(AQ35*6) -> 151.8 | BA35: =(AH35*1)+(AI35*0.1)+(AK35*6)+(AO35*0.1)+(AQ35*6) -> 247.8
A36: WR*Weaver, Xavier - ARI | B36: 23 | C36: 17 | D36: =F36/E36 -> 0 | E36: 2 | F36: 0 | G36: 0 | H36: =G36/F36 -> #DIV/0! | I36: 0 | J36: =I36/F36 -> #DIV/0! | N36: =M36/L36 -> #DIV/0! | O36: 0 | P36: =O36/L36 -> #DIV/0! | S36: Weaver, Xavier - ARI | T36: =(E36+L36)/($D$27+$L$27+$N$17+$E$47+$L$47) -> 0.0031152648 | U36: =E36/($E$17) -> 0.0049627792 | V36: =L36/($N$17+$D$27+$L$38+$L$47) -> 0 | X36: =($G36*('Scoring Format'!$B$4))+($I36*'Scoring Format'!$B$7)+($M36*('Scoring Format'!$B$3))+($O36*('Scoring Format'!$B$6)) -> 0 | Y36: =(F36*1)+(($G36*('Scoring Format'!$B$4))+($I36*'Scoring Format'!$B$7)+($M36*('Scoring Format'!$B$3))+($O36*('Scoring Format'!$B$6))) -> 0 | Z36: =(F36*0.5)+(($G36*('Scoring Format'!$B$4))+($I36*'Scoring Format'!$B$7)+($M36*('Scoring Format'!$B$3))+($O36*('Scoring Format'!$B$6))) -> 0 | AD36: Johnson, KeeSean - ARI | AF36: =AH36/AG36 -> 0.6 | AG36: 10 | AH36: 6 | AI36: 100 | AJ36: =AI36/AH36 -> 16.666667 | AK36: 0 | AL36: =AK36/AH36 -> 0 | AN36: 0 | AO36: 0 | AP36: =AO36/AN36 -> #DIV/0! | AQ36: 0 | AR36: =AQ36/AN36 -> #DIV/0! | AV36: =(#REF!+AK36)/(#REF!+AJ41) -> #REF! | AW36: =#REF!/(AK36+#REF!) -> #REF! | AX36: =AK36/(#REF!+AK36) -> #REF! | AZ36: =(AI36*0.1)+(AK36*6)+(AO36*0.1)+(AQ36*6) -> 10 | BA36: =(AH36*1)+(AI36*0.1)+(AK36*6)+(AO36*0.1)+(AQ36*6) -> 16
A37: WR*Virgil, Reggie - ARI | B37: 22 | C37: 17 | D37: =F37/E37 -> 0 | E37: 1 | F37: 0 | G37: 0 | H37: =G37/F37 -> #DIV/0! | I37: 0 | J37: =I37/F37 -> #DIV/0! | N37: =M37/L37 -> #DIV/0! | O37: 0 | P37: =O37/L37 -> #DIV/0! | S37: Virgil, Reggie - ARI | T37: =(E37+L37)/($D$27+$L$27+$N$17+$E$47+$L$47) -> 0.0015576324 | U37: =E37/($E$17) -> 0.0024813896 | V37: =L37/($N$17+$D$27+$L$38+$L$47) -> 0 | X37: =($G37*('Scoring Format'!$B$4))+($I37*'Scoring Format'!$B$7)+($M37*('Scoring Format'!$B$3))+($O37*('Scoring Format'!$B$6)) -> 0 | Y37: =(F37*1)+(($G37*('Scoring Format'!$B$4))+($I37*'Scoring Format'!$B$7)+($M37*('Scoring Format'!$B$3))+($O37*('Scoring Format'!$B$6))) -> 0 | Z37: =(F37*0.5)+(($G37*('Scoring Format'!$B$4))+($I37*'Scoring Format'!$B$7)+($M37*('Scoring Format'!$B$3))+($O37*('Scoring Format'!$B$6))) -> 0 | AD37: Moore, Rondale - ARI | AF37: =AH37/AG37 -> #DIV/0! | AL37: =AK37/AH37 -> #DIV/0! | AP37: =AO37/AN37 -> #DIV/0! | AR37: =AQ37/AN37 -> #DIV/0! | AV37: =(#REF!+AK37)/(#REF!+AK42) -> #REF! | AW37: =#REF!/(AK37+#REF!) -> #REF! | AX37: =AK37/(#REF!+AK37) -> #REF!
A38: Total | E38: =SUM(E32:E37) -> 296 | F38: =SUM(F32:F37) -> 183 | G38: =SUM(G32:G37) -> 2587 | I38: =SUM(I32:I37) -> 16 | L38: =SUM(L32:L37) -> 5 | M38: =SUM(M32:M37) -> 18 | O38: =SUM(O32:O37) -> 1 | AD38: Total | AG38: =SUM(AG32:AG37) -> 422 | AH38: =SUM(AH32:AH37) -> 265 | AI38: =SUM(AI32:AI37) -> 3125 | AK38: =SUM(AK32:AK37) -> 20 | AN38: =SUM(AN32:AN37) -> 17 | AO38: =SUM(AO32:AO37) -> 128 | AQ38: =SUM(AQ32:AQ37) -> 0
S39: Weaver, Xavier - ARI
A41: Receiving | K41: Rushing | S41: Touches | W41: Fantasy Points | AD41: Receiving | AM41: Rushing | AU41: Touches | AY41: Fantasy Points
A42: Tes | B42: Age | C42: G | D42: Catch % | E42: Targets | F42: Rec | G42: Yds | H42: Yds/Rec | I42: TDs | J42: TDs/Rec | L42: Ratt | M42: Ryds | N42: Ryds/Att | O42: RTDs | P42: TDs/Att | S42: Tes | T42: Touch % | U42: Pct Pass | V42: Pct Run | X42: Fpts | Y42: PPR Fpts | Z42: .5 PPR | AD42: Tes | AE42: G | AF42: Catch % | AG42: Targets | AH42: Rec | AI42: Yds | AJ42: Yds/Rec | AK42: TDs | AL42: TDs/Rec | AN42: Ratt | AO42: Ryds | AP42: Ryds/Att | AQ42: RTDs | AR42: TDs/Att | AV42: Touch % | AW42: Pct Pass | AX42: Pct Run | AZ42: Fpts | BA42: PPR Fpts
A43: TE*McBride, Trey - ARI | B43: 26 | C43: 17 | D43: =F43/E43 -> 0.75316456 | E43: 158 | F43: 119 | G43: 1193 | H43: =G43/F43 -> 10.02521 | I43: 8 | J43: =I43/F43 -> 0.067226891 | L43: 0 | M43: 0 | N43: 0 | O43: 0 | P43: =O43/L43 -> #DIV/0! | S43: McBride, Trey - ARI | T43: =(E43+L43)/($E$47+$L$47+$E$38+$L$38+$K$27+$D$27+$N$17) -> 0.16221766 | U43: =E43/($E$47+$E$38+$K$27) -> 0.26689189 | V43: =L43/($L$47+$L$38+$D$27+$N$17) -> 0 | X43: =($G43*('Scoring Format'!$B$4))+($I43*'Scoring Format'!$B$7)+($M43*('Scoring Format'!$B$3))+($O43*('Scoring Format'!$B$6)) -> 167.3 | Y43: =(F43*1)+(($G43*('Scoring Format'!$B$4))+($I43*'Scoring Format'!$B$7)+($M43*('Scoring Format'!$B$3))+($O43*('Scoring Format'!$B$6))) -> 286.3 | Z43: =(F43*0.5)+(($G43*('Scoring Format'!$B$4))+($I43*'Scoring Format'!$B$7)+($M43*('Scoring Format'!$B$3))+($O43*('Scoring Format'!$B$6))) -> 226.8 | AD43: Williams, Maxx - ARI | AF43: =AH43/AG43 -> 0.5625 | AG43: 16 | AH43: 9 | AI43: 108 | AJ43: =AI43/AH43 -> 12 | AK43: 1 | AL43: =AK43/AH43 -> 0.11111111 | AN43: 0 | AO43: 0 | AP43: 0 | AQ43: 0 | AR43: =AQ43/AN43 -> #DIV/0! | AV43: =(#REF!+AK43)/(#REF!+AK46) -> #REF! | AW43: =#REF!/(AK43+#REF!) -> #REF! | AX43: =AK43/(#REF!+AK43) -> #REF! | AZ43: =(AI43*0.1)+(AK43*6)+(AO43*0.1)+(AQ43*6) -> 16.8 | BA43: =(AH43*1)+(AI43*0.1)+(AK43*6)+(AO43*0.1)+(AQ43*6) -> 25.8
A44: TE*Higgins, Elijah - ARI | B44: 26 | C44: 17 | D44: =F44/E44 -> 0.8 | E44: 10 | F44: 8 | G44: 72 | H44: =G44/F44 -> 9 | I44: 0 | J44: =I44/F44 -> 0 | L44: 0 | M44: 0 | N44: 0 | O44: 0 | P44: =O44/L44 -> #DIV/0! | S44: Higgins, Elijah - ARI | T44: =(E44+L44)/($E$47+$L$47+$E$38+$L$38+$K$27+$D$27+$N$17) -> 0.01026694 | U44: =E44/($E$47+$E$38+$K$27) -> 0.016891892 | V44: =L44/($L$47+$L$38+$D$27+$N$17) -> 0 | X44: =($G44*('Scoring Format'!$B$4))+($I44*'Scoring Format'!$B$7)+($M44*('Scoring Format'!$B$3))+($O44*('Scoring Format'!$B$6)) -> 7.2 | Y44: =(F44*1)+(($G44*('Scoring Format'!$B$4))+($I44*'Scoring Format'!$B$7)+($M44*('Scoring Format'!$B$3))+($O44*('Scoring Format'!$B$6))) -> 15.2 | Z44: =(F44*0.5)+(($G44*('Scoring Format'!$B$4))+($I44*'Scoring Format'!$B$7)+($M44*('Scoring Format'!$B$3))+($O44*('Scoring Format'!$B$6))) -> 11.2 | AD44: Daniels, Darenell - ARI | AF44: =AH44/AG44 -> 0.74285714 | AG44: 35 | AH44: 26 | AI44: 283 | AJ44: =AI44/AH44 -> 10.884615 | AK44: 2 | AL44: =AK44/AH44 -> 0.076923077 | AN44: 0 | AO44: 0 | AP44: 0 | AQ44: 0 | AR44: =AQ44/AN44 -> #DIV/0! | AV44: =(#REF!+AK44)/(#REF!+AK47) -> #REF! | AW44: =#REF!/(AK44+#REF!) -> #REF! | AX44: =AK44/(#REF!+AK44) -> #REF! | AZ44: =(AI44*0.1)+(AK44*6)+(AO44*0.1)+(AQ44*6) -> 40.3 | BA44: =(AH44*1)+(AI44*0.1)+(AK44*6)+(AO44*0.1)+(AQ44*6) -> 66.3
A45: TE*Reiman, Tip - ARI | B45: 25 | C45: 17 | D45: =F45/E45 -> 0.6 | E45: 10 | F45: 6 | G45: 39 | H45: =G45/F45 -> 6.5 | I45: 1 | J45: =I45/F45 -> 0.16666667 | L45: 0 | M45: 0 | N45: 0 | O45: 0 | P45: =O45/L45 -> #DIV/0! | S45: Reiman, Tip - ARI | T45: =(E45+L45)/($E$47+$L$47+$E$38+$L$38+$K$27+$D$27+$N$17) -> 0.01026694 | U45: =E45/($E$47+$E$38+$K$27) -> 0.016891892 | V45: =L45/($L$47+$L$38+$D$27+$N$17) -> 0 | X45: =($G45*('Scoring Format'!$B$4))+($I45*'Scoring Format'!$B$7)+($M45*('Scoring Format'!$B$3))+($O45*('Scoring Format'!$B$6)) -> 9.9 | Y45: =(F45*1)+(($G45*('Scoring Format'!$B$4))+($I45*'Scoring Format'!$B$7)+($M45*('Scoring Format'!$B$3))+($O45*('Scoring Format'!$B$6))) -> 15.9 | Z45: =(F45*0.5)+(($G45*('Scoring Format'!$B$4))+($I45*'Scoring Format'!$B$7)+($M45*('Scoring Format'!$B$3))+($O45*('Scoring Format'!$B$6))) -> 12.9 | AD45: Bunting, Ian - ARI | AF45: =AH45/AG45 -> 0.5 | AG45: 12 | AH45: 6 | AI45: 65 | AJ45: =AI45/AH45 -> 10.833333 | AK45: 0 | AL45: =AK45/AH45 -> 0 | AN45: 0 | AO45: 0 | AP45: 0 | AQ45: 0 | AR45: =AQ45/AN45 -> #DIV/0! | AV45: =(#REF!+AK45)/(#REF!+AJ49) -> #REF! | AW45: =#REF!/(AK45+#REF!) -> #REF! | AX45: =AK45/(#REF!+AK45) -> #REF! | AZ45: =(AI45*0.1)+(AK45*6)+(AO45*0.1)+(AQ45*6) -> 6.5 | BA45: =(AH45*1)+(AI45*0.1)+(AK45*6)+(AO45*0.1)+(AQ45*6) -> 12.5
A46: TE*Quitoriano, Teegan - ARI | B46: 26 | D46: =F46/E46 -> #DIV/0! | H46: =G46/F46 -> #DIV/0! | I46: 0 | J46: =I46/F46 -> #DIV/0! | L46: 0 | M46: 0 | N46: 0 | O46: 0 | P46: =O46/L46 -> #DIV/0! | S46: Quitoriano, Teegan - ARI | T46: =(E46+L46)/($E$47+$L$47+$E$38+$L$38+$K$27+$D$27+$N$17) -> 0 | U46: =E46/($E$47+$E$38+$K$27) -> 0 | V46: =L46/($L$47+$L$38+$D$27+$N$17) -> 0 | X46: =($G46*('Scoring Format'!$B$4))+($I46*'Scoring Format'!$B$7)+($M46*('Scoring Format'!$B$3))+($O46*('Scoring Format'!$B$6)) -> 0 | Y46: =(F46*1)+(($G46*('Scoring Format'!$B$4))+($I46*'Scoring Format'!$B$7)+($M46*('Scoring Format'!$B$3))+($O46*('Scoring Format'!$B$6))) -> 0 | Z46: =(F46*0.5)+(($G46*('Scoring Format'!$B$4))+($I46*'Scoring Format'!$B$7)+($M46*('Scoring Format'!$B$3))+($O46*('Scoring Format'!$B$6))) -> 0 | AF46: =AH46/AG46 -> #DIV/0! | AJ46: =AI46/AH46 -> #DIV/0! | AL46: =AK46/AH46 -> #DIV/0! | AQ46: 0 | AR46: =AQ46/AN46 -> #DIV/0! | AV46: =(#REF!+AK46)/(#REF!+AJ50) -> #REF! | AW46: =#REF!/(AK46+#REF!) -> #REF! | AX46: =AK46/(#REF!+AK46) -> #REF! | AZ46: =(AI46*0.1)+(AK46*6)+(AO46*0.1)+(AQ46*6) -> 0 | BA46: =(AH46*1)+(AI46*0.1)+(AK46*6)+(AO46*0.1)+(AQ46*6) -> 0
A47: Total | E47: =SUM(E43:E46) -> 178 | F47: =SUM(F43:F46) -> 133 | G47: =SUM(G43:G46) -> 1304 | I47: =SUM(I43:I46) -> 9 | L47: =SUM(L43:L46) -> 0 | M47: =SUM(M43:M46) -> 0 | O47: =SUM(O43:O46) -> 0 | AD47: Total | AG47: =SUM(AG43:AG46) -> 63 | AH47: =SUM(AH43:AH46) -> 41 | AI47: =SUM(AI43:AI46) -> 456 | AK47: =SUM(AK43:AK46) -> 3 | AN47: =SUM(AN43:AN46) -> 0 | AO47: =SUM(AO43:AO46) -> 0 | AQ47: =SUM(AQ43:AQ46) -> 0
A50: Team Totals and Splits | K50: Taxi Squad* | S50: Injured Reserve | AD50: Team Totals and Splits | AM50: Taxi Squad* | AU50: Injured Reserve
B51: Targets | C51: Rec. | D51: Yds | E51: TDs | J51: Player | N51: Position | R51: Player | V51: Position | AD51: Targets | AE51: Rec. | AF51: Yds | AG51: TDs | AL51: Player | AP51: Position | AT51: Player | AX51: Position
A52: Rec Totals* | B52: =SUM(K22:K26,E32:E37,E43:E46) -> 592 | C52: =SUM(F43:F46,F32:F37,L22:L26) -> 403 | D52: =SUM(G43:G46,G32:G37,M22:M26) -> 4542 | E52: =SUM(O22:O26,I32:I37,I43:I46) -> 28 | J52: Kedon Slovis | N52: QB | AC52: Rec Totals | AD52: =SUM(AM22:AM26,AG32:AG37,AG43:AG46) -> 583 | AE52: =SUM(AH43:AH46,AH32:AH37,AM22:AM26) -> 404 | AF52: =SUM(AI43:AI46,AI32:AI37,AN22:AN26) -> 3653 | AG52: =SUM(AQ22:AQ26,AK32:AK37,AK43:AK46) -> 27
A53: QB Totals | B53: =SUM(D17) -> 592 | C53: =SUM(E17) -> 403 | D53: =SUM(G17) -> 4542 | E53: =SUM(I17) -> 28 | J53: Corey Kiner | N53: RB | AC53: QB Totals | AD53: =SUM(AF17) -> 583 | AE53: =SUM(AG17) -> 378 | AF53: =SUM(AI17) -> 4072 | AG53: =SUM(AK17) -> 27
A54: League Att Avg. | J54: Simi Fehoko | N54: WR | AC54: League Att Avg.
J55: Jalen Brooks | N55: WR
B56: Att | C56: Yards | D56: TDs | J56: Evan Hull | N56: RB | AD56: Att | AE56: Yards | AF56: TDs
A57: Rush Totals | B57: =SUM(N14:N16,D22:D26,L32:L37,L43:L46) -> 382 | C57: =SUM(O14:O16,E22:E26,M32:M37,M43:M46) -> 1545 | D57: =SUM(Q14:Q16,G22:G26,O32:O37,O43:O46) -> 13 | J57: Harrison Wallace | N57: WR | AC57: Rush Totals | AD57: =SUM(AP14:AP16,AF22:AF26,AN32:AN37,AN43:AN46) -> 421 | AE57: =SUM(AQ14:AQ16,AG22:AG26,AO32:AO37,AO43:AO46) -> 2231 | AF57: =SUM(AS14:AS16,AI22:AI26,AQ32:AQ37,AQ43:AQ46) -> 18
A58: League Att Avg. | J58: Bryson Green | N58: WR | AC58: League Att Avg.
J59: Ihmir Smith-Marsette | N59: WR
B60: Run | C60: Pass | J60: Rivaldo Fairweather | N60: TE | AD60: Run | AE60: Pass
A61: Run/Pass Pct | B61: =B57/(B53+B57) -> 0.39219713 | C61: =B53/(B53+B57) -> 0.60780287 | J61: *Projected options during offseason/Actual options during the season. | AC61: Run/Pass Pct | AD61: =AD57/(AD53+AD57) -> 0.41932271 | AE61: =AD53/(AD53+AD57) -> 0.58067729 | AL61: *Projected options during offseason/Actual options during the season.
A62: League Average | J62: Kenny Yeboah | N62: TE | AC62: League Average
A73: Team Projections Menu
I75: RSP Projections: Year 1 | N75: Adjustable Projections: Year 1 | T75: Offense Distribution
I76: RSP Projections: Year 2 | N76: Past Run/Pass Performances | T76: Run | U76: Pass
T77: =(N87+D97+L108+L117)/(N87+D97+L108+D87) -> #DIV/0! | U77: =D87/(D87+N87+D97+L108+L117) -> #DIV/0!
A80: RSP Projections: Year 2
D82: Passing | M82: Rushing | S82: Touches | W82: Fantasy Points
A83: QB | B83: Age | C83: G | D83: Att | E83: Comp | F83: Pct | G83: Yards | H83: Yds/Att | I83: TDs | J83: TDs/Att | K83: Int | L83: Int/Att | N83: Ratt | O83: Ryds | P83: Ryds/Att | Q83: TDs | R83: Tds/Att | T83: Touch % | U83: Pct Pass | V83: Pct Run | X83: Fpts | Y83: Adjusted
F84: =E84/D84 -> #DIV/0! | H84: =G84/D84 -> #DIV/0! | J84: =I84/D84 -> #DIV/0! | L84: =K84/D84 -> #DIV/0! | P84: =O84/N84 -> #DIV/0! | R84: =Q84/N84 -> #DIV/0! | T84: =(D84+N84)/($D$17+$N$17) -> 0 | U84: =D84/($D$17) -> 0 | V84: =N84/($N$17) -> 0 | X84: =(G84*0.05)+(I84*4)+(K84*-1)+(O84*0.1)+(Q84*6) -> 0 | Y84: =((G84*0.05)+(I84*4)+(K84*-1)+(O84*0.1)+(Q84*6))*0.4 -> 0
F85: =E85/D85 -> #DIV/0! | H85: =G85/D85 -> #DIV/0! | J85: =I85/D85 -> #DIV/0! | L85: =K85/D85 -> #DIV/0! | P85: =O85/N85 -> #DIV/0! | R85: =Q85/N85 -> #DIV/0! | T85: =(D85+N85)/($D$17+$N$17) -> 0 | U85: =D85/($D$17) -> 0 | V85: =N85/($N$17) -> 0 | X85: =(G85*0.05)+(I85*4)+(K85*-1)+(O85*0.1)+(Q85*6) -> 0 | Y85: =((G85*0.05)+(I85*4)+(K85*-1)+(O85*0.1)+(Q85*6))*0.4 -> 0
F86: =E86/D86 -> #DIV/0! | H86: =G86/D86 -> #DIV/0! | J86: =I86/D86 -> #DIV/0! | L86: =K86/D86 -> #DIV/0! | P86: =O86/N86 -> #DIV/0! | Q86: 0 | R86: =Q86/N86 -> #DIV/0! | T86: =(D86+N86)/($D$17+$N$17) -> 0 | U86: =D86/($D$17) -> 0 | V86: =N86/($N$17) -> 0 | X86: =(G86*0.05)+(I86*4)+(K86*-1)+(O86*0.1)+(Q86*6) -> 0 | Y86: =((G86*0.05)+(I86*4)+(K86*-1)+(O86*0.1)+(Q86*6))*0.4 -> 0
A87: Total | D87: =SUM(D84:D86) -> 0 | E87: =SUM(E84:E86) -> 0 | G87: =SUM(G84:G86) -> 0 | I87: =SUM(I84:I86) -> 0 | K87: =SUM(K84:K86) -> 0 | N87: =SUM(N84:N86) -> 0 | O87: =SUM(O84:O86) -> 0 | Q87: =SUM(Q84:Q86) -> 0 | T87: =T84+T85+T86 -> 0 | U87: =D87/(D87+N87) -> #DIV/0! | V87: =N87/(N87+D87) -> #DIV/0!
A90: Rushing | I90: Receiving | S90: Touches | W90: Fantasy Points
A91: RB | B91: Age | C91: G | D91: Att | E91: Yards | F91: Yds/Att | G91: TDs | H91: TDs/Att | J91: Catch % | K91: Targets | L91: Rec | M91: Yds | N91: Yds/Rec | O91: TDs | P91: TDs/Rec | S91: RB | T91: Touch % | U91: Pct Pass | V91: Pct Run | X91: Fpts | Y91: PPR Fpts | Z91: .5 PPR
F92: =E92/D92 -> #DIV/0! | H92: =G92/D92 -> #DIV/0! | J92: =L92/K92 -> #DIV/0! | N92: =M92/L92 -> #DIV/0! | P92: =O92/L92 -> #DIV/0! | T92: =(D92+K92)/($D$27+$K$27+$N$17+$E$17+$L$38+$L$47) -> 0 | U92: =K92/($K$27+$F$38+$F$47) -> 0 | V92: =D92/($D$27+$N$17+$L$38+$L$47) -> 0 | X92: =(E92*0.1)+(G92*6)+(M92*0.1)+(O92*6) -> 0 | Y92: =(E92*0.1)+(G92*6)+(L92*1)+(M92*0.1)+(O92*6) -> 0 | Z92: =(E92*0.1)+(G92*6)+(L92*0.5)+(M92*0.1)+(O92*6) -> 0
F93: =E93/D93 -> #DIV/0! | H93: =G93/D93 -> #DIV/0! | J93: =L93/K93 -> #DIV/0! | N93: =M93/L93 -> #DIV/0! | P93: =O93/L93 -> #DIV/0! | T93: =(D93+K93)/($D$27+$K$27+$N$17+$E$17+$L$38+$L$47) -> 0 | U93: =K93/($K$27+$F$38+$F$47) -> 0 | V93: =D93/($D$27+$N$17+$L$38+$L$47) -> 0 | X93: =(E93*0.1)+(G93*6)+(M93*0.1)+(O93*6) -> 0 | Y93: =(E93*0.1)+(G93*6)+(L93*1)+(M93*0.1)+(O93*6) -> 0 | Z93: =(E93*0.1)+(G93*6)+(L93*0.5)+(M93*0.1)+(O93*6) -> 0
F94: =E94/D94 -> #DIV/0! | H94: =G94/D94 -> #DIV/0! | J94: =L94/K94 -> #DIV/0! | N94: =M94/L94 -> #DIV/0! | P94: =O94/L94 -> #DIV/0! | T94: =(D94+K94)/($D$27+$K$27+$N$17+$E$17+$L$38+$L$47) -> 0 | U94: =K94/($K$27+$F$38+$F$47) -> 0 | V94: =D94/($D$27+$N$17+$L$38+$L$47) -> 0 | X94: =(E94*0.1)+(G94*6)+(M94*0.1)+(O94*6) -> 0 | Y94: =(E94*0.1)+(G94*6)+(L94*1)+(M94*0.1)+(O94*6) -> 0 | Z94: =(E94*0.1)+(G94*6)+(L94*0.5)+(M94*0.1)+(O94*6) -> 0
F95: =E95/D95 -> #DIV/0! | H95: =G95/D95 -> #DIV/0! | J95: =L95/K95 -> #DIV/0! | N95: =M95/L95 -> #DIV/0! | P95: =O95/L95 -> #DIV/0! | T95: =(D95+K95)/($D$27+$K$27+$N$17+$E$17+$L$38+$L$47) -> 0 | U95: =K95/($K$27+$F$38+$F$47) -> 0 | V95: =D95/($D$27+$N$17+$L$38+$L$47) -> 0 | X95: =(E95*0.1)+(G95*6)+(M95*0.1)+(O95*6) -> 0 | Y95: =(E95*0.1)+(G95*6)+(L95*1)+(M95*0.1)+(O95*6) -> 0 | Z95: =(E95*0.1)+(G95*6)+(L95*0.5)+(M95*0.1)+(O95*6) -> 0
F96: =E96/D96 -> #DIV/0! | H96: =G96/D96 -> #DIV/0! | J96: =L96/K96 -> #DIV/0! | N96: =M96/L96 -> #DIV/0! | P96: =O96/L96 -> #DIV/0! | T96: =(D96+K96)/($D$27+$K$27+$N$17+$E$17+$L$38+$L$47) -> 0 | U96: =K96/($K$27+$F$38+$F$47) -> 0 | V96: =D96/($D$27+$N$17+$L$38+$L$47) -> 0 | X96: =(E96*0.1)+(G96*6)+(M96*0.1)+(O96*6) -> 0 | Y96: =(E96*0.1)+(G96*6)+(L96*1)+(M96*0.1)+(O96*6) -> 0 | Z96: =(E96*0.1)+(G96*6)+(L96*0.5)+(M96*0.1)+(O96*6) -> 0
A97: Total | D97: =SUM(D92:D96) -> 0 | E97: =SUM(E92:E96) -> 0 | G97: =SUM(G92:G96) -> 0 | K97: =SUM(K92:K96) -> 0 | L97: =SUM(L92:L96) -> 0 | M97: =SUM(M92:M96) -> 0 | O97: =SUM(O92:O96) -> 0
A100: Receiving | K100: Rushing | S100: Touches | W100: Fantasy Points
A101: WRs | B101: Age | C101: G | D101: Catch % | E101: Targets | F101: Rec | G101: Yds | H101: Yds/Rec | I101: TDs | J101: TDs/Rec | L101: Ratt | M101: Ryds | N101: Ryds/Att | O101: RTds | P101: TDs/Att | S101: WRs | T101: Touch % | U101: Pct Pass | V101: Pct Run | X101: Fpts | Y101: PPR Fpts | Z101: .5PPR
D102: =F102/E102 -> #DIV/0! | H102: =G102/F102 -> #DIV/0! | J102: =I102/F102 -> #DIV/0! | N102: =M102/L102 -> #DIV/0! | P102: =O102/L102 -> #DIV/0! | T102: =(E102+L102)/($D$27+$L$27+$N$17+$E$47+$L$47) -> 0 | U102: =E102/($E$17) -> 0 | V102: =L102/($N$17+$D$27+$L$38+$L$47) -> 0 | X102: =(G102*0.1)+(I102*6)+(M102*0.1)+(O102*6) -> 0 | Y102: =(F102*1)+(G102*0.1)+(I102*6)+(M102*0.1)+(O102*6) -> 0 | Z102: =(F102*0.5)+(G102*0.1)+(I102*6)+(M102*0.1)+(O102*6) -> 0
D103: =F103/E103 -> #DIV/0! | H103: =G103/F103 -> #DIV/0! | J103: =I103/F103 -> #DIV/0! | N103: =M103/L103 -> #DIV/0! | P103: =O103/L103 -> #DIV/0! | T103: =(E103+L103)/($D$27+$L$27+$N$17+$E$47+$L$47) -> 0 | U103: =E103/($E$17) -> 0 | V103: =L103/($N$17+$D$27+$L$38+$L$47) -> 0 | X103: =(G103*0.1)+(I103*6)+(M103*0.1)+(O103*6) -> 0 | Y103: =(F103*1)+(G103*0.1)+(I103*6)+(M103*0.1)+(O103*6) -> 0 | Z103: =(F103*0.5)+(G103*0.1)+(I103*6)+(M103*0.1)+(O103*6) -> 0
D104: =F104/E104 -> #DIV/0! | H104: =G104/F104 -> #DIV/0! | J104: =I104/F104 -> #DIV/0! | N104: =M104/L104 -> #DIV/0! | P104: =O104/L104 -> #DIV/0! | T104: =(E104+L104)/($D$27+$L$27+$N$17+$E$47+$L$47) -> 0 | U104: =E104/($E$17) -> 0 | V104: =L104/($N$17+$D$27+$L$38+$L$47) -> 0 | X104: =(G104*0.1)+(I104*6)+(M104*0.1)+(O104*6) -> 0 | Y104: =(F104*1)+(G104*0.1)+(I104*6)+(M104*0.1)+(O104*6) -> 0 | Z104: =(F104*0.5)+(G104*0.1)+(I104*6)+(M104*0.1)+(O104*6) -> 0
D105: =F105/E105 -> #DIV/0! | H105: =G105/F105 -> #DIV/0! | J105: =I105/F105 -> #DIV/0! | N105: =M105/L105 -> #DIV/0! | P105: =O105/L105 -> #DIV/0! | T105: =(E105+L105)/($D$27+$L$27+$N$17+$E$47+$L$47) -> 0 | U105: =E105/($E$17) -> 0 | V105: =L105/($N$17+$D$27+$L$38+$L$47) -> 0 | X105: =(G105*0.1)+(I105*6)+(M105*0.1)+(O105*6) -> 0 | Y105: =(F105*1)+(G105*0.1)+(I105*6)+(M105*0.1)+(O105*6) -> 0 | Z105: =(F105*0.5)+(G105*0.1)+(I105*6)+(M105*0.1)+(O105*6) -> 0
D106: =F106/E106 -> #DIV/0! | H106: =G106/F106 -> #DIV/0! | J106: =I106/F106 -> #DIV/0! | N106: =M106/L106 -> #DIV/0! | P106: =O106/L106 -> #DIV/0! | T106: =(E106+L106)/($D$27+$L$27+$N$17+$E$47+$L$47) -> 0 | U106: =E106/($E$17) -> 0 | V106: =L106/($N$17+$D$27+$L$38+$L$47) -> 0 | X106: =(G106*0.1)+(I106*6)+(M106*0.1)+(O106*6) -> 0 | Y106: =(F106*1)+(G106*0.1)+(I106*6)+(M106*0.1)+(O106*6) -> 0 | Z106: =(F106*0.5)+(G106*0.1)+(I106*6)+(M106*0.1)+(O106*6) -> 0
D107: =F107/E107 -> #DIV/0! | H107: =G107/F107 -> #DIV/0! | J107: =I107/F107 -> #DIV/0! | N107: =M107/L107 -> #DIV/0! | P107: =O107/L107 -> #DIV/0! | T107: =(E107+L107)/($D$27+$L$27+$N$17+$E$47+$L$47) -> 0 | U107: =E107/($E$17) -> 0 | V107: =L107/($N$17+$D$27+$L$38+$L$47) -> 0 | X107: =(G107*0.1)+(I107*6)+(M107*0.1)+(O107*6) -> 0 | Y107: =(F107*1)+(G107*0.1)+(I107*6)+(M107*0.1)+(O107*6) -> 0 | Z107: =(F107*0.5)+(G107*0.1)+(I107*6)+(M107*0.1)+(O107*6) -> 0
A108: Total | E108: =SUM(E102:E107) -> 0 | F108: =SUM(F102:F107) -> 0 | G108: =SUM(G102:G107) -> 0 | I108: =SUM(I102:I107) -> 0 | L108: =SUM(L102:L107) -> 0 | M108: =SUM(M102:M107) -> 0 | O108: =SUM(O102:O107) -> 0
A111: Receiving | K111: Rushing | S111: Touches | W111: Fantasy Points
A112: Tes | B112: Age | C112: G | D112: Catch % | E112: Targets | F112: Rec | G112: Yds | H112: Yds/Rec | I112: TDs | J112: TDs/Rec | L112: Ratt | M112: Ryds | N112: Ryds/Att | O112: RTDs | P112: TDs/Att | S112: Tes | T112: Touch % | U112: Pct Pass | V112: Pct Run | X112: Fpts | Y112: PPR Fpts | Z112: .5 PPR
D113: =F113/E113 -> #DIV/0! | H113: =G113/F113 -> #DIV/0! | I113: 9 | J113: =I113/F113 -> #DIV/0! | L113: 0 | M113: 0 | N113: 0 | O113: 0 | P113: =O113/L113 -> #DIV/0! | T113: =(E113+L113)/($E$47+$L$47+$E$38+$L$38+$K$27+$D$27+$N$17) -> 0 | U113: =E113/($E$47+$E$38+$K$27) -> 0 | V113: =L113/($L$47+$L$38+$D$27+$N$17) -> 0 | X113: =(G113*0.1)+(I113*6)+(M113*0.1)+(O113*6) -> 54 | Y113: =(F113*1)+(G113*0.1)+(I113*6)+(M113*0.1)+(O113*6) -> 54 | Z113: =(F113*0.5)+(G113*0.1)+(I113*6)+(M113*0.1)+(O113*6) -> 54
D114: =F114/E114 -> #DIV/0! | H114: =G114/F114 -> #DIV/0! | I114: 0 | J114: =I114/F114 -> #DIV/0! | L114: 0 | M114: 0 | N114: 0 | O114: 0 | P114: =O114/L114 -> #DIV/0! | T114: =(E114+L114)/($E$47+$L$47+$E$38+$L$38+$K$27+$D$27+$N$17) -> 0 | U114: =E114/($E$47+$E$38+$K$27) -> 0 | V114: =L114/($L$47+$L$38+$D$27+$N$17) -> 0 | X114: =(G114*0.1)+(I114*6)+(M114*0.1)+(O114*6) -> 0 | Y114: =(F114*1)+(G114*0.1)+(I114*6)+(M114*0.1)+(O114*6) -> 0 | Z114: =(F114*0.5)+(G114*0.1)+(I114*6)+(M114*0.1)+(O114*6) -> 0
D115: =F115/E115 -> #DIV/0! | H115: =G115/F115 -> #DIV/0! | I115: 0 | J115: =I115/F115 -> #DIV/0! | L115: 0 | M115: 0 | N115: 0 | O115: 0 | P115: =O115/L115 -> #DIV/0! | T115: =(E115+L115)/($E$47+$L$47+$E$38+$L$38+$K$27+$D$27+$N$17) -> 0 | U115: =E115/($E$47+$E$38+$K$27) -> 0 | V115: =L115/($L$47+$L$38+$D$27+$N$17) -> 0 | X115: =(G115*0.1)+(I115*6)+(M115*0.1)+(O115*6) -> 0 | Y115: =(F115*1)+(G115*0.1)+(I115*6)+(M115*0.1)+(O115*6) -> 0 | Z115: =(F115*0.5)+(G115*0.1)+(I115*6)+(M115*0.1)+(O115*6) -> 0
D116: =F116/E116 -> #DIV/0! | H116: =G116/F116 -> #DIV/0! | J116: =I116/F116 -> #DIV/0! | N116: 0 | O116: 0 | P116: =O116/L116 -> #DIV/0! | T116: =(E116+L116)/($E$47+$L$47+$E$38+$L$38+$K$27+$D$27+$N$17) -> 0 | U116: =E116/($E$47+$E$38+$K$27) -> 0 | V116: =L116/($L$47+$L$38+$D$27+$N$17) -> 0 | X116: =(G116*0.1)+(I116*6)+(M116*0.1)+(O116*6) -> 0 | Y116: =(F116*1)+(G116*0.1)+(I116*6)+(M116*0.1)+(O116*6) -> 0 | Z116: =(F116*0.5)+(G116*0.1)+(I116*6)+(M116*0.1)+(O116*6) -> 0
A117: Total | E117: =SUM(E113:E116) -> 0 | F117: =SUM(F113:F116) -> 0 | G117: =SUM(G113:G116) -> 0 | I117: =SUM(I113:I116) -> 9 | L117: =SUM(L113:L116) -> 0 | M117: =SUM(M113:M116) -> 0 | O117: =SUM(O113:O116) -> 0
A120: Team Totals and Splits | K120: Taxi Squad* | S120: Injured Reserve
B121: Targets | C121: Rec. | D121: Yds | E121: TDs | J121: Player | N121: Position | R121: Player | V121: Position
A122: Rec Totals* | B122: =SUM(K92:K96,E102:E107,E113:E116) -> 0 | C122: =SUM(F113:F116,F102:F107,L92:L96) -> 0 | D122: =SUM(G113:G116,G102:G107,M92:M96) -> 0 | E122: =SUM(O92:O96,I102:I107,I113:I116) -> 9
A123: QB Totals | B123: =SUM(D87) -> 0 | C123: =SUM(E87) -> 0 | D123: =SUM(G87) -> 0 | E123: =SUM(I87) -> 0
A124: League Att Avg.
B126: Att | C126: Yards | D126: TDs
A127: Rush Totals | B127: =SUM(N84:N86,D92:D96,L102:L107,L113:L116) -> 0 | C127: =SUM(O84:O86,E92:E96,M102:M107,M113:M116) -> 0 | D127: =SUM(Q84:Q86,G92:G96,O102:O107,O113:O116) -> 0
A128: League Att Avg.
B130: Run | C130: Pass
A131: Run/Pass Pct | B131: =B127/(B123+B127) -> #DIV/0! | C131: =B123/(B123+B127) -> #DIV/0!
A132: League Average | J132: *Projected options during offseason/Actual options during the season.
A141: 2-Year Team Historical Performance
I143: RSP Projections: Year 1 | N143: Adjustable Projections: Year 1
I144: RSP Projections: Year 2
...

Sheet ATL
A1: Atlanta Falcons
A3: Team Projections Menu | AD3: Team Projections Menu
I5: RSP Projections: Year 1 | N5: Adjustable Projections: Year 1 | T5: Offense Distribution | AK5: RSP Projections: Year 1 | AP5: Adjustable Projections: Year 1
I6: RSP Projections: Year 2 | N6: Past Run/Pass Performances | T6: Run | U6: Pass | AK6: RSP Projections: Year 2
T7: =(N17+D27+L38+L47)/(N17+D27+L38+D17) -> 0.47104247 | U7: =D17/(D17+N17+D27+L38+L47) -> 0.52895753
T8: Drop 2-4 percent
A10: RSP Projections: Year 1 | AD10: Adjustable Projections: Year 1
D12: Passing | M12: Rushing | S12: Touches | W12: Fantasy Points | AF12: Passing | AO12: Rushing | AU12: Touches | AY12: Fantasy Points
A13: QB | B13: Age | C13: G | D13: Att | E13: Comp | F13: Pct | G13: Yards | H13: Yds/Att | I13: TDs | J13: TDs/Att | K13: Int | L13: Int/Att | N13: Ratt | O13: Ryds | P13: Ryds/Att | Q13: TDs | R13: Tds/Att | T13: Touch % | U13: Pct Pass | V13: Pct Run | X13: Fpts | Y13: Adjusted | AD13: QB | AE13: G | AF13: Att | AG13: Comp | AH13: Pct | AI13: Yards | AJ13: Yds/Att | AK13: TDs | AL13: TDs/Att | AM13: Int | AN13: Int/Att | AP13: Ratt | AQ13: Ryds | AR13: Ryds/Att | AS13: TDs | AT13: Tds/Att | AV13: Touch % | AW13: Pct Pass | AX13: Pct Run | AZ13: Fpts | BA13: Adjusted
A14: QB*Tagovailoa, Tua - ATL | B14: 28 | C14: 9 | D14: 274 | E14: 190 | F14: =E14/D14 -> 0.69343066 | G14: 1922 | H14: =G14/D14 -> 7.0145985 | I14: 11 | J14: =I14/D14 -> 0.040145985 | K14: 8 | L14: =K14/D14 -> 0.02919708 | N14: 12 | O14: 24 | P14: =O14/N14 -> 2 | Q14: 0 | R14: =Q14/N14 -> 0 | T14: =(D14+N14)/($D$17+$N$17) -> 0.48639456 | U14: =D14/($D$17) -> 0.5 | V14: =N14/($N$17) -> 0.3 | X14: =($G14*('Scoring Format'!$B$2))+($I14*('Scoring Format'!$B$5))+($K14*('Scoring Format'!$B$8))+($O14*('Scoring Format'!$B$3))+($Q14*('Scoring Format'!$B$6)) -> 134.5 | Y14: =(($G14*('Scoring Format'!$B$2))+($I14*('Scoring Format'!$B$5))+($K14*('Scoring Format'!$B$8))+($O14*('Scoring Format'!$B$3))+($Q14*('Scoring Format'!$B$6)))*0.4 -> 53.8 | AD14: Murray, Kyler - ARI | AF14: 583 | AG14: 378 | AH14: =AG14/AF14 -> 0.6483705 | AI14: 4072 | AJ14: =AI14/AF14 -> 6.9845626 | AK14: 27 | AL14: =AK14/AF14 -> 0.046312178 | AM14: 11 | AN14: =AM14/AF14 -> 0.018867925 | AP14: 100 | AQ14: 590 | AR14: =AQ14/AP14 -> 5.9 | AS14: 5 | AT14: =AS14/AP14 -> 0.05 | AV14: =(AF14+AP14)/(AF17+AP17) -> 1 | AW14: =AF14/(AP14+AF14) -> 0.85358712 | AX14: =AP14/(AF14+AP14) -> 0.14641288 | AZ14: =((AI14*0.05)+(AK14*4)+(AM14*-1)+(AQ14*0.1)+(AS14*6))*0.55 -> 214.28 | BA14: =((AI14*0.05)+(AK14*4)+(AM14*-1)+(AQ14*0.1)+(AS14*6))*0.4 -> 155.84
A15: QB*Siemian, Trevor - ATL | B15: 34 | C15: 0 | F15: =E15/D15 -> #DIV/0! | H15: =G15/D15 -> #DIV/0! | J15: =I15/D15 -> #DIV/0! | L15: =K15/D15 -> #DIV/0! | P15: =O15/N15 -> #DIV/0! | Q15: 0 | R15: =Q15/N15 -> #DIV/0! | T15: =(D15+N15)/($D$17+$N$17) -> 0 | U15: =D15/($D$17) -> 0 | V15: =N15/($N$17) -> 0 | X15: =($G15*('Scoring Format'!$B$2))+($I15*('Scoring Format'!$B$5))+($K15*('Scoring Format'!$B$8))+($O15*('Scoring Format'!$B$3))+($Q15*('Scoring Format'!$B$6)) -> 0 | Y15: =(($G15*('Scoring Format'!$B$2))+($I15*('Scoring Format'!$B$5))+($K15*('Scoring Format'!$B$8))+($O15*('Scoring Format'!$B$3))+($Q15*('Scoring Format'!$B$6)))*0.4 -> 0 | AD15: McCoy, Colt - ARI | AF15: 0 | AG15: 0 | AH15: 0 | AI15: 0 | AK15: 0 | AL15: =AK15/AF15 -> #DIV/0! | AM15: 0 | AN15: =AM15/AF15 -> #DIV/0! | AP15: 0 | AQ15: 0 | AS15: 0 | AT15: =AS15/AP15 -> #DIV/0! | AV15: =(AF15+AP15)/(AE18+AO18) -> #DIV/0! | AW15: =AF15/(AP15+AF15) -> #DIV/0! | AX15: =AP15/(AF15+AP15) -> #DIV/0!
A16: QB*Penix, Michael - ATL | B16: 26 | C16: 8 | D16: 274 | E16: 175 | F16: =E16/D16 -> 0.63868613 | G16: 2042 | H16: =G16/D16 -> 7.4525547 | I16: 13 | J16: =I16/D16 -> 0.047445255 | K16: 6 | L16: =K16/D16 -> 0.02189781 | N16: 28 | O16: 56 | P16: =O16/N16 -> 2 | Q16: 0 | R16: =Q16/N16 -> 0 | T16: =(D16+N16)/($D$17+$N$17) -> 0.51360544 | U16: =D16/($D$17) -> 0.5 | V16: =N16/($N$17) -> 0.7 | X16: =($G16*('Scoring Format'!$B$2))+($I16*('Scoring Format'!$B$5))+($K16*('Scoring Format'!$B$8))+($O16*('Scoring Format'!$B$3))+($Q16*('Scoring Format'!$B$6)) -> 153.7 | Y16: =(($G16*('Scoring Format'!$B$2))+($I16*('Scoring Format'!$B$5))+($K16*('Scoring Format'!$B$8))+($O16*('Scoring Format'!$B$3))+($Q16*('Scoring Format'!$B$6)))*0.4 -> 61.48 | AD16: McDonald, Cole - ARI | AH16: =AG16/AF16 -> #DIV/0! | AJ16: =AI16/AF16 -> #DIV/0! | AL16: =AK16/AF16 -> #DIV/0! | AN16: =AM16/AF16 -> #DIV/0! | AR16: =AQ16/AP16 -> #DIV/0! | AT16: =AS16/AP16 -> #DIV/0! | AV16: =(AF16+AP16)/(AE20+AO20) -> #DIV/0! | AW16: =AF16/(AP16+AF16) -> #DIV/0! | AX16: =AP16/(AF16+AP16) -> #DIV/0! | AZ16: =((AI16*0.05)+(AK16*4)+(AM16*-1)+(AQ16*0.1)+(AS16*6))*0.55 -> 0 | BA16: =((AI16*0.05)+(AK16*4)+(AM16*-1)+(AQ16*0.1)+(AS16*6))*0.4 -> 0
A17: Total | D17: =SUM(D14:D16) -> 548 | E17: =SUM(E14:E16) -> 365 | G17: =SUM(G14:G16) -> 3964 | I17: =SUM(I14:I16) -> 24 | K17: =SUM(K14:K16) -> 14 | N17: =SUM(N14:N16) -> 40 | O17: =SUM(O14:O16) -> 80 | Q17: =SUM(Q14:Q16) -> 0 | T17: =T14+T15+T16 -> 1 | U17: =D17/(D17+N17) -> 0.93197279 | V17: =N17/(N17+D17) -> 0.068027211 | AD17: Total | AF17: =SUM(AF14:AF16) -> 583 | AG17: =SUM(AG14:AG16) -> 378 | AI17: =SUM(AI14:AI16) -> 4072 | AK17: =SUM(AK14:AK16) -> 27 | AM17: =SUM(AM14:AM16) -> 11 | AP17: =SUM(AP14:AP16) -> 100 | AQ17: =SUM(AQ14:AQ16) -> 590 | AS17: =SUM(AS14:AS16) -> 5 | AV17: =AV14+AV15+AV16 -> #DIV/0! | AW17: =AF17/(AF17+AP17) -> 0.85358712 | AX17: =AP17/(AP17+AF17) -> 0.14641288
A20: Rushing | I20: Receiving | S20: Touches | W20: Fantasy Points | AD20: Rushing | AK20: Receiving | AU20: Touches | AY20: Fantasy Points
A21: RB | B21: Age | C21: G | D21: Att | E21: Yards | F21: Yds/Att | G21: TDs | H21: TDs/Att | J21: Catch % | K21: Targets | L21: Rec | M21: Yds | N21: Yds/Rec | O21: TDs | P21: TDs/Rec | S21: RB | T21: Touch % | U21: Pct Pass | V21: Pct Run | X21: Fpts | Y21: PPR Fpts | Z21: .5 PPR | AD21: RB | AE21: G | AF21: Att | AG21: Yards | AH21: Yds/Att | AI21: TDs | AJ21: TDs/Att | AL21: Catch % | AM21: Targets | AN21: Rec | AO21: Yds | AP21: Yds/Rec | AQ21: TDs | AR21: TDs/Rec | AV21: Touch % | AW21: Pct Pass | AX21: Pct Run | AZ21: Fpts | BA21: PPR Fpts
A22: RB*Robinson, Bijan - ATL | B22: 26 | C22: 17 | D22: 295 | E22: 1466 | F22: =E22/D22 -> 4.9694915 | G22: 11 | H22: =G22/D22 -> 0.037288136 | J22: =L22/K22 -> 0.79545455 | K22: 88 | L22: 70 | M22: 625 | N22: =M22/L22 -> 8.9285714 | O22: 3 | P22: =O22/L22 -> 0.042857143 | S22: Robinson, Bijan - ATL | T22: =(D22+K22)/($D$27+$K$27+$N$17+$E$17+$L$38+$L$47) -> 0.39484536 | U22: =K22/($K$27+$F$38+$F$47) -> 0.22564103 | V22: =D22/($D$27+$N$17+$L$38+$L$47) -> 0.6045082 | X22: =($E22*('Scoring Format'!$B$3))+($G22*('Scoring Format'!$B$6))+($M22*('Scoring Format'!$B$4))+($O22*('Scoring Format'!$B$7)) -> 293.1 | Y22: =($E22*('Scoring Format'!$B$3))+($G22*('Scoring Format'!$B$6))+(L22*1)+($M22*('Scoring Format'!$B$4))+($O22*('Scoring Format'!$B$7)) -> 363.1 | Z22: =($E22*('Scoring Format'!$B$3))+($G22*('Scoring Format'!$B$6))+(L22*0.5)+($M22*('Scoring Format'!$B$4))+($O22*('Scoring Format'!$B$7)) -> 328.1 | AD22: Conner, James - ARI | AF22: 200 | AG22: 1040 | AH22: =AG22/AF22 -> 5.2 | AI22: 7 | AJ22: =AI22/AF22 -> 0.035 | AL22: =AN22/AM22 -> 0.8 | AM22: 70 | AN22: 56 | AO22: 364 | AP22: =AO22/AN22 -> 6.5 | AQ22: 2 | AR22: =AQ22/AN22 -> 0.035714286 | AV22: =(#REF!+AM22)/(#REF!+AM25) -> #REF! | AW22: =#REF!/(AM22+#REF!) -> #REF! | AX22: =AM22/(#REF!+AM22) -> #REF! | AZ22: =(#REF!*0.1)+(AF22*6)+(AL22*0.1)+(AN22*6) -> #REF! | BA22: =(#REF!*0.1)+(AF22*6)+(AK22*1)+(AL22*0.1)+(AN22*6) -> #REF!
A23: RB*Robinson, Brian - ATL | B23: 27 | C23: 17 | D23: 140 | E23: 579 | F23: =E23/D23 -> 4.1357143 | G23: 3 | H23: =G23/D23 -> 0.021428571 | J23: =L23/K23 -> 0.77272727 | K23: 22 | L23: 17 | M23: 116 | N23: =M23/L23 -> 6.8235294 | O23: 0 | P23: =O23/L23 -> 0 | S23: Robinson, Brian - ATL | T23: =(D23+K23)/($D$27+$K$27+$N$17+$E$17+$L$38+$L$47) -> 0.16701031 | U23: =K23/($K$27+$F$38+$F$47) -> 0.056410256 | V23: =D23/($D$27+$N$17+$L$38+$L$47) -> 0.28688525 | X23: =($E23*('Scoring Format'!$B$3))+($G23*('Scoring Format'!$B$6))+($M23*('Scoring Format'!$B$4))+($O23*('Scoring Format'!$B$7)) -> 87.5 | Y23: =($E23*('Scoring Format'!$B$3))+($G23*('Scoring Format'!$B$6))+(L23*1)+($M23*('Scoring Format'!$B$4))+($O23*('Scoring Format'!$B$7)) -> 104.5 | Z23: =($E23*('Scoring Format'!$B$3))+($G23*('Scoring Format'!$B$6))+(L23*0.5)+($M23*('Scoring Format'!$B$4))+($O23*('Scoring Format'!$B$7)) -> 96 | AD23: Edmonds, Chase - ARI | AF23: 96 | AG23: 445 | AH23: =AG23/AF23 -> 4.6354167 | AI23: 6 | AJ23: =AI23/AF23 -> 0.0625 | AL23: =AN23/AM23 -> 0.58333333 | AM23: 24 | AN23: 14 | AO23: 110 | AP23: =AO23/AN23 -> 7.8571429 | AQ23: 2 | AR23: =AQ23/AN23 -> 0.14285714 | AV23: =(#REF!+AM23)/(#REF!+AM26) -> #REF! | AW23: =#REF!/(AM23+#REF!) -> #REF! | AX23: =AM23/(#REF!+AM23) -> #REF! | AZ23: =(#REF!*0.1)+(AF23*6)+(AL23*0.1)+(AN23*6) -> #REF! | BA23: =(#REF!*0.1)+(AF23*6)+(AK23*1)+(AL23*0.1)+(AN23*6) -> #REF!
A24: RB*Goodson, Tyler - ATL | B24: 25 | C24: 17 | D24: 10 | E24: 57 | F24: =E24/D24 -> 5.7 | G24: 1 | H24: =G24/D24 -> 0.1 | J24: =L24/K24 -> 0.71428571 | K24: 7 | L24: 5 | M24: 30 | N24: =M24/L24 -> 6 | O24: 0 | P24: =O24/L24 -> 0 | S24: Goodson, Tyler - ATL | T24: =(D24+K24)/($D$27+$K$27+$N$17+$E$17+$L$38+$L$47) -> 0.017525773 | U24: =K24/($K$27+$F$38+$F$47) -> 0.017948718 | V24: =D24/($D$27+$N$17+$L$38+$L$47) -> 0.020491803 | X24: =($E24*('Scoring Format'!$B$3))+($G24*('Scoring Format'!$B$6))+($M24*('Scoring Format'!$B$4))+($O24*('Scoring Format'!$B$7)) -> 14.7 | Y24: =($E24*('Scoring Format'!$B$3))+($G24*('Scoring Format'!$B$6))+(L24*1)+($M24*('Scoring Format'!$B$4))+($O24*('Scoring Format'!$B$7)) -> 19.7 | Z24: =($E24*('Scoring Format'!$B$3))+($G24*('Scoring Format'!$B$6))+(L24*0.5)+($M24*('Scoring Format'!$B$4))+($O24*('Scoring Format'!$B$7)) -> 17.2 | AD24: Benjamin, Eno - ARI | AF24: 8 | AG24: 28 | AH24: =AG24/AF24 -> 3.5 | AI24: 0 | AJ24: =AI24/AF24 -> 0 | AL24: =AN24/AM24 -> 0.5 | AM24: 4 | AN24: 2 | AO24: 17 | AP24: =AO24/AN24 -> 8.5 | AQ24: 0 | AR24: =AQ24/AN24 -> 0 | AV24: =(#REF!+AM24)/(#REF!+AL30) -> #REF! | AW24: =#REF!/(AM24+#REF!) -> #REF! | AX24: =AM24/(#REF!+AM24) -> #REF! | AZ24: =(#REF!*0.1)+(AF24*6)+(AL24*0.1)+(AN24*6) -> #REF! | BA24: =(#REF!*0.1)+(AF24*6)+(AK24*1)+(AL24*0.1)+(AN24*6) -> #REF!
F25: =E25/D25 -> #DIV/0! | G25: 0 | H25: =G25/D25 -> #DIV/0! | J25: =L25/K25 -> #DIV/0! | N25: =M25/L25 -> #DIV/0! | O25: 0 | P25: =O25/L25 -> #DIV/0! | T25: =(D25+K25)/($D$27+$K$27+$N$17+$E$17+$L$38+$L$47) -> 0 | U25: =K25/($K$27+$F$38+$F$47) -> 0 | V25: =D25/($D$27+$N$17+$L$38+$L$47) -> 0 | X25: =($E25*('Scoring Format'!$B$3))+($G25*('Scoring Format'!$B$6))+($M25*('Scoring Format'!$B$4))+($O25*('Scoring Format'!$B$7)) -> 0 | Y25: =($E25*('Scoring Format'!$B$3))+($G25*('Scoring Format'!$B$6))+(L25*1)+($M25*('Scoring Format'!$B$4))+($O25*('Scoring Format'!$B$7)) -> 0 | Z25: =($E25*('Scoring Format'!$B$3))+($G25*('Scoring Format'!$B$6))+(L25*0.5)+($M25*('Scoring Format'!$B$4))+($O25*('Scoring Format'!$B$7)) -> 0 | AD25: Ward, Jonathan - ARI | AH25: =AG25/AF25 -> #DIV/0! | AI25: 0 | AJ25: =AI25/AF25 -> #DIV/0! | AL25: =AN25/AM25 -> #DIV/0! | AP25: =AO25/AN25 -> #DIV/0! | AQ25: 0 | AR25: =AQ25/AN25 -> #DIV/0! | AV25: =(#REF!+AM25)/(#REF!+AM31) -> #REF! | AW25: =#REF!/(AM25+#REF!) -> #REF! | AX25: =AM25/(#REF!+AM25) -> #REF! | AZ25: =(#REF!*0.1)+(AF25*6)+(AL25*0.1)+(AN25*6) -> #REF! | BA25: =(#REF!*0.1)+(AF25*6)+(AK25*1)+(AL25*0.1)+(AN25*6) -> #REF!
F26: =E26/D26 -> #DIV/0! | G26: 0 | H26: =G26/D26 -> #DIV/0! | J26: =L26/K26 -> #DIV/0! | N26: =M26/L26 -> #DIV/0! | O26: 0 | P26: =O26/L26 -> #DIV/0! | T26: =(D26+K26)/($D$27+$K$27+$N$17+$E$17+$L$38+$L$47) -> 0 | U26: =K26/($K$27+$F$38+$F$47) -> 0 | V26: =D26/($D$27+$N$17+$L$38+$L$47) -> 0 | X26: =($E26*('Scoring Format'!$B$3))+($G26*('Scoring Format'!$B$6))+($M26*('Scoring Format'!$B$4))+($O26*('Scoring Format'!$B$7)) -> 0 | Y26: =($E26*('Scoring Format'!$B$3))+($G26*('Scoring Format'!$B$6))+(L26*1)+($M26*('Scoring Format'!$B$4))+($O26*('Scoring Format'!$B$7)) -> 0 | Z26: =($E26*('Scoring Format'!$B$3))+($G26*('Scoring Format'!$B$6))+(L26*0.5)+($M26*('Scoring Format'!$B$4))+($O26*('Scoring Format'!$B$7)) -> 0 | AD26: Muhammad, Khalfani - ARI | AH26: =AG26/AF26 -> #DIV/0! | AJ26: =AI26/AF26 -> #DIV/0! | AL26: =AN26/AM26 -> #DIV/0! | AQ26: =(AG26*0.1)+(AI26*6)+(AN26*0.1)+(AP26*6) -> 0 | AR26: =AQ26/AN26 -> #DIV/0! | AV26: =(#REF!+AM26)/(#REF!+AM32) -> #REF! | AW26: =#REF!/(AM26+#REF!) -> #REF! | AX26: =AM26/(#REF!+AM26) -> #REF! | AZ26: =(#REF!*0.1)+(AF26*6)+(AJ26*1)+(AK26*0.1)+(AM26*6) -> #REF! | BA26: =(#REF!*0.1)+(AF26*6)+(AK26*1)+(AL26*0.1)+(AN26*6) -> #REF!
A27: Total | D27: =SUM(D22:D26) -> 445 | E27: =SUM(E22:E26) -> 2102 | G27: =SUM(G22:G26) -> 15 | K27: =SUM(K22:K26) -> 117 | L27: =SUM(L22:L26) -> 92 | M27: =SUM(M22:M26) -> 771 | O27: =SUM(O22:O26) -> 3 | AD27: Total | AF27: =SUM(AF22:AF26) -> 304 | AG27: =SUM(AG22:AG26) -> 1513 | AI27: =SUM(AI22:AI26) -> 13 | AM27: =SUM(AM22:AM26) -> 98 | AN27: =SUM(AN22:AN26) -> 72 | AO27: =SUM(AO22:AO26) -> 491 | AQ27: =SUM(AQ22:AQ26) -> 4
A30: Receiving | K30: Rushing | S30: Touches | W30: Fantasy Points | AD30: Receiving | AM30: Rushing | AU30: Touches | AY30: Fantasy Points
A31: WRs | B31: Age | C31: G | D31: Catch % | E31: Targets | F31: Rec | G31: Yds | H31: Yds/Rec | I31: TDs | J31: TDs/Rec | L31: Ratt | M31: Ryds | N31: Ryds/Att | O31: RTds | P31: TDs/Att | S31: WRs | T31: Touch % | U31: Pct Pass | V31: Pct Run | X31: Fpts | Y31: PPR Fpts | Z31: .5PPR | AD31: WRs | AE31: G | AF31: Catch % | AG31: Targets | AH31: Rec | AI31: Yds | AJ31: Yds/Rec | AK31: TDs | AL31: TDs/Rec | AN31: Ratt | AO31: Ryds | AP31: Ryds/Att | AQ31: RTds | AR31: TDs/Att | AV31: Touch % | AW31: Pct Pass | AX31: Pct Run | AZ31: Fpts | BA31: PPR Fpts
A32: WR*London, Drake - ATL | B32: 24 | C32: 17 | D32: =F32/E32 -> 0.60377358 | E32: 159 | F32: 96 | G32: 1300 | H32: =G32/F32 -> 13.541667 | I32: 10 | J32: =I32/F32 -> 0.10416667 | L32: 0 | M32: 0 | N32: =M32/L32 -> #DIV/0! | O32: 0 | P32: =O32/L32 -> #DIV/0! | S32: London, Drake - ATL | T32: =(E32+L32)/($D$27+$L$27+$N$17+$E$47+$L$47) -> 0.21285141 | U32: =E32/($E$17) -> 0.43561644 | V32: =L32/($N$17+$D$27+$L$38+$L$47) -> 0 | X32: =($G32*('Scoring Format'!$B$4))+($I32*'Scoring Format'!$B$7)+($M32*('Scoring Format'!$B$3))+($O32*('Scoring Format'!$B$6)) -> 190 | Y32: =(F32*1)+(($G32*('Scoring Format'!$B$4))+($I32*'Scoring Format'!$B$7)+($M32*('Scoring Format'!$B$3))+($O32*('Scoring Format'!$B$6))) -> 286 | Z32: =(F32*0.5)+(($G32*('Scoring Format'!$B$4))+($I32*'Scoring Format'!$B$7)+($M32*('Scoring Format'!$B$3))+($O32*('Scoring Format'!$B$6))) -> 238 | AD32: Green, A.J. - ARI | AF32: =AH32/AG32 -> 0.60747664 | AG32: 107 | AH32: 65 | AI32: 710 | AJ32: =AI32/AH32 -> 10.923077 | AK32: 6 | AL32: =AK32/AH32 -> 0.092307692 | AN32: 0 | AO32: 0 | AP32: =AO32/AN32 -> #DIV/0! | AQ32: 0 | AR32: =AQ32/AN32 -> #DIV/0! | AV32: =(#REF!+AK32)/(#REF!+AK35) -> #REF! | AW32: =#REF!/(AK32+#REF!) -> #REF! | AX32: =AK32/(#REF!+AK32) -> #REF! | AZ32: =(AI32*0.1)+(AK32*6)+(AO32*0.1)+(AQ32*6) -> 107 | BA32: =(AH32*1)+(AI32*0.1)+(AK32*6)+(AO32*0.1)+(AQ32*6) -> 172
A33: WR*Zaccheaus, Olamide - ATL | B33: 28 | C33: 17 | D33: =F33/E33 -> 0.63636364 | E33: 33 | F33: 21 | G33: 205 | H33: =G33/F33 -> 9.7619048 | I33: 2 | J33: =I33/F33 -> 0.095238095 | L33: 3 | M33: 16 | N33: =M33/L33 -> 5.3333333 | O33: 0 | P33: =O33/L33 -> 0 | S33: Zaccheaus, Olamide - ATL | T33: =(E33+L33)/($D$27+$L$27+$N$17+$E$47+$L$47) -> 0.048192771 | U33: =E33/($E$17) -> 0.090410959 | V33: =L33/($N$17+$D$27+$L$38+$L$47) -> 0.006147541 | X33: =($G33*('Scoring Format'!$B$4))+($I33*'Scoring Format'!$B$7)+($M33*('Scoring Format'!$B$3))+($O33*('Scoring Format'!$B$6)) -> 34.1 | Y33: =(F33*1)+(($G33*('Scoring Format'!$B$4))+($I33*'Scoring Format'!$B$7)+($M33*('Scoring Format'!$B$3))+($O33*('Scoring Format'!$B$6))) -> 55.1 | Z33: =(F33*0.5)+(($G33*('Scoring Format'!$B$4))+($I33*'Scoring Format'!$B$7)+($M33*('Scoring Format'!$B$3))+($O33*('Scoring Format'!$B$6))) -> 44.6 | AD33: Kirk, Christian- ARI | AF33: =AH33/AG33 -> 0.63333333 | AG33: 120 | AH33: 76 | AI33: 892 | AJ33: =AI33/AH33 -> 11.736842 | AK33: 5 | AL33: =AK33/AH33 -> 0.065789474 | AN33: 12 | AO33: 108 | AP33: =AO33/AN33 -> 9 | AQ33: 0 | AR33: =AQ33/AN33 -> 0 | AV33: =(#REF!+AK33)/(#REF!+AK36) -> #REF! | AW33: =#REF!/(AK33+#REF!) -> #REF! | AX33: =AK33/(#REF!+AK33) -> #REF! | AZ33: =(AI33*0.1)+(AK33*6)+(AO33*0.1)+(AQ33*6) -> 130 | BA33: =(AH33*1)+(AI33*0.1)+(AK33*6)+(AO33*0.1)+(AQ33*6) -> 206
A34: WR*Washington, Casey - ATL | B34: 25 | C34: 17 | D34: =F34/E34 -> 0.42857143 | E34: 7 | F34: 3 | G34: 47 | H34: =G34/F34 -> 15.666667 | I34: 0 | J34: =I34/F34 -> 0 | N34: =M34/L34 -> #DIV/0! | O34: 0 | P34: =O34/L34 -> #DIV/0! | S34: Washington, Casey - ATL | T34: =(E34+L34)/($D$27+$L$27+$N$17+$E$47+$L$47) -> 0.0093708166 | U34: =E34/($E$17) -> 0.019178082 | V34: =L34/($N$17+$D$27+$L$38+$L$47) -> 0 | X34: =($G34*('Scoring Format'!$B$4))+($I34*'Scoring Format'!$B$7)+($M34*('Scoring Format'!$B$3))+($O34*('Scoring Format'!$B$6)) -> 4.7 | Y34: =(F34*1)+(($G34*('Scoring Format'!$B$4))+($I34*'Scoring Format'!$B$7)+($M34*('Scoring Format'!$B$3))+($O34*('Scoring Format'!$B$6))) -> 7.7 | Z34: =(F34*0.5)+(($G34*('Scoring Format'!$B$4))+($I34*'Scoring Format'!$B$7)+($M34*('Scoring Format'!$B$3))+($O34*('Scoring Format'!$B$6))) -> 6.2 | AD34: Isabella, Andy - ARI | AF34: =AH34/AG34 -> 0.55 | AG34: 40 | AH34: 22 | AI34: 325 | AJ34: =AI34/AH34 -> 14.772727 | AK34: 2 | AL34: =AK34/AH34 -> 0.090909091 | AN34: 5 | AO34: 20 | AP34: =AO34/AN34 -> 4 | AQ34: 0 | AR34: =AQ34/AN34 -> 0 | AV34: =(#REF!+AK34)/(#REF!+AK37) -> #REF! | AW34: =#REF!/(AK34+#REF!) -> #REF! | AX34: =AK34/(#REF!+AK34) -> #REF! | AZ34: =(AI34*0.1)+(AK34*6)+(AO34*0.1)+(AQ34*6) -> 46.5 | BA34: =(AH34*1)+(AI34*0.1)+(AK34*6)+(AO34*0.1)+(AQ34*6) -> 68.5
A35: WR*Branch, Zachariah - ATL | B35: 22 | C35: 17 | D35: =F35/E35 -> 0.5 | E35: 20 | F35: 10 | G35: 90 | H35: =G35/F35 -> 9 | I35: 1 | J35: =I35/F35 -> 0.1 | N35: =M35/L35 -> #DIV/0! | O35: 1 | P35: =O35/L35 -> #DIV/0! | S35: Branch, Zachariah - ATL | T35: =(E35+L35)/($D$27+$L$27+$N$17+$E$47+$L$47) -> 0.026773762 | U35: =E35/($E$17) -> 0.054794521 | V35: =L35/($N$17+$D$27+$L$38+$L$47) -> 0 | X35: =($G35*('Scoring Format'!$B$4))+($I35*'Scoring Format'!$B$7)+($M35*('Scoring Format'!$B$3))+($O35*('Scoring Format'!$B$6)) -> 21 | Y35: =(F35*1)+(($G35*('Scoring Format'!$B$4))+($I35*'Scoring Format'!$B$7)+($M35*('Scoring Format'!$B$3))+($O35*('Scoring Format'!$B$6))) -> 31 | Z35: =(F35*0.5)+(($G35*('Scoring Format'!$B$4))+($I35*'Scoring Format'!$B$7)+($M35*('Scoring Format'!$B$3))+($O35*('Scoring Format'!$B$6))) -> 26 | AD35: Hopkins, DeAndre - ARI | AF35: =AH35/AG35 -> 0.66206897 | AG35: 145 | AH35: 96 | AI35: 1098 | AJ35: =AI35/AH35 -> 11.4375 | AK35: 7 | AL35: =AK35/AH35 -> 0.072916667 | AN35: 0 | AO35: 0 | AP35: =AO35/AN35 -> #DIV/0! | AQ35: 0 | AR35: =AQ35/AN35 -> #DIV/0! | AV35: =(#REF!+AK35)/(#REF!+AK38) -> #REF! | AW35: =#REF!/(AK35+#REF!) -> #REF! | AX35: =AK35/(#REF!+AK35) -> #REF! | AZ35: =(AI35*0.1)+(AK35*6)+(AO35*0.1)+(AQ35*6) -> 151.8 | BA35: =(AH35*1)+(AI35*0.1)+(AK35*6)+(AO35*0.1)+(AQ35*6) -> 247.8
A36: WR*Jahan Dotson, ATL | B36: 25 | C36: 17 | D36: =F36/E36 -> 0.63888889 | E36: 36 | F36: 23 | G36: 272 | H36: =G36/F36 -> 11.826087 | I36: 1 | J36: =I36/F36 -> 0.043478261 | N36: =M36/L36 -> #DIV/0! | O36: 0 | P36: =O36/L36 -> #DIV/0! | S36: Dotson, Jahan - ATL | T36: =(E36+L36)/($D$27+$L$27+$N$17+$E$47+$L$47) -> 0.048192771 | U36: =E36/($E$17) -> 0.098630137 | V36: =L36/($N$17+$D$27+$L$38+$L$47) -> 0 | X36: =($G36*('Scoring Format'!$B$4))+($I36*'Scoring Format'!$B$7)+($M36*('Scoring Format'!$B$3))+($O36*('Scoring Format'!$B$6)) -> 33.2 | Y36: =(F36*1)+(($G36*('Scoring Format'!$B$4))+($I36*'Scoring Format'!$B$7)+($M36*('Scoring Format'!$B$3))+($O36*('Scoring Format'!$B$6))) -> 56.2 | Z36: =(F36*0.5)+(($G36*('Scoring Format'!$B$4))+($I36*'Scoring Format'!$B$7)+($M36*('Scoring Format'!$B$3))+($O36*('Scoring Format'!$B$6))) -> 44.7 | AD36: Johnson, KeeSean - ARI | AF36: =AH36/AG36 -> 0.6 | AG36: 10 | AH36: 6 | AI36: 100 | AJ36: =AI36/AH36 -> 16.666667 | AK36: 0 | AL36: =AK36/AH36 -> 0 | AN36: 0 | AO36: 0 | AP36: =AO36/AN36 -> #DIV/0! | AQ36: 0 | AR36: =AQ36/AN36 -> #DIV/0! | AV36: =(#REF!+AK36)/(#REF!+AJ41) -> #REF! | AW36: =#REF!/(AK36+#REF!) -> #REF! | AX36: =AK36/(#REF!+AK36) -> #REF! | AZ36: =(AI36*0.1)+(AK36*6)+(AO36*0.1)+(AQ36*6) -> 10 | BA36: =(AH36*1)+(AI36*0.1)+(AK36*6)+(AO36*0.1)+(AQ36*6) -> 16
A37: WR*Anthony, Vinny - ATL | B37: 22 | C37: 17 | D37: =F37/E37 -> 0.5 | E37: 6 | F37: 3 | G37: 29 | H37: =G37/F37 -> 9.6666667 | I37: 0 | J37: =I37/F37 -> 0 | N37: =M37/L37 -> #DIV/0! | O37: 0 | P37: =O37/L37 -> #DIV/0! | S37: Anthony, Vinny - ATL | T37: =(E37+L37)/($D$27+$L$27+$N$17+$E$47+$L$47) -> 0.0080321285 | U37: =E37/($E$17) -> 0.016438356 | V37: =L37/($N$17+$D$27+$L$38+$L$47) -> 0 | X37: =($G37*('Scoring Format'!$B$4))+($I37*'Scoring Format'!$B$7)+($M37*('Scoring Format'!$B$3))+($O37*('Scoring Format'!$B$6)) -> 2.9 | Y37: =(F37*1)+(($G37*('Scoring Format'!$B$4))+($I37*'Scoring Format'!$B$7)+($M37*('Scoring Format'!$B$3))+($O37*('Scoring Format'!$B$6))) -> 5.9 | Z37: =(F37*0.5)+(($G37*('Scoring Format'!$B$4))+($I37*'Scoring Format'!$B$7)+($M37*('Scoring Format'!$B$3))+($O37*('Scoring Format'!$B$6))) -> 4.4 | AD37: Moore, Rondale - ARI | AF37: =AH37/AG37 -> #DIV/0! | AL37: =AK37/AH37 -> #DIV/0! | AP37: =AO37/AN37 -> #DIV/0! | AR37: =AQ37/AN37 -> #DIV/0! | AV37: =(#REF!+AK37)/(#REF!+AK42) -> #REF! | AW37: =#REF!/(AK37+#REF!) -> #REF! | AX37: =AK37/(#REF!+AK37) -> #REF!
A38: Total | E38: =SUM(E32:E37) -> 261 | F38: =SUM(F32:F37) -> 156 | G38: =SUM(G32:G37) -> 1943 | I38: =SUM(I32:I37) -> 14 | L38: =SUM(L32:L37) -> 3 | M38: =SUM(M32:M37) -> 16 | O38: =SUM(O32:O37) -> 1 | AD38: Total | AG38: =SUM(AG32:AG37) -> 422 | AH38: =SUM(AH32:AH37) -> 265 | AI38: =SUM(AI32:AI37) -> 3125 | AK38: =SUM(AK32:AK37) -> 20 | AN38: =SUM(AN32:AN37) -> 17 | AO38: =SUM(AO32:AO37) -> 128 | AQ38: =SUM(AQ32:AQ37) -> 0
A41: Receiving | K41: Rushing | S41: Touches | W41: Fantasy Points | AD41: Receiving | AM41: Rushing | AU41: Touches | AY41: Fantasy Points
A42: Tes | B42: Age | C42: G | D42: Catch % | E42: Targets | F42: Rec | G42: Yds | H42: Yds/Rec | I42: TDs | J42: TDs/Rec | L42: Ratt | M42: Ryds | N42: Ryds/Att | O42: RTDs | P42: TDs/Att | S42: Tes | T42: Touch % | U42: Pct Pass | V42: Pct Run | X42: Fpts | Y42: PPR Fpts | Z42: .5 PPR | AD42: Tes | AE42: G | AF42: Catch % | AG42: Targets | AH42: Rec | AI42: Yds | AJ42: Yds/Rec | AK42: TDs | AL42: TDs/Rec | AN42: Ratt | AO42: Ryds | AP42: Ryds/Att | AQ42: RTDs | AR42: TDs/Att | AV42: Touch % | AW42: Pct Pass | AX42: Pct Run | AZ42: Fpts | BA42: PPR Fpts
A43: TE*Pitts, Kyle - ATL | B43: 25 | C43: 17 | D43: =F43/E43 -> 0.66176471 | E43: 136 | F43: 90 | G43: 1028 | H43: =G43/F43 -> 11.422222 | I43: 6 | J43: =I43/F43 -> 0.066666667 | L43: 0 | M43: 0 | N43: 0 | O43: 0 | P43: =O43/L43 -> #DIV/0! | S43: Pitts, Kyle - ATL | T43: =(E43+L43)/($E$47+$L$47+$E$38+$L$38+$K$27+$D$27+$N$17) -> 0.13127413 | U43: =E43/($E$47+$E$38+$K$27) -> 0.24817518 | V43: =L43/($L$47+$L$38+$D$27+$N$17) -> 0 | X43: =($G43*('Scoring Format'!$B$4))+($I43*'Scoring Format'!$B$7)+($M43*('Scoring Format'!$B$3))+($O43*('Scoring Format'!$B$6)) -> 138.8 | Y43: =(F43*1)+(($G43*('Scoring Format'!$B$4))+($I43*'Scoring Format'!$B$7)+($M43*('Scoring Format'!$B$3))+($O43*('Scoring Format'!$B$6))) -> 228.8 | Z43: =(F43*0.5)+(($G43*('Scoring Format'!$B$4))+($I43*'Scoring Format'!$B$7)+($M43*('Scoring Format'!$B$3))+($O43*('Scoring Format'!$B$6))) -> 183.8 | AD43: Williams, Maxx - ARI | AF43: =AH43/AG43 -> 0.5625 | AG43: 16 | AH43: 9 | AI43: 108 | AJ43: =AI43/AH43 -> 12 | AK43: 1 | AL43: =AK43/AH43 -> 0.11111111 | AN43: 0 | AO43: 0 | AP43: 0 | AQ43: 0 | AR43: =AQ43/AN43 -> #DIV/0! | AV43: =(#REF!+AK43)/(#REF!+AK46) -> #REF! | AW43: =#REF!/(AK43+#REF!) -> #REF! | AX43: =AK43/(#REF!+AK43) -> #REF! | AZ43: =(AI43*0.1)+(AK43*6)+(AO43*0.1)+(AQ43*6) -> 16.8 | BA43: =(AH43*1)+(AI43*0.1)+(AK43*6)+(AO43*0.1)+(AQ43*6) -> 25.8
A44: TE*Woerner, Charlie - ATL | B44: 28 | C44: 16 | D44: =F44/E44 -> 0.77777778 | E44: 9 | F44: 7 | G44: 42 | H44: =G44/F44 -> 6 | I44: 0 | J44: =I44/F44 -> 0 | L44: 0 | M44: 0 | N44: 0 | O44: 0 | P44: =O44/L44 -> #DIV/0! | S44: Woerner, Charlie - ATL | T44: =(E44+L44)/($E$47+$L$47+$E$38+$L$38+$K$27+$D$27+$N$17) -> 0.0086872587 | U44: =E44/($E$47+$E$38+$K$27) -> 0.016423358 | V44: =L44/($L$47+$L$38+$D$27+$N$17) -> 0 | X44: =($G44*('Scoring Format'!$B$4))+($I44*'Scoring Format'!$B$7)+($M44*('Scoring Format'!$B$3))+($O44*('Scoring Format'!$B$6)) -> 4.2 | Y44: =(F44*1)+(($G44*('Scoring Format'!$B$4))+($I44*'Scoring Format'!$B$7)+($M44*('Scoring Format'!$B$3))+($O44*('Scoring Format'!$B$6))) -> 11.2 | Z44: =(F44*0.5)+(($G44*('Scoring Format'!$B$4))+($I44*'Scoring Format'!$B$7)+($M44*('Scoring Format'!$B$3))+($O44*('Scoring Format'!$B$6))) -> 7.7 | AD44: Daniels, Darenell - ARI | AF44: =AH44/AG44 -> 0.74285714 | AG44: 35 | AH44: 26 | AI44: 283 | AJ44: =AI44/AH44 -> 10.884615 | AK44: 2 | AL44: =AK44/AH44 -> 0.076923077 | AN44: 0 | AO44: 0 | AP44: 0 | AQ44: 0 | AR44: =AQ44/AN44 -> #DIV/0! | AV44: =(#REF!+AK44)/(#REF!+AK47) -> #REF! | AW44: =#REF!/(AK44+#REF!) -> #REF! | AX44: =AK44/(#REF!+AK44) -> #REF! | AZ44: =(AI44*0.1)+(AK44*6)+(AO44*0.1)+(AQ44*6) -> 40.3 | BA44: =(AH44*1)+(AI44*0.1)+(AK44*6)+(AO44*0.1)+(AQ44*6) -> 66.3
A45: TE*Hooper, Austin | B45: 31 | C45: 17 | D45: =F45/E45 -> 0.8 | E45: 25 | F45: 20 | G45: 180 | H45: =G45/F45 -> 9 | I45: 1 | J45: =I45/F45 -> 0.05 | L45: 0 | M45: 0 | N45: 0 | O45: 0 | P45: =O45/L45 -> #DIV/0! | S45: Hooper, Austin - ATL | T45: =(E45+L45)/($E$47+$L$47+$E$38+$L$38+$K$27+$D$27+$N$17) -> 0.024131274 | U45: =E45/($E$47+$E$38+$K$27) -> 0.045620438 | V45: =L45/($L$47+$L$38+$D$27+$N$17) -> 0 | X45: =($G45*('Scoring Format'!$B$4))+($I45*'Scoring Format'!$B$7)+($M45*('Scoring Format'!$B$3))+($O45*('Scoring Format'!$B$6)) -> 24 | Y45: =(F45*1)+(($G45*('Scoring Format'!$B$4))+($I45*'Scoring Format'!$B$7)+($M45*('Scoring Format'!$B$3))+($O45*('Scoring Format'!$B$6))) -> 44 | Z45: =(F45*0.5)+(($G45*('Scoring Format'!$B$4))+($I45*'Scoring Format'!$B$7)+($M45*('Scoring Format'!$B$3))+($O45*('Scoring Format'!$B$6))) -> 34 | AD45: Bunting, Ian - ARI | AF45: =AH45/AG45 -> 0.5 | AG45: 12 | AH45: 6 | AI45: 65 | AJ45: =AI45/AH45 -> 10.833333 | AK45: 0 | AL45: =AK45/AH45 -> 0 | AN45: 0 | AO45: 0 | AP45: 0 | AQ45: 0 | AR45: =AQ45/AN45 -> #DIV/0! | AV45: =(#REF!+AK45)/(#REF!+AJ49) -> #REF! | AW45: =#REF!/(AK45+#REF!) -> #REF! | AX45: =AK45/(#REF!+AK45) -> #REF! | AZ45: =(AI45*0.1)+(AK45*6)+(AO45*0.1)+(AQ45*6) -> 6.5 | BA45: =(AH45*1)+(AI45*0.1)+(AK45*6)+(AO45*0.1)+(AQ45*6) -> 12.5
D46: =F46/E46 -> #DIV/0! | H46: =G46/F46 -> #DIV/0! | I46: 0 | J46: =I46/F46 -> #DIV/0! | N46: 0 | O46: 0 | P46: =O46/L46 -> #DIV/0! | T46: =(E46+L46)/($E$47+$L$47+$E$38+$L$38+$K$27+$D$27+$N$17) -> 0 | U46: =E46/($E$47+$E$38+$K$27) -> 0 | V46: =L46/($L$47+$L$38+$D$27+$N$17) -> 0 | X46: =($G46*('Scoring Format'!$B$4))+($I46*'Scoring Format'!$B$7)+($M46*('Scoring Format'!$B$3))+($O46*('Scoring Format'!$B$6)) -> 0 | Y46: =(F46*1)+(($G46*('Scoring Format'!$B$4))+($I46*'Scoring Format'!$B$7)+($M46*('Scoring Format'!$B$3))+($O46*('Scoring Format'!$B$6))) -> 0 | Z46: =(F46*0.5)+(($G46*('Scoring Format'!$B$4))+($I46*'Scoring Format'!$B$7)+($M46*('Scoring Format'!$B$3))+($O46*('Scoring Format'!$B$6))) -> 0 | AF46: =AH46/AG46 -> #DIV/0! | AJ46: =AI46/AH46 -> #DIV/0! | AL46: =AK46/AH46 -> #DIV/0! | AQ46: 0 | AR46: =AQ46/AN46 -> #DIV/0! | AV46: =(#REF!+AK46)/(#REF!+AJ50) -> #REF! | AW46: =#REF!/(AK46+#REF!) -> #REF! | AX46: =AK46/(#REF!+AK46) -> #REF! | AZ46: =(AI46*0.1)+(AK46*6)+(AO46*0.1)+(AQ46*6) -> 0 | BA46: =(AH46*1)+(AI46*0.1)+(AK46*6)+(AO46*0.1)+(AQ46*6) -> 0
A47: Total | E47: =SUM(E43:E46) -> 170 | F47: =SUM(F43:F46) -> 117 | G47: =SUM(G43:G46) -> 1250 | I47: =SUM(I43:I46) -> 7 | L47: =SUM(L43:L46) -> 0 | M47: =SUM(M43:M46) -> 0 | O47: =SUM(O43:O46) -> 0 | AD47: Total | AG47: =SUM(AG43:AG46) -> 63 | AH47: =SUM(AH43:AH46) -> 41 | AI47: =SUM(AI43:AI46) -> 456 | AK47: =SUM(AK43:AK46) -> 3 | AN47: =SUM(AN43:AN46) -> 0 | AO47: =SUM(AO43:AO46) -> 0 | AQ47: =SUM(AQ43:AQ46) -> 0
A50: Team Totals and Splits | K50: Taxi Squad* | S50: Injured Reserve | AD50: Team Totals and Splits | AM50: Taxi Squad* | AU50: Injured Reserve
C51: Targets | D51: Rec. | E51: Yds | F51: TDs | J51: Player | N51: Position | R51: Player | V51: Position | AE51: Targets | AF51: Rec. | AG51: Yds | AH51: TDs | AM51: Player | AQ51: Position | AU51: Player | AY51: Position
A52: Rec Totals | C52: =SUM(K22:K26,E32:E37,E43:E46) -> 548 | D52: =SUM(F43:F46,F32:F37,L22:L26) -> 365 | E52: =SUM(G43:G46,G32:G37,M22:M26) -> 3964 | F52: =SUM(O22:O26,I32:I37,I43:I46) -> 24 | J52: Nathan Carter | N52: RB | AC52: Rec Totals | AD52: =SUM(AM22:AM26,AG32:AG37,AG43:AG46) -> 583 | AE52: =SUM(AH43:AH46,AH32:AH37,AM22:AM26) -> 404 | AF52: =SUM(AI43:AI46,AI32:AI37,AN22:AN26) -> 3653 | AG52: =SUM(AQ22:AQ26,AK32:AK37,AK43:AK46) -> 27
A53: QB Totals | C53: =SUM(D17) -> 548 | D53: =SUM(E17) -> 365 | E53: =SUM(G17) -> 3964 | F53: =SUM(I17) -> 24 | J53: Jack Strand | N53: QB | AC53: QB Totals | AD53: =SUM(AF17) -> 583 | AE53: =SUM(AG17) -> 378 | AF53: =SUM(AI17) -> 4072 | AG53: =SUM(AK17) -> 27
A54: League Att Avg. | J54: Cash Jones | N54: RB | AC54: League Att Avg.
J55: Dylan Drummond | N55: WR
B56: Att | C56: Yards | D56: TDs | J56: Chris Blair | N56: WR | AD56: Att | AE56: Yards | AF56: TDs
A57: Rush Totals | B57: =SUM(N14:N16,D22:D26,L32:L37,L43:L46) -> 488 | C57: =SUM(O14:O16,E22:E26,M32:M37,M43:M46) -> 2198 | D57: =SUM(Q14:Q16,G22:G26,O32:O37,O43:O46) -> 16 | J57: Le'Meke Brockington | N57: WR | AC57: Rush Totals | AD57: =SUM(AP14:AP16,AF22:AF26,AN32:AN37,AN43:AN46) -> 421 | AE57: =SUM(AQ14:AQ16,AG22:AG26,AO32:AO37,AO43:AO46) -> 2231 | AF57: =SUM(AS14:AS16,AI22:AI26,AQ32:AQ37,AQ43:AQ46) -> 18
A58: League Att Avg. | J58: Joshua Simon | N58: TE | AC58: League Att Avg.
J59: Jack Velling | N59: TE
B60: Run | C60: Pass | J60: Antwane Wells | N60: WR | AD60: Run | AE60: Pass
A61: Run/Pass Pct | B61: =B57/(C53+B57) -> 0.47104247 | C61: =C53/(C53+B57) -> 0.52895753 | J61: Kristian Wilerson | N61: WR | AC61: Run/Pass Pct | AD61: =AD57/(AD53+AD57) -> 0.41932271 | AE61: =AD53/(AD53+AD57) -> 0.58067729 | AL61: *Projected options during offseason/Actual options during the season.
A62: League Average | J62: *Projected options during offseason/Actual options during the season. | AC62: League Average
A73: Team Projections Menu
I75: RSP Projections: Year 1 | N75: Adjustable Projections: Year 1 | T75: Offense Distribution
I76: RSP Projections: Year 2 | N76: Past Run/Pass Performances | T76: Run | U76: Pass
T77: =(N87+D97+L108+L117)/(N87+D97+L108+D87) -> #DIV/0! | U77: =D87/(D87+N87+D97+L108+L117) -> #DIV/0!
A80: RSP Projections: Year 2
D82: Passing | M82: Rushing | S82: Touches | W82: Fantasy Points
A83: QB | B83: Age | C83: G | D83: Att | E83: Comp | F83: Pct | G83: Yards | H83: Yds/Att | I83: TDs | J83: TDs/Att | K83: Int | L83: Int/Att | N83: Ratt | O83: Ryds | P83: Ryds/Att | Q83: TDs | R83: Tds/Att | T83: Touch % | U83: Pct Pass | V83: Pct Run | X83: Fpts | Y83: Adjusted
F84: =E84/D84 -> #DIV/0! | H84: =G84/D84 -> #DIV/0! | J84: =I84/D84 -> #DIV/0! | L84: =K84/D84 -> #DIV/0! | P84: =O84/N84 -> #DIV/0! | R84: =Q84/N84 -> #DIV/0! | T84: =(D84+N84)/($D$17+$N$17) -> 0 | U84: =D84/($D$17) -> 0 | V84: =N84/($N$17) -> 0 | X84: =(G84*0.05)+(I84*4)+(K84*-1)+(O84*0.1)+(Q84*6) -> 0 | Y84: =((G84*0.05)+(I84*4)+(K84*-1)+(O84*0.1)+(Q84*6))*0.4 -> 0
F85: =E85/D85 -> #DIV/0! | H85: =G85/D85 -> #DIV/0! | J85: =I85/D85 -> #DIV/0! | L85: =K85/D85 -> #DIV/0! | P85: =O85/N85 -> #DIV/0! | R85: =Q85/N85 -> #DIV/0! | T85: =(D85+N85)/($D$17+$N$17) -> 0 | U85: =D85/($D$17) -> 0 | V85: =N85/($N$17) -> 0 | X85: =(G85*0.05)+(I85*4)+(K85*-1)+(O85*0.1)+(Q85*6) -> 0 | Y85: =((G85*0.05)+(I85*4)+(K85*-1)+(O85*0.1)+(Q85*6))*0.4 -> 0
C86: 0 | F86: =E86/D86 -> #DIV/0! | H86: =G86/D86 -> #DIV/0! | J86: =I86/D86 -> #DIV/0! | L86: =K86/D86 -> #DIV/0! | P86: =O86/N86 -> #DIV/0! | R86: =Q86/N86 -> #DIV/0! | T86: =(D86+N86)/($D$17+$N$17) -> 0 | U86: =D86/($D$17) -> 0 | V86: =N86/($N$17) -> 0 | X86: =(G86*0.05)+(I86*4)+(K86*-1)+(O86*0.1)+(Q86*6) -> 0 | Y86: =((G86*0.05)+(I86*4)+(K86*-1)+(O86*0.1)+(Q86*6))*0.4 -> 0
A87: Total | D87: =SUM(D84:D86) -> 0 | E87: =SUM(E84:E86) -> 0 | G87: =SUM(G84:G86) -> 0 | I87: =SUM(I84:I86) -> 0 | K87: =SUM(K84:K86) -> 0 | N87: =SUM(N84:N86) -> 0 | O87: =SUM(O84:O86) -> 0 | Q87: =SUM(Q84:Q86) -> 0 | T87: =T84+T85+T86 -> 0 | U87: =D87/(D87+N87) -> #DIV/0! | V87: =N87/(N87+D87) -> #DIV/0!
A90: Rushing | I90: Receiving | S90: Touches | W90: Fantasy Points
A91: RB | B91: Age | C91: G | D91: Att | E91: Yards | F91: Yds/Att | G91: TDs | H91: TDs/Att | J91: Catch % | K91: Targets | L91: Rec | M91: Yds | N91: Yds/Rec | O91: TDs | P91: TDs/Rec | S91: RB | T91: Touch % | U91: Pct Pass | V91: Pct Run | X91: Fpts | Y91: PPR Fpts | Z91: .5 PPR
F92: =E92/D92 -> #DIV/0! | H92: =G92/D92 -> #DIV/0! | J92: =L92/K92 -> #DIV/0! | N92: =M92/L92 -> #DIV/0! | P92: =O92/L92 -> #DIV/0! | T92: =(D92+K92)/($D$27+$K$27+$N$17+$E$17+$L$38+$L$47) -> 0 | U92: =K92/($K$27+$F$38+$F$47) -> 0 | V92: =D92/($D$27+$N$17+$L$38+$L$47) -> 0 | X92: =(E92*0.1)+(G92*6)+(M92*0.1)+(O92*6) -> 0 | Y92: =(E92*0.1)+(G92*6)+(L92*1)+(M92*0.1)+(O92*6) -> 0 | Z92: =(E92*0.1)+(G92*6)+(L92*0.5)+(M92*0.1)+(O92*6) -> 0
F93: =E93/D93 -> #DIV/0! | H93: =G93/D93 -> #DIV/0! | J93: =L93/K93 -> #DIV/0! | N93: =M93/L93 -> #DIV/0! | P93: =O93/L93 -> #DIV/0! | T93: =(D93+K93)/($D$27+$K$27+$N$17+$E$17+$L$38+$L$47) -> 0 | U93: =K93/($K$27+$F$38+$F$47) -> 0 | V93: =D93/($D$27+$N$17+$L$38+$L$47) -> 0 | X93: =(E93*0.1)+(G93*6)+(M93*0.1)+(O93*6) -> 0 | Y93: =(E93*0.1)+(G93*6)+(L93*1)+(M93*0.1)+(O93*6) -> 0 | Z93: =(E93*0.1)+(G93*6)+(L93*0.5)+(M93*0.1)+(O93*6) -> 0
F94: =E94/D94 -> #DIV/0! | H94: =G94/D94 -> #DIV/0! | J94: =L94/K94 -> #DIV/0! | N94: =M94/L94 -> #DIV/0! | P94: =O94/L94 -> #DIV/0! | T94: =(D94+K94)/($D$27+$K$27+$N$17+$E$17+$L$38+$L$47) -> 0 | U94: =K94/($K$27+$F$38+$F$47) -> 0 | V94: =D94/($D$27+$N$17+$L$38+$L$47) -> 0 | X94: =(E94*0.1)+(G94*6)+(M94*0.1)+(O94*6) -> 0 | Y94: =(E94*0.1)+(G94*6)+(L94*1)+(M94*0.1)+(O94*6) -> 0 | Z94: =(E94*0.1)+(G94*6)+(L94*0.5)+(M94*0.1)+(O94*6) -> 0
F95: =E95/D95 -> #DIV/0! | H95: =G95/D95 -> #DIV/0! | J95: =L95/K95 -> #DIV/0! | N95: =M95/L95 -> #DIV/0! | P95: =O95/L95 -> #DIV/0! | T95: =(D95+K95)/($D$27+$K$27+$N$17+$E$17+$L$38+$L$47) -> 0 | U95: =K95/($K$27+$F$38+$F$47) -> 0 | V95: =D95/($D$27+$N$17+$L$38+$L$47) -> 0 | X95: =(E95*0.1)+(G95*6)+(M95*0.1)+(O95*6) -> 0 | Y95: =(E95*0.1)+(G95*6)+(L95*1)+(M95*0.1)+(O95*6) -> 0 | Z95: =(E95*0.1)+(G95*6)+(L95*0.5)+(M95*0.1)+(O95*6) -> 0
F96: =E96/D96 -> #DIV/0! | H96: =G96/D96 -> #DIV/0! | J96: =L96/K96 -> #DIV/0! | N96: =M96/L96 -> #DIV/0! | P96: =O96/L96 -> #DIV/0! | T96: =(D96+K96)/($D$27+$K$27+$N$17+$E$17+$L$38+$L$47) -> 0 | U96: =K96/($K$27+$F$38+$F$47) -> 0 | V96: =D96/($D$27+$N$17+$L$38+$L$47) -> 0 | X96: =(E96*0.1)+(G96*6)+(M96*0.1)+(O96*6) -> 0 | Y96: =(E96*0.1)+(G96*6)+(L96*1)+(M96*0.1)+(O96*6) -> 0 | Z96: =(E96*0.1)+(G96*6)+(L96*0.5)+(M96*0.1)+(O96*6) -> 0
A97: Total | D97: =SUM(D92:D96) -> 0 | E97: =SUM(E92:E96) -> 0 | G97: =SUM(G92:G96) -> 0 | K97: =SUM(K92:K96) -> 0 | L97: =SUM(L92:L96) -> 0 | M97: =SUM(M92:M96) -> 0 | O97: =SUM(O92:O96) -> 0
A100: Receiving | K100: Rushing | S100: Touches | W100: Fantasy Points
A101: WRs | B101: Age | C101: G | D101: Catch % | E101: Targets | F101: Rec | G101: Yds | H101: Yds/Rec | I101: TDs | J101: TDs/Rec | L101: Ratt | M101: Ryds | N101: Ryds/Att | O101: RTds | P101: TDs/Att | S101: WRs | T101: Touch % | U101: Pct Pass | V101: Pct Run | X101: Fpts | Y101: PPR Fpts | Z101: .5PPR
D102: =F102/E102 -> #DIV/0! | H102: =G102/F102 -> #DIV/0! | J102: =I102/F102 -> #DIV/0! | N102: =M102/L102 -> #DIV/0! | O102: 0 | P102: =O102/L102 -> #DIV/0! | T102: =(E102+L102)/($D$27+$L$27+$N$17+$E$47+$L$47) -> 0 | U102: =E102/($E$17) -> 0 | V102: =L102/($N$17+$D$27+$L$38+$L$47) -> 0 | X102: =(G102*0.1)+(I102*6)+(M102*0.1)+(O102*6) -> 0 | Y102: =(F102*1)+(G102*0.1)+(I102*6)+(M102*0.1)+(O102*6) -> 0 | Z102: =(F102*0.5)+(G102*0.1)+(I102*6)+(M102*0.1)+(O102*6) -> 0
D103: =F103/E103 -> #DIV/0! | H103: =G103/F103 -> #DIV/0! | J103: =I103/F103 -> #DIV/0! | N103: =M103/L103 -> #DIV/0! | O103: 0 | P103: =O103/L103 -> #DIV/0! | T103: =(E103+L103)/($D$27+$L$27+$N$17+$E$47+$L$47) -> 0 | U103: =E103/($E$17) -> 0 | V103: =L103/($N$17+$D$27+$L$38+$L$47) -> 0 | X103: =(G103*0.1)+(I103*6)+(M103*0.1)+(O103*6) -> 0 | Y103: =(F103*1)+(G103*0.1)+(I103*6)+(M103*0.1)+(O103*6) -> 0 | Z103: =(F103*0.5)+(G103*0.1)+(I103*6)+(M103*0.1)+(O103*6) -> 0
D104: =F104/E104 -> #DIV/0! | H104: =G104/F104 -> #DIV/0! | J104: =I104/F104 -> #DIV/0! | N104: =M104/L104 -> #DIV/0! | O104: 0 | P104: =O104/L104 -> #DIV/0! | T104: =(E104+L104)/($D$27+$L$27+$N$17+$E$47+$L$47) -> 0 | U104: =E104/($E$17) -> 0 | V104: =L104/($N$17+$D$27+$L$38+$L$47) -> 0 | X104: =(G104*0.1)+(I104*6)+(M104*0.1)+(O104*6) -> 0 | Y104: =(F104*1)+(G104*0.1)+(I104*6)+(M104*0.1)+(O104*6) -> 0 | Z104: =(F104*0.5)+(G104*0.1)+(I104*6)+(M104*0.1)+(O104*6) -> 0
D105: =F105/E105 -> #DIV/0! | H105: =G105/F105 -> #DIV/0! | J105: =I105/F105 -> #DIV/0! | N105: =M105/L105 -> #DIV/0! | O105: 0 | P105: =O105/L105 -> #DIV/0! | T105: =(E105+L105)/($D$27+$L$27+$N$17+$E$47+$L$47) -> 0 | U105: =E105/($E$17) -> 0 | V105: =L105/($N$17+$D$27+$L$38+$L$47) -> 0 | X105: =(G105*0.1)+(I105*6)+(M105*0.1)+(O105*6) -> 0 | Y105: =(F105*1)+(G105*0.1)+(I105*6)+(M105*0.1)+(O105*6) -> 0 | Z105: =(F105*0.5)+(G105*0.1)+(I105*6)+(M105*0.1)+(O105*6) -> 0
D106: =F106/E106 -> #DIV/0! | H106: =G106/F106 -> #DIV/0! | J106: =I106/F106 -> #DIV/0! | N106: =M106/L106 -> #DIV/0! | O106: 0 | P106: =O106/L106 -> #DIV/0! | T106: =(E106+L106)/($D$27+$L$27+$N$17+$E$47+$L$47) -> 0 | U106: =E106/($E$17) -> 0 | V106: =L106/($N$17+$D$27+$L$38+$L$47) -> 0 | X106: =(G106*0.1)+(I106*6)+(M106*0.1)+(O106*6) -> 0 | Y106: =(F106*1)+(G106*0.1)+(I106*6)+(M106*0.1)+(O106*6) -> 0 | Z106: =(F106*0.5)+(G106*0.1)+(I106*6)+(M106*0.1)+(O106*6) -> 0
D107: =F107/E107 -> #DIV/0! | H107: =G107/F107 -> #DIV/0! | J107: =I107/F107 -> #DIV/0! | N107: =M107/L107 -> #DIV/0! | O107: 0 | P107: =O107/L107 -> #DIV/0! | T107: =(E107+L107)/($D$27+$L$27+$N$17+$E$47+$L$47) -> 0 | U107: =E107/($E$17) -> 0 | V107: =L107/($N$17+$D$27+$L$38+$L$47) -> 0 | X107: =(G107*0.1)+(I107*6)+(M107*0.1)+(O107*6) -> 0 | Y107: =(F107*1)+(G107*0.1)+(I107*6)+(M107*0.1)+(O107*6) -> 0 | Z107: =(F107*0.5)+(G107*0.1)+(I107*6)+(M107*0.1)+(O107*6) -> 0
A108: Total | E108: =SUM(E102:E107) -> 0 | F108: =SUM(F102:F107) -> 0 | G108: =SUM(G102:G107) -> 0 | I108: =SUM(I102:I107) -> 0 | L108: =SUM(L102:L107) -> 0 | M108: =SUM(M102:M107) -> 0 | O108: =SUM(O102:O107) -> 0
A111: Receiving | K111: Rushing | S111: Touches | W111: Fantasy Points
A112: Tes | B112: Age | C112: G | D112: Catch % | E112: Targets | F112: Rec | G112: Yds | H112: Yds/Rec | I112: TDs | J112: TDs/Rec | L112: Ratt | M112: Ryds | N112: Ryds/Att | O112: RTDs | P112: TDs/Att | S112: Tes | T112: Touch % | U112: Pct Pass | V112: Pct Run | X112: Fpts | Y112: PPR Fpts | Z112: .5 PPR
D113: =F113/E113 -> #DIV/0! | H113: =G113/F113 -> #DIV/0! | J113: =I113/F113 -> #DIV/0! | L113: 0 | M113: 0 | N113: 0 | O113: 0 | P113: =O113/L113 -> #DIV/0! | T113: =(E113+L113)/($E$47+$L$47+$E$38+$L$38+$K$27+$D$27+$N$17) -> 0 | U113: =E113/($E$47+$E$38+$K$27) -> 0 | V113: =L113/($L$47+$L$38+$D$27+$N$17) -> 0 | X113: =(G113*0.1)+(I113*6)+(M113*0.1)+(O113*6) -> 0 | Y113: =(F113*1)+(G113*0.1)+(I113*6)+(M113*0.1)+(O113*6) -> 0 | Z113: =(F113*0.5)+(G113*0.1)+(I113*6)+(M113*0.1)+(O113*6) -> 0
D114: =F114/E114 -> #DIV/0! | H114: =G114/F114 -> #DIV/0! | J114: =I114/F114 -> #DIV/0! | L114: 0 | M114: 0 | N114: 0 | O114: 0 | P114: =O114/L114 -> #DIV/0! | T114: =(E114+L114)/($E$47+$L$47+$E$38+$L$38+$K$27+$D$27+$N$17) -> 0 | U114: =E114/($E$47+$E$38+$K$27) -> 0 | V114: =L114/($L$47+$L$38+$D$27+$N$17) -> 0 | X114: =(G114*0.1)+(I114*6)+(M114*0.1)+(O114*6) -> 0 | Y114: =(F114*1)+(G114*0.1)+(I114*6)+(M114*0.1)+(O114*6) -> 0 | Z114: =(F114*0.5)+(G114*0.1)+(I114*6)+(M114*0.1)+(O114*6) -> 0
D115: =F115/E115 -> #DIV/0! | H115: =G115/F115 -> #DIV/0! | J115: =I115/F115 -> #DIV/0! | L115: 0 | M115: 0 | N115: 0 | O115: 0 | P115: =O115/L115 -> #DIV/0! | T115: =(E115+L115)/($E$47+$L$47+$E$38+$L$38+$K$27+$D$27+$N$17) -> 0 | U115: =E115/($E$47+$E$38+$K$27) -> 0 | V115: =L115/($L$47+$L$38+$D$27+$N$17) -> 0 | X115: =(G115*0.1)+(I115*6)+(M115*0.1)+(O115*6) -> 0 | Y115: =(F115*1)+(G115*0.1)+(I115*6)+(M115*0.1)+(O115*6) -> 0 | Z115: =(F115*0.5)+(G115*0.1)+(I115*6)+(M115*0.1)+(O115*6) -> 0
D116: =F116/E116 -> #DIV/0! | H116: =G116/F116 -> #DIV/0! | J116: =I116/F116 -> #DIV/0! | N116: 0 | O116: 0 | P116: =O116/L116 -> #DIV/0! | T116: =(E116+L116)/($E$47+$L$47+$E$38+$L$38+$K$27+$D$27+$N$17) -> 0 | U116: =E116/($E$47+$E$38+$K$27) -> 0 | V116: =L116/($L$47+$L$38+$D$27+$N$17) -> 0 | X116: =(G116*0.1)+(I116*6)+(M116*0.1)+(O116*6) -> 0 | Y116: =(F116*1)+(G116*0.1)+(I116*6)+(M116*0.1)+(O116*6) -> 0 | Z116: =(F116*0.5)+(G116*0.1)+(I116*6)+(M116*0.1)+(O116*6) -> 0
A117: Total | E117: =SUM(E113:E116) -> 0 | F117: =SUM(F113:F116) -> 0 | G117: =SUM(G113:G116) -> 0 | I117: =SUM(I113:I116) -> 0 | L117: =SUM(L113:L116) -> 0 | M117: =SUM(M113:M116) -> 0 | O117: =SUM(O113:O116) -> 0
A120: Team Totals and Splits | K120: Taxi Squad* | S120: Injured Reserve
B121: Targets | C121: Rec. | D121: Yds | E121: TDs | J121: Player | N121: Position | R121: Player | V121: Position
A122: Rec Totals | B122: =SUM(K92:K96,E102:E107,E113:E116) -> 0 | C122: =SUM(F113:F116,F102:F107,L92:L96) -> 0 | D122: =SUM(G113:G116,G102:G107,M92:M96) -> 0 | E122: =SUM(O92:O96,I102:I107,I113:I116) -> 0
A123: QB Totals | B123: =SUM(D87) -> 0 | C123: =SUM(E87) -> 0 | D123: =SUM(G87) -> 0 | E123: =SUM(I87) -> 0
A124: League Att Avg.
B126: Att | C126: Yards | D126: TDs
A127: Rush Totals | B127: =SUM(N84:N86,D92:D96,L102:L107,L113:L116) -> 0 | C127: =SUM(O84:O86,E92:E96,M102:M107,M113:M116) -> 0 | D127: =SUM(Q84:Q86,G92:G96,O102:O107,O113:O116) -> 0
A128: League Att Avg.
B130: Run | C130: Pass
A131: Run/Pass Pct | B131: =B127/(B123+B127) -> #DIV/0! | C131: =B123/(B123+B127) -> #DIV/0! | J131: *Projected options during offseason/Actual options during the season.
A132: League Average
A141: 2-Year Team Historical Performance
I143: RSP Projections: Year 1 | N143: Adjustable Projections: Year 1
I144: RSP Projections: Year 2
E147: Historical Production | Q147: Touch Distribution
...

Sheet BALT
A1: Baltimore Ravens
A3: Team Projections Menu | AC3: Team Projections Menu
H5: RSP Projections: Year 1 | M5: Adjustable Projections: Year 1 | S5: Offense Distribution | AJ5: RSP Projections: Year 1 | AO5: Adjustable Projections: Year 1
H6: RSP Projections: Year 2 | M6: Past Run/Pass Performances | S6: Run | T6: Pass | AJ6: RSP Projections: Year 2
S7: =(N17+D27+L38+L47)/(N17+D27+L38+D17) -> 0.53134041 | T7: =D17/(D17+N17+D27+L38+L47) -> 0.46865959
A10: RSP Projections: Year 1 | AC10: Adjustable Projections: Year 1
C12: Passing | L12: Rushing | R12: Touches | V12: Fantasy Points | AE12: Passing | AN12: Rushing | AT12: Touches | AX12: Fantasy Points
A13: QB | B13: Age | C13: G | D13: Att | E13: Comp | F13: Pct | G13: Yards | H13: Yds/Att | I13: TDs | J13: TDs/Att | K13: Int | L13: Int/Att | N13: Ratt | O13: Ryds | P13: Ryds/Att | Q13: TDs | R13: Tds/Att | T13: Touch % | U13: Pct Pass | V13: Pct Run | X13: Fpts | Y13: Adjusted | AD13: QB | AE13: G | AF13: Att | AG13: Comp | AH13: Pct | AI13: Yards | AJ13: Yds/Att | AK13: TDs | AL13: TDs/Att | AM13: Int | AN13: Int/Att | AP13: Ratt | AQ13: Ryds | AR13: Ryds/Att | AS13: TDs | AT13: Tds/Att | AV13: Touch % | AW13: Pct Pass | AX13: Pct Run | AZ13: Fpts | BA13: Adjusted
A14: QB*Jackson, Lamar - BAL | B14: 29 | C14: 17 | D14: 486 | E14: 322 | F14: =E14/D14 -> 0.66255144 | G14: 4135 | H14: =G14/D14 -> 8.5082305 | I14: 38 | J14: =I14/D14 -> 0.0781893 | K14: 6 | L14: =K14/D14 -> 0.012345679 | N14: 151 | O14: 896 | P14: =O14/N14 -> 5.9337748 | Q14: 5 | R14: =Q14/N14 -> 0.033112583 | T14: =(D14+N14)/($D$17+$N$17) -> 1 | U14: =D14/($D$17) -> 1 | V14: =N14/($N$17) -> 1 | X14: =($G14*('Scoring Format'!$B$2))+($I14*('Scoring Format'!$B$5))+($K14*('Scoring Format'!$B$8))+($O14*('Scoring Format'!$B$3))+($Q14*('Scoring Format'!$B$6)) -> 472.35 | Y14: =(($G14*('Scoring Format'!$B$2))+($I14*('Scoring Format'!$B$5))+($K14*('Scoring Format'!$B$8))+($O14*('Scoring Format'!$B$3))+($Q14*('Scoring Format'!$B$6)))*0.4 -> 188.94 | AD14: Murray, Kyler - ARI | AF14: 583 | AG14: 378 | AH14: =AG14/AF14 -> 0.6483705 | AI14: 4072 | AJ14: =AI14/AF14 -> 6.9845626 | AK14: 27 | AL14: =AK14/AF14 -> 0.046312178 | AM14: 11 | AN14: =AM14/AF14 -> 0.018867925 | AP14: 100 | AQ14: 590 | AR14: =AQ14/AP14 -> 5.9 | AS14: 5 | AT14: =AS14/AP14 -> 0.05 | AV14: =(AF14+AP14)/(AF17+AP17) -> 1 | AW14: =AF14/(AP14+AF14) -> 0.85358712 | AX14: =AP14/(AF14+AP14) -> 0.14641288 | AZ14: =((AI14*0.05)+(AK14*4)+(AM14*-1)+(AQ14*0.1)+(AS14*6))*0.55 -> 214.28 | BA14: =((AI14*0.05)+(AK14*4)+(AM14*-1)+(AQ14*0.1)+(AS14*6))*0.4 -> 155.84
A15: QB*Huntley, Tyler-BAL | B15: 28 | F15: =E15/D15 -> #DIV/0! | H15: =G15/D15 -> #DIV/0! | J15: =I15/D15 -> #DIV/0! | L15: =K15/D15 -> #DIV/0! | P15: =O15/N15 -> #DIV/0! | R15: =Q15/N15 -> #DIV/0! | T15: =(D15+N15)/($D$17+$N$17) -> 0 | U15: =D15/($D$17) -> 0 | V15: =N15/($N$17) -> 0 | X15: =($G15*('Scoring Format'!$B$2))+($I15*('Scoring Format'!$B$5))+($K15*('Scoring Format'!$B$8))+($O15*('Scoring Format'!$B$3))+($Q15*('Scoring Format'!$B$6)) -> 0 | Y15: =(($G15*('Scoring Format'!$B$2))+($I15*('Scoring Format'!$B$5))+($K15*('Scoring Format'!$B$8))+($O15*('Scoring Format'!$B$3))+($Q15*('Scoring Format'!$B$6)))*0.4 -> 0 | AD15: McCoy, Colt - ARI | AF15: 0 | AG15: 0 | AH15: 0 | AI15: 0 | AK15: 0 | AL15: =AK15/AF15 -> #DIV/0! | AM15: 0 | AN15: =AM15/AF15 -> #DIV/0! | AP15: 0 | AQ15: 0 | AS15: 0 | AT15: =AS15/AP15 -> #DIV/0! | AV15: =(AF15+AP15)/(AD18+AN18) -> #DIV/0! | AW15: =AF15/(AP15+AF15) -> #DIV/0! | AX15: =AP15/(AF15+AP15) -> #DIV/0!
A16: QB*Pavia, Diego - BAL | B16: 24 | F16: =E16/D16 -> #DIV/0! | H16: =G16/D16 -> #DIV/0! | J16: =I16/D16 -> #DIV/0! | L16: =K16/D16 -> #DIV/0! | P16: =O16/N16 -> #DIV/0! | Q16: 0 | R16: =Q16/N16 -> #DIV/0! | T16: =(D16+N16)/($D$17+$N$17) -> 0 | U16: =D16/($D$17) -> 0 | V16: =N16/($N$17) -> 0 | X16: =($G16*('Scoring Format'!$B$2))+($I16*('Scoring Format'!$B$5))+($K16*('Scoring Format'!$B$8))+($O16*('Scoring Format'!$B$3))+($Q16*('Scoring Format'!$B$6)) -> 0 | Y16: =(($G16*('Scoring Format'!$B$2))+($I16*('Scoring Format'!$B$5))+($K16*('Scoring Format'!$B$8))+($O16*('Scoring Format'!$B$3))+($Q16*('Scoring Format'!$B$6)))*0.4 -> 0 | AD16: McDonald, Cole - ARI | AH16: =AG16/AF16 -> #DIV/0! | AJ16: =AI16/AF16 -> #DIV/0! | AL16: =AK16/AF16 -> #DIV/0! | AN16: =AM16/AF16 -> #DIV/0! | AR16: =AQ16/AP16 -> #DIV/0! | AT16: =AS16/AP16 -> #DIV/0! | AV16: =(AF16+AP16)/(AD20+AN20) -> #DIV/0! | AW16: =AF16/(AP16+AF16) -> #DIV/0! | AX16: =AP16/(AF16+AP16) -> #DIV/0! | AZ16: =((AI16*0.05)+(AK16*4)+(AM16*-1)+(AQ16*0.1)+(AS16*6))*0.55 -> 0 | BA16: =((AI16*0.05)+(AK16*4)+(AM16*-1)+(AQ16*0.1)+(AS16*6))*0.4 -> 0
A17: Total | D17: =SUM(D14:D16) -> 486 | E17: =SUM(E14:E16) -> 322 | G17: =SUM(G14:G16) -> 4135 | I17: =SUM(I14:I16) -> 38 | K17: =SUM(K14:K16) -> 6 | N17: =SUM(N14:N16) -> 151 | O17: =SUM(O14:O16) -> 896 | Q17: =SUM(Q14:Q16) -> 5 | T17: =T14+T15+T16 -> 1 | U17: =D17/(D17+N17) -> 0.76295133 | V17: =N17/(N17+D17) -> 0.23704867 | AD17: Total | AF17: =SUM(AF14:AF16) -> 583 | AG17: =SUM(AG14:AG16) -> 378 | AI17: =SUM(AI14:AI16) -> 4072 | AK17: =SUM(AK14:AK16) -> 27 | AM17: =SUM(AM14:AM16) -> 11 | AP17: =SUM(AP14:AP16) -> 100 | AQ17: =SUM(AQ14:AQ16) -> 590 | AS17: =SUM(AS14:AS16) -> 5 | AV17: =AV14+AV15+AV16 -> #DIV/0! | AW17: =AF17/(AF17+AP17) -> 0.85358712 | AX17: =AP17/(AP17+AF17) -> 0.14641288
A20: Rushing | H20: Receiving | R20: Touches | V20: Fantasy Points | AC20: Rushing | AJ20: Receiving | AT20: Touches | AX20: Fantasy Points
A21: RB | B21: Age | C21: G | D21: Att | E21: Yards | F21: Yds/Att | G21: TDs | H21: TDs/Att | J21: Catch % | K21: Targets | L21: Rec | M21: Yds | N21: Yds/Rec | O21: TDs | P21: TDs/Rec | S21: RB | T21: Touch % | U21: Pct Pass | V21: Pct Run | X21: Fpts | Y21: PPR Fpts | Z21: .5 PPR | AD21: RB | AE21: G | AF21: Att | AG21: Yards | AH21: Yds/Att | AI21: TDs | AJ21: TDs/Att | AL21: Catch % | AM21: Targets | AN21: Rec | AO21: Yds | AP21: Yds/Rec | AQ21: TDs | AR21: TDs/Rec | AV21: Touch % | AW21: Pct Pass | AX21: Pct Run | AZ21: Fpts | BA21: PPR Fpts
A22: RB*Henry, Derrick - BAL | B22: 32 | C22: 17 | D22: 316 | E22: 1753 | F22: =E22/D22 -> 5.5474684 | G22: 16 | H22: =G22/D22 -> 0.050632911 | J22: =L22/K22 -> 0.76190476 | K22: 21 | L22: 16 | M22: 160 | N22: =M22/L22 -> 10 | O22: 1 | P22: =O22/L22 -> 0.0625 | S22: Henry, Derrick - BAL | T22: =(D22+K22)/($D$27+$K$27+$N$17+$E$17+$L$38+$L$47) -> 0.36042781 | U22: =K22/($K$27+$F$38+$F$47) -> 0.0625 | V22: =D22/($D$27+$N$17+$L$38+$L$47) -> 0.57350272 | X22: =($E22*('Scoring Format'!$B$3))+($G22*('Scoring Format'!$B$6))+($M22*('Scoring Format'!$B$4))+($O22*('Scoring Format'!$B$7)) -> 293.3 | Y22: =($E22*('Scoring Format'!$B$3))+($G22*('Scoring Format'!$B$6))+(L22*1)+($M22*('Scoring Format'!$B$4))+($O22*('Scoring Format'!$B$7)) -> 309.3 | Z22: =($E22*('Scoring Format'!$B$3))+($G22*('Scoring Format'!$B$6))+(L22*0.5)+($M22*('Scoring Format'!$B$4))+($O22*('Scoring Format'!$B$7)) -> 301.3 | AD22: Conner, James - ARI | AF22: 200 | AG22: 1040 | AH22: =AG22/AF22 -> 5.2 | AI22: 7 | AJ22: =AI22/AF22 -> 0.035 | AL22: =AN22/AM22 -> 0.8 | AM22: 70 | AN22: 56 | AO22: 364 | AP22: =AO22/AN22 -> 6.5 | AQ22: 2 | AR22: =AQ22/AN22 -> 0.035714286 | AV22: =(#REF!+AM22)/(#REF!+AM25) -> #REF! | AW22: =#REF!/(AM22+#REF!) -> #REF! | AX22: =AM22/(#REF!+AM22) -> #REF! | AZ22: =(#REF!*0.1)+(AF22*6)+(AL22*0.1)+(AN22*6) -> #REF! | BA22: =(#REF!*0.1)+(AF22*6)+(AK22*1)+(AL22*0.1)+(AN22*6) -> #REF!
A23: RB*Ali, Rasheen - BAL | B23: 25 | C23: 17 | D23: 9 | E23: 32 | F23: =E23/D23 -> 3.5555556 | G23: 0 | H23: =G23/D23 -> 0 | J23: =L23/K23 -> 0.8 | K23: 10 | L23: 8 | M23: 56 | N23: =M23/L23 -> 7 | O23: 0 | P23: =O23/L23 -> 0 | S23: Ali, Rasheen - BAL | T23: =(D23+K23)/($D$27+$K$27+$N$17+$E$17+$L$38+$L$47) -> 0.020320856 | U23: =K23/($K$27+$F$38+$F$47) -> 0.029761905 | V23: =D23/($D$27+$N$17+$L$38+$L$47) -> 0.016333938 | X23: =($E23*('Scoring Format'!$B$3))+($G23*('Scoring Format'!$B$6))+($M23*('Scoring Format'!$B$4))+($O23*('Scoring Format'!$B$7)) -> 8.8 | Y23: =($E23*('Scoring Format'!$B$3))+($G23*('Scoring Format'!$B$6))+(L23*1)+($M23*('Scoring Format'!$B$4))+($O23*('Scoring Format'!$B$7)) -> 16.8 | Z23: =($E23*('Scoring Format'!$B$3))+($G23*('Scoring Format'!$B$6))+(L23*0.5)+($M23*('Scoring Format'!$B$4))+($O23*('Scoring Format'!$B$7)) -> 12.8 | AD23: Edmonds, Chase - ARI | AF23: 96 | AG23: 445 | AH23: =AG23/AF23 -> 4.6354167 | AI23: 6 | AJ23: =AI23/AF23 -> 0.0625 | AL23: =AN23/AM23 -> 0.58333333 | AM23: 24 | AN23: 14 | AO23: 110 | AP23: =AO23/AN23 -> 7.8571429 | AQ23: 2 | AR23: =AQ23/AN23 -> 0.14285714 | AV23: =(#REF!+AM23)/(#REF!+AM26) -> #REF! | AW23: =#REF!/(AM23+#REF!) -> #REF! | AX23: =AM23/(#REF!+AM23) -> #REF! | AZ23: =(#REF!*0.1)+(AF23*6)+(AL23*0.1)+(AN23*6) -> #REF! | BA23: =(#REF!*0.1)+(AF23*6)+(AK23*1)+(AL23*0.1)+(AN23*6) -> #REF!
A24: RB*Hill, Justice - BAL | B24: 29 | C24: 17 | D24: 55 | E24: 305 | F24: =E24/D24 -> 5.5454545 | G24: 2 | H24: =G24/D24 -> 0.036363636 | J24: =L24/K24 -> 0.8 | K24: 25 | L24: 20 | M24: 160 | N24: =M24/L24 -> 8 | O24: 2 | P24: =O24/L24 -> 0.1 | S24: Hill, Justice - BAL | T24: =(D24+K24)/($D$27+$K$27+$N$17+$E$17+$L$38+$L$47) -> 0.085561497 | U24: =K24/($K$27+$F$38+$F$47) -> 0.074404762 | V24: =D24/($D$27+$N$17+$L$38+$L$47) -> 0.099818512 | X24: =($E24*('Scoring Format'!$B$3))+($G24*('Scoring Format'!$B$6))+($M24*('Scoring Format'!$B$4))+($O24*('Scoring Format'!$B$7)) -> 70.5 | Y24: =($E24*('Scoring Format'!$B$3))+($G24*('Scoring Format'!$B$6))+(L24*1)+($M24*('Scoring Format'!$B$4))+($O24*('Scoring Format'!$B$7)) -> 90.5 | Z24: =($E24*('Scoring Format'!$B$3))+($G24*('Scoring Format'!$B$6))+(L24*0.5)+($M24*('Scoring Format'!$B$4))+($O24*('Scoring Format'!$B$7)) -> 80.5 | AD24: Benjamin, Eno - ARI | AF24: 8 | AG24: 28 | AH24: =AG24/AF24 -> 3.5 | AI24: 0 | AJ24: =AI24/AF24 -> 0 | AL24: =AN24/AM24 -> 0.5 | AM24: 4 | AN24: 2 | AO24: 17 | AP24: =AO24/AN24 -> 8.5 | AQ24: 0 | AR24: =AQ24/AN24 -> 0 | AV24: =(#REF!+AM24)/(#REF!+AK30) -> #REF! | AW24: =#REF!/(AM24+#REF!) -> #REF! | AX24: =AM24/(#REF!+AM24) -> #REF! | AZ24: =(#REF!*0.1)+(AF24*6)+(AL24*0.1)+(AN24*6) -> #REF! | BA24: =(#REF!*0.1)+(AF24*6)+(AK24*1)+(AL24*0.1)+(AN24*6) -> #REF!
A25: RB*Randall, Adam - BAL | B25: 21 | C25: 17 | D25: 10 | E25: 36 | F25: =E25/D25 -> 3.6 | G25: 0 | H25: =G25/D25 -> 0 | J25: =L25/K25 -> 0.66666667 | K25: 6 | L25: 4 | M25: 16 | N25: =M25/L25 -> 4 | O25: 0 | P25: =O25/L25 -> 0 | S25: Randall, Adam - BAL | T25: =(D25+K25)/($D$27+$K$27+$N$17+$E$17+$L$38+$L$47) -> 0.017112299 | U25: =K25/($K$27+$F$38+$F$47) -> 0.017857143 | V25: =D25/($D$27+$N$17+$L$38+$L$47) -> 0.01814882 | X25: =($E25*('Scoring Format'!$B$3))+($G25*('Scoring Format'!$B$6))+($M25*('Scoring Format'!$B$4))+($O25*('Scoring Format'!$B$7)) -> 5.2 | Y25: =($E25*('Scoring Format'!$B$3))+($G25*('Scoring Format'!$B$6))+(L25*1)+($M25*('Scoring Format'!$B$4))+($O25*('Scoring Format'!$B$7)) -> 9.2 | Z25: =($E25*('Scoring Format'!$B$3))+($G25*('Scoring Format'!$B$6))+(L25*0.5)+($M25*('Scoring Format'!$B$4))+($O25*('Scoring Format'!$B$7)) -> 7.2 | AD25: Ward, Jonathan - ARI | AH25: =AG25/AF25 -> #DIV/0! | AI25: 0 | AJ25: =AI25/AF25 -> #DIV/0! | AL25: =AN25/AM25 -> #DIV/0! | AP25: =AO25/AN25 -> #DIV/0! | AQ25: 0 | AR25: =AQ25/AN25 -> #DIV/0! | AV25: =(#REF!+AM25)/(#REF!+AM31) -> #REF! | AW25: =#REF!/(AM25+#REF!) -> #REF! | AX25: =AM25/(#REF!+AM25) -> #REF! | AZ25: =(#REF!*0.1)+(AF25*6)+(AL25*0.1)+(AN25*6) -> #REF! | BA25: =(#REF!*0.1)+(AF25*6)+(AK25*1)+(AL25*0.1)+(AN25*6) -> #REF!
F26: =E26/D26 -> #DIV/0! | G26: 0 | H26: =G26/D26 -> #DIV/0! | J26: =L26/K26 -> #DIV/0! | N26: =M26/L26 -> #DIV/0! | O26: 0 | P26: =O26/L26 -> #DIV/0! | T26: =(D26+K26)/($D$27+$K$27+$N$17+$E$17+$L$38+$L$47) -> 0 | U26: =K26/($K$27+$F$38+$F$47) -> 0 | V26: =D26/($D$27+$N$17+$L$38+$L$47) -> 0 | X26: =($E26*('Scoring Format'!$B$3))+($G26*('Scoring Format'!$B$6))+($M26*('Scoring Format'!$B$4))+($O26*('Scoring Format'!$B$7)) -> 0 | Y26: =($E26*('Scoring Format'!$B$3))+($G26*('Scoring Format'!$B$6))+(L26*1)+($M26*('Scoring Format'!$B$4))+($O26*('Scoring Format'!$B$7)) -> 0 | Z26: =($E26*('Scoring Format'!$B$3))+($G26*('Scoring Format'!$B$6))+(L26*0.5)+($M26*('Scoring Format'!$B$4))+($O26*('Scoring Format'!$B$7)) -> 0 | AD26: Muhammad, Khalfani - ARI | AH26: =AG26/AF26 -> #DIV/0! | AJ26: =AI26/AF26 -> #DIV/0! | AL26: =AN26/AM26 -> #DIV/0! | AQ26: =(AG26*0.1)+(AI26*6)+(AN26*0.1)+(AP26*6) -> 0 | AR26: =AQ26/AN26 -> #DIV/0! | AV26: =(#REF!+AM26)/(#REF!+AM32) -> #REF! | AW26: =#REF!/(AM26+#REF!) -> #REF! | AX26: =AM26/(#REF!+AM26) -> #REF! | AZ26: =(#REF!*0.1)+(AF26*6)+(AJ26*1)+(AK26*0.1)+(AM26*6) -> #REF! | BA26: =(#REF!*0.1)+(AF26*6)+(AK26*1)+(AL26*0.1)+(AN26*6) -> #REF!
A27: Total | D27: =SUM(D22:D26) -> 390 | E27: =SUM(E22:E26) -> 2126 | G27: =SUM(G22:G26) -> 18 | K27: =SUM(K22:K26) -> 62 | L27: =SUM(L22:L26) -> 48 | M27: =SUM(M22:M26) -> 392 | O27: =SUM(O22:O26) -> 3 | AD27: Total | AF27: =SUM(AF22:AF26) -> 304 | AG27: =SUM(AG22:AG26) -> 1513 | AI27: =SUM(AI22:AI26) -> 13 | AM27: =SUM(AM22:AM26) -> 98 | AN27: =SUM(AN22:AN26) -> 72 | AO27: =SUM(AO22:AO26) -> 491 | AQ27: =SUM(AQ22:AQ26) -> 4
A30: Receiving | J30: Rushing | R30: Touches | V30: Fantasy Points | AC30: Receiving | AL30: Rushing | AT30: Touches | AX30: Fantasy Points
A31: WRs | B31: Age | C31: G | D31: Catch % | E31: Targets | F31: Rec | G31: Yds | H31: Yds/Rec | I31: TDs | J31: TDs/Rec | L31: Ratt | M31: Ryds | N31: Ryds/Att | O31: RTds | P31: TDs/Att | S31: WRs | T31: Touch % | U31: Pct Pass | V31: Pct Run | X31: Fpts | Y31: PPR Fpts | Z31: .5PPR | AD31: WRs | AE31: G | AF31: Catch % | AG31: Targets | AH31: Rec | AI31: Yds | AJ31: Yds/Rec | AK31: TDs | AL31: TDs/Rec | AN31: Ratt | AO31: Ryds | AP31: Ryds/Att | AQ31: RTds | AR31: TDs/Att | AV31: Touch % | AW31: Pct Pass | AX31: Pct Run | AZ31: Fpts | BA31: PPR Fpts
A32: WR*Bateman, Rashod - BAL | B32: 27 | C32: 17 | D32: =F32/E32 -> 0.625 | E32: 88 | F32: 55 | G32: 863 | H32: =G32/F32 -> 15.690909 | I32: 7 | J32: =I32/F32 -> 0.12727273 | N32: =M32/L32 -> #DIV/0! | O32: 0 | P32: =O32/L32 -> #DIV/0! | S32: Bateman, Rashod - BAL | T32: =(E32+L32)/($D$27+$L$27+$N$17+$E$47+$L$47) -> 0.11859838 | U32: =E32/($E$17) -> 0.27329193 | V32: =L32/($N$17+$D$27+$L$38+$L$47) -> 0 | X32: =($G32*('Scoring Format'!$B$4))+($I32*'Scoring Format'!$B$7)+($M32*('Scoring Format'!$B$3))+($O32*('Scoring Format'!$B$6)) -> 128.3 | Y32: =(F32*1)+(($G32*('Scoring Format'!$B$4))+($I32*'Scoring Format'!$B$7)+($M32*('Scoring Format'!$B$3))+($O32*('Scoring Format'!$B$6))) -> 183.3 | Z32: =(F32*0.5)+(($G32*('Scoring Format'!$B$4))+($I32*'Scoring Format'!$B$7)+($M32*('Scoring Format'!$B$3))+($O32*('Scoring Format'!$B$6))) -> 155.8 | AD32: Green, A.J. - ARI | AF32: =AH32/AG32 -> 0.60747664 | AG32: 107 | AH32: 65 | AI32: 710 | AJ32: =AI32/AH32 -> 10.923077 | AK32: 6 | AL32: =AK32/AH32 -> 0.092307692 | AN32: 0 | AO32: 0 | AP32: =AO32/AN32 -> #DIV/0! | AQ32: 0 | AR32: =AQ32/AN32 -> #DIV/0! | AV32: =(#REF!+AK32)/(#REF!+AK35) -> #REF! | AW32: =#REF!/(AK32+#REF!) -> #REF! | AX32: =AK32/(#REF!+AK32) -> #REF! | AZ32: =(AI32*0.1)+(AK32*6)+(AO32*0.1)+(AQ32*6) -> 107 | BA32: =(AH32*1)+(AI32*0.1)+(AK32*6)+(AO32*0.1)+(AQ32*6) -> 172
A33: WR*Sarratt, Elijah - BAL | B33: 23 | C33: 17 | D33: =F33/E33 -> 0.625 | E33: 24 | F33: 15 | G33: 180 | H33: =G33/F33 -> 12 | I33: 2 | J33: =I33/F33 -> 0.13333333 | N33: =M33/L33 -> #DIV/0! | O33: 0 | P33: =O33/L33 -> #DIV/0! | S33: Sarratt, Elijah - BAL | T33: =(E33+L33)/($D$27+$L$27+$N$17+$E$47+$L$47) -> 0.032345013 | U33: =E33/($E$17) -> 0.074534161 | V33: =L33/($N$17+$D$27+$L$38+$L$47) -> 0 | X33: =($G33*('Scoring Format'!$B$4))+($I33*'Scoring Format'!$B$7)+($M33*('Scoring Format'!$B$3))+($O33*('Scoring Format'!$B$6)) -> 30 | Y33: =(F33*1)+(($G33*('Scoring Format'!$B$4))+($I33*'Scoring Format'!$B$7)+($M33*('Scoring Format'!$B$3))+($O33*('Scoring Format'!$B$6))) -> 45 | Z33: =(F33*0.5)+(($G33*('Scoring Format'!$B$4))+($I33*'Scoring Format'!$B$7)+($M33*('Scoring Format'!$B$3))+($O33*('Scoring Format'!$B$6))) -> 37.5 | AD33: Kirk, Christian- ARI | AF33: =AH33/AG33 -> 0.63333333 | AG33: 120 | AH33: 76 | AI33: 892 | AJ33: =AI33/AH33 -> 11.736842 | AK33: 5 | AL33: =AK33/AH33 -> 0.065789474 | AN33: 12 | AO33: 108 | AP33: =AO33/AN33 -> 9 | AQ33: 0 | AR33: =AQ33/AN33 -> 0 | AV33: =(#REF!+AK33)/(#REF!+AK36) -> #REF! | AW33: =#REF!/(AK33+#REF!) -> #REF! | AX33: =AK33/(#REF!+AK33) -> #REF! | AZ33: =(AI33*0.1)+(AK33*6)+(AO33*0.1)+(AQ33*6) -> 130 | BA33: =(AH33*1)+(AI33*0.1)+(AK33*6)+(AO33*0.1)+(AQ33*6) -> 206
A34: WR*Flowers, Zay - BAL | B34: 26 | C34: 17 | D34: =F34/E34 -> 0.64166667 | E34: 120 | F34: 77 | G34: 1101 | H34: =G34/F34 -> 14.298701 | I34: 8 | J34: =I34/F34 -> 0.1038961 | L34: 10 | M34: 60 | N34: =M34/L34 -> 6 | P34: =O34/L34 -> 0 | S34: Flowers, Zay - BAL | T34: =(E34+L34)/($D$27+$L$27+$N$17+$E$47+$L$47) -> 0.17520216 | U34: =E34/($E$17) -> 0.37267081 | V34: =L34/($N$17+$D$27+$L$38+$L$47) -> 0.01814882 | X34: =($G34*('Scoring Format'!$B$4))+($I34*'Scoring Format'!$B$7)+($M34*('Scoring Format'!$B$3))+($O34*('Scoring Format'!$B$6)) -> 164.1 | Y34: =(F34*1)+(($G34*('Scoring Format'!$B$4))+($I34*'Scoring Format'!$B$7)+($M34*('Scoring Format'!$B$3))+($O34*('Scoring Format'!$B$6))) -> 241.1 | Z34: =(F34*0.5)+(($G34*('Scoring Format'!$B$4))+($I34*'Scoring Format'!$B$7)+($M34*('Scoring Format'!$B$3))+($O34*('Scoring Format'!$B$6))) -> 202.6 | AD34: Isabella, Andy - ARI | AF34: =AH34/AG34 -> 0.55 | AG34: 40 | AH34: 22 | AI34: 325 | AJ34: =AI34/AH34 -> 14.772727 | AK34: 2 | AL34: =AK34/AH34 -> 0.090909091 | AN34: 5 | AO34: 20 | AP34: =AO34/AN34 -> 4 | AQ34: 0 | AR34: =AQ34/AN34 -> 0 | AV34: =(#REF!+AK34)/(#REF!+AK37) -> #REF! | AW34: =#REF!/(AK34+#REF!) -> #REF! | AX34: =AK34/(#REF!+AK34) -> #REF! | AZ34: =(AI34*0.1)+(AK34*6)+(AO34*0.1)+(AQ34*6) -> 46.5 | BA34: =(AH34*1)+(AI34*0.1)+(AK34*6)+(AO34*0.1)+(AQ34*6) -> 68.5
A35: WR*Lane, Ja'Kobi - BAL | B35: 21 | C35: 12 | D35: =F35/E35 -> 0.47058824 | E35: 17 | F35: 8 | G35: 105 | H35: =G35/F35 -> 13.125 | I35: 3 | J35: =I35/F35 -> 0.375 | N35: =M35/L35 -> #DIV/0! | O35: 0 | P35: =O35/L35 -> #DIV/0! | S35: Lane, Ja'Kobi - BAL | T35: =(E35+L35)/($D$27+$L$27+$N$17+$E$47+$L$47) -> 0.022911051 | U35: =E35/($E$17) -> 0.052795031 | V35: =L35/($N$17+$D$27+$L$38+$L$47) -> 0 | X35: =($G35*('Scoring Format'!$B$4))+($I35*'Scoring Format'!$B$7)+($M35*('Scoring Format'!$B$3))+($O35*('Scoring Format'!$B$6)) -> 28.5 | Y35: =(F35*1)+(($G35*('Scoring Format'!$B$4))+($I35*'Scoring Format'!$B$7)+($M35*('Scoring Format'!$B$3))+($O35*('Scoring Format'!$B$6))) -> 36.5 | Z35: =(F35*0.5)+(($G35*('Scoring Format'!$B$4))+($I35*'Scoring Format'!$B$7)+($M35*('Scoring Format'!$B$3))+($O35*('Scoring Format'!$B$6))) -> 32.5 | AD35: Hopkins, DeAndre - ARI | AF35: =AH35/AG35 -> 0.66206897 | AG35: 145 | AH35: 96 | AI35: 1098 | AJ35: =AI35/AH35 -> 11.4375 | AK35: 7 | AL35: =AK35/AH35 -> 0.072916667 | AN35: 0 | AO35: 0 | AP35: =AO35/AN35 -> #DIV/0! | AQ35: 0 | AR35: =AQ35/AN35 -> #DIV/0! | AV35: =(#REF!+AK35)/(#REF!+AK38) -> #REF! | AW35: =#REF!/(AK35+#REF!) -> #REF! | AX35: =AK35/(#REF!+AK35) -> #REF! | AZ35: =(AI35*0.1)+(AK35*6)+(AO35*0.1)+(AQ35*6) -> 151.8 | BA35: =(AH35*1)+(AI35*0.1)+(AK35*6)+(AO35*0.1)+(AQ35*6) -> 247.8
A36: WR*Walker, Devontez - BAL | B36: 25 | C36: 17 | D36: =F36/E36 -> 0.54545455 | E36: 22 | F36: 12 | G36: 266 | H36: =G36/F36 -> 22.166667 | I36: 3 | J36: =I36/F36 -> 0.25 | N36: =M36/L36 -> #DIV/0! | O36: 0 | P36: =O36/L36 -> #DIV/0! | S36: Walker, Devontez - BAL | T36: =(E36+L36)/($D$27+$L$27+$N$17+$E$47+$L$47) -> 0.029649596 | U36: =E36/($E$17) -> 0.068322981 | V36: =L36/($N$17+$D$27+$L$38+$L$47) -> 0 | X36: =($G36*('Scoring Format'!$B$4))+($I36*'Scoring Format'!$B$7)+($M36*('Scoring Format'!$B$3))+($O36*('Scoring Format'!$B$6)) -> 44.6 | Y36: =(F36*1)+(($G36*('Scoring Format'!$B$4))+($I36*'Scoring Format'!$B$7)+($M36*('Scoring Format'!$B$3))+($O36*('Scoring Format'!$B$6))) -> 56.6 | Z36: =(F36*0.5)+(($G36*('Scoring Format'!$B$4))+($I36*'Scoring Format'!$B$7)+($M36*('Scoring Format'!$B$3))+($O36*('Scoring Format'!$B$6))) -> 50.6 | AD36: Johnson, KeeSean - ARI | AF36: =AH36/AG36 -> 0.6 | AG36: 10 | AH36: 6 | AI36: 100 | AJ36: =AI36/AH36 -> 16.666667 | AK36: 0 | AL36: =AK36/AH36 -> 0 | AN36: 0 | AO36: 0 | AP36: =AO36/AN36 -> #DIV/0! | AQ36: 0 | AR36: =AQ36/AN36 -> #DIV/0! | AV36: =(#REF!+AK36)/(#REF!+AI41) -> #REF! | AW36: =#REF!/(AK36+#REF!) -> #REF! | AX36: =AK36/(#REF!+AK36) -> #REF! | AZ36: =(AI36*0.1)+(AK36*6)+(AO36*0.1)+(AQ36*6) -> 10 | BA36: =(AH36*1)+(AI36*0.1)+(AK36*6)+(AO36*0.1)+(AQ36*6) -> 16
A37: WR*Guillory, Xavier - BAL | B37: 24 | D37: =F37/E37 -> #DIV/0! | H37: =G37/F37 -> #DIV/0! | J37: =I37/F37 -> #DIV/0! | L37: 0 | M37: 0 | N37: =M37/L37 -> #DIV/0! | O37: 0 | P37: =O37/L37 -> #DIV/0! | S37: Guillory, Xavier - BAL | T37: =(E37+L37)/($D$27+$L$27+$N$17+$E$47+$L$47) -> 0 | U37: =E37/($E$17) -> 0 | V37: =L37/($N$17+$D$27+$L$38+$L$47) -> 0 | X37: =($G37*('Scoring Format'!$B$4))+($I37*'Scoring Format'!$B$7)+($M37*('Scoring Format'!$B$3))+($O37*('Scoring Format'!$B$6)) -> 0 | Y37: =(F37*1)+(($G37*('Scoring Format'!$B$4))+($I37*'Scoring Format'!$B$7)+($M37*('Scoring Format'!$B$3))+($O37*('Scoring Format'!$B$6))) -> 0 | Z37: =(F37*0.5)+(($G37*('Scoring Format'!$B$4))+($I37*'Scoring Format'!$B$7)+($M37*('Scoring Format'!$B$3))+($O37*('Scoring Format'!$B$6))) -> 0 | AD37: Moore, Rondale - ARI | AF37: =AH37/AG37 -> #DIV/0! | AL37: =AK37/AH37 -> #DIV/0! | AP37: =AO37/AN37 -> #DIV/0! | AR37: =AQ37/AN37 -> #DIV/0! | AV37: =(#REF!+AK37)/(#REF!+AK42) -> #REF! | AW37: =#REF!/(AK37+#REF!) -> #REF! | AX37: =AK37/(#REF!+AK37) -> #REF!
A38: Total | E38: =SUM(E32:E37) -> 271 | F38: =SUM(F32:F37) -> 167 | G38: =SUM(G32:G37) -> 2515 | I38: =SUM(I32:I37) -> 23 | L38: =SUM(L32:L37) -> 10 | M38: =SUM(M32:M37) -> 60 | O38: =SUM(O32:O37) -> 0 | AD38: Total | AG38: =SUM(AG32:AG37) -> 422 | AH38: =SUM(AH32:AH37) -> 265 | AI38: =SUM(AI32:AI37) -> 3125 | AK38: =SUM(AK32:AK37) -> 20 | AN38: =SUM(AN32:AN37) -> 17 | AO38: =SUM(AO32:AO37) -> 128 | AQ38: =SUM(AQ32:AQ37) -> 0
A41: Receiving | J41: Rushing | R41: Touches | V41: Fantasy Points | AC41: Receiving | AL41: Rushing | AT41: Touches | AX41: Fantasy Points
A42: Tes | B42: Age | C42: G | D42: Catch % | E42: Targets | F42: Rec | G42: Yds | H42: Yds/Rec | I42: TDs | J42: TDs/Rec | L42: Ratt | M42: Ryds | N42: Ryds/Att | O42: RTDs | P42: TDs/Att | S42: Tes | T42: Touch % | U42: Pct Pass | V42: Pct Run | X42: Fpts | Y42: PPR Fpts | Z42: .5 PPR | AD42: Tes | AE42: G | AF42: Catch % | AG42: Targets | AH42: Rec | AI42: Yds | AJ42: Yds/Rec | AK42: TDs | AL42: TDs/Rec | AN42: Ratt | AO42: Ryds | AP42: Ryds/Att | AQ42: RTDs | AR42: TDs/Att | AV42: Touch % | AW42: Pct Pass | AX42: Pct Run | AZ42: Fpts | BA42: PPR Fpts
A43: TE*Andrews, Mark - BAL | B43: 31 | C43: 17 | D43: =F43/E43 -> 0.68421053 | E43: 95 | F43: 65 | G43: 804 | H43: =G43/F43 -> 12.369231 | I43: 9 | J43: =I43/F43 -> 0.13846154 | L43: 0 | M43: 0 | N43: 0 | O43: 0 | P43: =O43/L43 -> #DIV/0! | S43: Andrews, Mark - BAL | T43: =(E43+L43)/($E$47+$L$47+$E$38+$L$38+$K$27+$D$27+$N$17) -> 0.091610415 | U43: =E43/($E$47+$E$38+$K$27) -> 0.19547325 | V43: =L43/($L$47+$L$38+$D$27+$N$17) -> 0 | X43: =($G43*('Scoring Format'!$B$4))+($I43*'Scoring Format'!$B$7)+($M43*('Scoring Format'!$B$3))+($O43*('Scoring Format'!$B$6)) -> 134.4 | Y43: =(F43*1)+(($G43*('Scoring Format'!$B$4))+($I43*'Scoring Format'!$B$7)+($M43*('Scoring Format'!$B$3))+($O43*('Scoring Format'!$B$6))) -> 199.4 | Z43: =(F43*0.5)+(($G43*('Scoring Format'!$B$4))+($I43*'Scoring Format'!$B$7)+($M43*('Scoring Format'!$B$3))+($O43*('Scoring Format'!$B$6))) -> 166.9 | AD43: Williams, Maxx - ARI | AF43: =AH43/AG43 -> 0.5625 | AG43: 16 | AH43: 9 | AI43: 108 | AJ43: =AI43/AH43 -> 12 | AK43: 1 | AL43: =AK43/AH43 -> 0.11111111 | AN43: 0 | AO43: 0 | AP43: 0 | AQ43: 0 | AR43: =AQ43/AN43 -> #DIV/0! | AV43: =(#REF!+AK43)/(#REF!+AK46) -> #REF! | AW43: =#REF!/(AK43+#REF!) -> #REF! | AX43: =AK43/(#REF!+AK43) -> #REF! | AZ43: =(AI43*0.1)+(AK43*6)+(AO43*0.1)+(AQ43*6) -> 16.8 | BA43: =(AH43*1)+(AI43*0.1)+(AK43*6)+(AO43*0.1)+(AQ43*6) -> 25.8
A44: TE*Ricard, Patrick - BAL | B44: 32 | C44: 17 | D44: =F44/E44 -> 0.6 | E44: 5 | F44: 3 | G44: 22 | H44: =G44/F44 -> 7.3333333 | I44: 1 | J44: =I44/F44 -> 0.33333333 | P44: =O44/L44 -> #DIV/0! | S44: Richard, Patrick - BAL | T44: =(E44+L44)/($E$47+$L$47+$E$38+$L$38+$K$27+$D$27+$N$17) -> 0.0048216008 | U44: =E44/($E$47+$E$38+$K$27) -> 0.010288066 | V44: =L44/($L$47+$L$38+$D$27+$N$17) -> 0 | X44: =($G44*('Scoring Format'!$B$4))+($I44*'Scoring Format'!$B$7)+($M44*('Scoring Format'!$B$3))+($O44*('Scoring Format'!$B$6)) -> 8.2 | Y44: =(F44*1)+(($G44*('Scoring Format'!$B$4))+($I44*'Scoring Format'!$B$7)+($M44*('Scoring Format'!$B$3))+($O44*('Scoring Format'!$B$6))) -> 11.2 | Z44: =(F44*0.5)+(($G44*('Scoring Format'!$B$4))+($I44*'Scoring Format'!$B$7)+($M44*('Scoring Format'!$B$3))+($O44*('Scoring Format'!$B$6))) -> 9.7 | AD44: Daniels, Darenell - ARI | AF44: =AH44/AG44 -> 0.74285714 | AG44: 35 | AH44: 26 | AI44: 283 | AJ44: =AI44/AH44 -> 10.884615 | AK44: 2 | AL44: =AK44/AH44 -> 0.076923077 | AN44: 0 | AO44: 0 | AP44: 0 | AQ44: 0 | AR44: =AQ44/AN44 -> #DIV/0! | AV44: =(#REF!+AK44)/(#REF!+AK47) -> #REF! | AW44: =#REF!/(AK44+#REF!) -> #REF! | AX44: =AK44/(#REF!+AK44) -> #REF! | AZ44: =(AI44*0.1)+(AK44*6)+(AO44*0.1)+(AQ44*6) -> 40.3 | BA44: =(AH44*1)+(AI44*0.1)+(AK44*6)+(AO44*0.1)+(AQ44*6) -> 66.3
A45: TE*Hibner, Matthew - BAL | B45: 24 | C45: 17 | D45: =F45/E45 -> 0.75 | E45: 40 | F45: 30 | G45: 320 | H45: =G45/F45 -> 10.666667 | I45: 2 | J45: =I45/F45 -> 0.066666667 | L45: 0 | M45: 0 | N45: 0 | O45: 0 | P45: =O45/L45 -> #DIV/0! | S45: Hibner, Matthew - BAL | T45: =(E45+L45)/($E$47+$L$47+$E$38+$L$38+$K$27+$D$27+$N$17) -> 0.038572806 | U45: =E45/($E$47+$E$38+$K$27) -> 0.082304527 | V45: =L45/($L$47+$L$38+$D$27+$N$17) -> 0 | X45: =($G45*('Scoring Format'!$B$4))+($I45*'Scoring Format'!$B$7)+($M45*('Scoring Format'!$B$3))+($O45*('Scoring Format'!$B$6)) -> 44 | Y45: =(F45*1)+(($G45*('Scoring Format'!$B$4))+($I45*'Scoring Format'!$B$7)+($M45*('Scoring Format'!$B$3))+($O45*('Scoring Format'!$B$6))) -> 74 | Z45: =(F45*0.5)+(($G45*('Scoring Format'!$B$4))+($I45*'Scoring Format'!$B$7)+($M45*('Scoring Format'!$B$3))+($O45*('Scoring Format'!$B$6))) -> 59 | AD45: Bunting, Ian - ARI | AF45: =AH45/AG45 -> 0.5 | AG45: 12 | AH45: 6 | AI45: 65 | AJ45: =AI45/AH45 -> 10.833333 | AK45: 0 | AL45: =AK45/AH45 -> 0 | AN45: 0 | AO45: 0 | AP45: 0 | AQ45: 0 | AR45: =AQ45/AN45 -> #DIV/0! | AV45: =(#REF!+AK45)/(#REF!+AI49) -> #REF! | AW45: =#REF!/(AK45+#REF!) -> #REF! | AX45: =AK45/(#REF!+AK45) -> #REF! | AZ45: =(AI45*0.1)+(AK45*6)+(AO45*0.1)+(AQ45*6) -> 6.5 | BA45: =(AH45*1)+(AI45*0.1)+(AK45*6)+(AO45*0.1)+(AQ45*6) -> 12.5
A46: TE*Cuevas, Josh - BAL | B46: 22 | C46: 17 | D46: =F46/E46 -> 0.69230769 | E46: 13 | F46: 9 | G46: 82 | H46: =G46/F46 -> 9.1111111 | I46: 0 | J46: =I46/F46 -> 0 | L46: 0 | M46: 0 | N46: 0 | O46: 0 | P46: =O46/L46 -> #DIV/0! | S46: Cuevas, Josh - BAL | T46: =(E46+L46)/($E$47+$L$47+$E$38+$L$38+$K$27+$D$27+$N$17) -> 0.012536162 | U46: =E46/($E$47+$E$38+$K$27) -> 0.026748971 | V46: =L46/($L$47+$L$38+$D$27+$N$17) -> 0 | X46: =($G46*('Scoring Format'!$B$4))+($I46*'Scoring Format'!$B$7)+($M46*('Scoring Format'!$B$3))+($O46*('Scoring Format'!$B$6)) -> 8.2 | Y46: =(F46*1)+(($G46*('Scoring Format'!$B$4))+($I46*'Scoring Format'!$B$7)+($M46*('Scoring Format'!$B$3))+($O46*('Scoring Format'!$B$6))) -> 17.2 | Z46: =(F46*0.5)+(($G46*('Scoring Format'!$B$4))+($I46*'Scoring Format'!$B$7)+($M46*('Scoring Format'!$B$3))+($O46*('Scoring Format'!$B$6))) -> 12.7 | AF46: =AH46/AG46 -> #DIV/0! | AJ46: =AI46/AH46 -> #DIV/0! | AL46: =AK46/AH46 -> #DIV/0! | AQ46: 0 | AR46: =AQ46/AN46 -> #DIV/0! | AV46: =(#REF!+AK46)/(#REF!+AI50) -> #REF! | AW46: =#REF!/(AK46+#REF!) -> #REF! | AX46: =AK46/(#REF!+AK46) -> #REF! | AZ46: =(AI46*0.1)+(AK46*6)+(AO46*0.1)+(AQ46*6) -> 0 | BA46: =(AH46*1)+(AI46*0.1)+(AK46*6)+(AO46*0.1)+(AQ46*6) -> 0
A47: Total | E47: =SUM(E43:E46) -> 153 | F47: =SUM(F43:F46) -> 107 | G47: =SUM(G43:G46) -> 1228 | I47: =SUM(I43:I46) -> 12 | L47: =SUM(L43:L46) -> 0 | M47: =SUM(M43:M46) -> 0 | O47: =SUM(O43:O46) -> 0 | AD47: Total | AG47: =SUM(AG43:AG46) -> 63 | AH47: =SUM(AH43:AH46) -> 41 | AI47: =SUM(AI43:AI46) -> 456 | AK47: =SUM(AK43:AK46) -> 3 | AN47: =SUM(AN43:AN46) -> 0 | AO47: =SUM(AO43:AO46) -> 0 | AQ47: =SUM(AQ43:AQ46) -> 0
A50: Team Totals and Splits | J50: Taxi Squad* | R50: Injured Reserve | AC50: Team Totals and Splits | AL50: Taxi Squad* | AT50: Injured Reserve
B51: Targets | C51: Rec. | D51: Yds | E51: TDs | J51: Player | N51: Position | R51: Player | V51: Position | AD51: Targets | AE51: Rec. | AF51: Yds | AG51: TDs | AL51: Player | AP51: Position | AT51: Player | AX51: Position
A52: Rec Totals | B52: =SUM(K22:K26,E32:E37,E43:E46) -> 486 | C52: =SUM(F43:F46,F32:F37,L22:L26) -> 322 | D52: =SUM(G43:G46,G32:G37,M22:M26) -> 4135 | E52: =SUM(O22:O26,I32:I37,I43:I46) -> 38 | J52: Skyler Thompson | N52: QB | AC52: Rec Totals | AD52: =SUM(AM22:AM26,AG32:AG37,AG43:AG46) -> 583 | AE52: =SUM(AH43:AH46,AH32:AH37,AM22:AM26) -> 404 | AF52: =SUM(AI43:AI46,AI32:AI37,AN22:AN26) -> 3653 | AG52: =SUM(AQ22:AQ26,AK32:AK37,AK43:AK46) -> 27
A53: QB Totals | B53: =SUM(D17) -> 486 | C53: =SUM(E17) -> 322 | D53: =SUM(G17) -> 4135 | E53: =SUM(I17) -> 38 | J53: Joe Fagnano | N53: QB | AC53: QB Totals | AD53: =SUM(AF17) -> 583 | AE53: =SUM(AG17) -> 378 | AF53: =SUM(AI17) -> 4072 | AG53: =SUM(AK17) -> 27
A54: League Att Avg. | J54: Dontae McMillan | N54: RB | AC54: League Att Avg.
J55: Elijah Tau-Tolliver | N55: RB
B56: Att | C56: Yards | D56: TDs | J56: LaJohntay Wester | N56: WR | AD56: Att | AE56: Yards | AF56: TDs
A57: Rush Totals | B57: =SUM(N14:N16,D22:D26,L32:L37,L43:L46) -> 551 | C57: =SUM(O14:O16,E22:E26,M32:M37,M43:M46) -> 3082 | D57: =SUM(Q14:Q16,G22:G26,O32:O37,O43:O46) -> 23 | J57: Dayton Wade | N57: WR | AC57: Rush Totals | AD57: =SUM(AP14:AP16,AF22:AF26,AN32:AN37,AN43:AN46) -> 421 | AE57: =SUM(AQ14:AQ16,AG22:AG26,AO32:AO37,AO43:AO46) -> 2231 | AF57: =SUM(AS14:AS16,AI22:AI26,AQ32:AQ37,AQ43:AQ46) -> 18
A58: League Att Avg. | J58: Cornelius Johnson | N58: WR | AC58: League Att Avg.
J59: Octavian Smith | N59: WR
B60: Run | C60: Pass | J60: Tyler Pezza | N60: TE | AD60: Run | AE60: Pass
A61: Run/Pass Pct | B61: =B57/(B53+B57) -> 0.53134041 | C61: =B53/(B53+B57) -> 0.46865959 | J61: Chris Moore | N61: WR | AC61: Run/Pass Pct | AD61: =AD57/(AD53+AD57) -> 0.41932271 | AE61: =AD53/(AD53+AD57) -> 0.58067729 | AL61: *Projected options during offseason/Actual options during the season.
A62: League Average | AC62: League Average
J68: *Projected options during offseason/Actual options during the season.
A73: Team Projections Menu
H75: RSP Projections: Year 1 | M75: Adjustable Projections: Year 1 | S75: Offense Distribution
H76: RSP Projections: Year 2 | M76: Past Run/Pass Performances | S76: Run | T76: Pass
S77: =(M87+C97+K108+K117)/(M87+C97+K108+C87) -> #DIV/0! | T77: =C87/(C87+M87+C97+K108+K117) -> #DIV/0!
A80: RSP Projections: Year 2
C82: Passing | L82: Rushing | R82: Touches | V82: Fantasy Points
A83: QB | B83: G | C83: Att | D83: Comp | E83: Pct | F83: Yards | G83: Yds/Att | H83: TDs | I83: TDs/Att | J83: Int | K83: Int/Att | M83: Ratt | N83: Ryds | O83: Ryds/Att | P83: TDs | Q83: Tds/Att | S83: Touch % | T83: Pct Pass | U83: Pct Run | W83: Fpts | X83: Adjusted
E84: =D84/C84 -> #DIV/0! | G84: =F84/C84 -> #DIV/0! | I84: =H84/C84 -> #DIV/0! | K84: =J84/C84 -> #DIV/0! | O84: =N84/M84 -> #DIV/0! | Q84: =P84/M84 -> #DIV/0! | S84: =(C84+M84)/($D$17+$N$17) -> 0 | T84: =C84/($D$17) -> 0 | U84: =M84/($N$17) -> 0 | W84: =(F84*0.05)+(H84*4)+(J84*-1)+(N84*0.1)+(P84*6) -> 0 | X84: =((F84*0.05)+(H84*4)+(J84*-1)+(N84*0.1)+(P84*6))*0.4 -> 0
E85: =D85/C85 -> #DIV/0! | G85: =F85/C85 -> #DIV/0! | I85: =H85/C85 -> #DIV/0! | K85: =J85/C85 -> #DIV/0! | O85: =N85/M85 -> #DIV/0! | Q85: =P85/M85 -> #DIV/0! | S85: =(C85+M85)/($D$17+$N$17) -> 0 | T85: =C85/($D$17) -> 0 | U85: =M85/($N$17) -> 0 | W85: =(F85*0.05)+(H85*4)+(J85*-1)+(N85*0.1)+(P85*6) -> 0 | X85: =((F85*0.05)+(H85*4)+(J85*-1)+(N85*0.1)+(P85*6))*0.4 -> 0
E86: =D86/C86 -> #DIV/0! | G86: =F86/C86 -> #DIV/0! | I86: =H86/C86 -> #DIV/0! | K86: =J86/C86 -> #DIV/0! | O86: =N86/M86 -> #DIV/0! | P86: 0 | Q86: =P86/M86 -> #DIV/0! | S86: =(C86+M86)/($D$17+$N$17) -> 0 | T86: =C86/($D$17) -> 0 | U86: =M86/($N$17) -> 0 | W86: =(F86*0.05)+(H86*4)+(J86*-1)+(N86*0.1)+(P86*6) -> 0 | X86: =((F86*0.05)+(H86*4)+(J86*-1)+(N86*0.1)+(P86*6))*0.4 -> 0
A87: Total | C87: =SUM(C84:C86) -> 0 | D87: =SUM(D84:D86) -> 0 | F87: =SUM(F84:F86) -> 0 | H87: =SUM(H84:H86) -> 0 | J87: =SUM(J84:J86) -> 0 | M87: =SUM(M84:M86) -> 0 | N87: =SUM(N84:N86) -> 0 | P87: =SUM(P84:P86) -> 0 | S87: =S84+S85+S86 -> 0 | T87: =C87/(C87+M87) -> #DIV/0! | U87: =M87/(M87+C87) -> #DIV/0!
A90: Rushing | H90: Receiving | R90: Touches | V90: Fantasy Points
A91: RB | B91: G | C91: Att | D91: Yards | E91: Yds/Att | F91: TDs | G91: TDs/Att | I91: Catch % | J91: Targets | K91: Rec | L91: Yds | M91: Yds/Rec | N91: TDs | O91: TDs/Rec | R91: RB | S91: Touch % | T91: Pct Pass | U91: Pct Run | W91: Fpts | X91: PPR Fpts | Y91: .5 PPR
E92: =D92/C92 -> #DIV/0! | G92: =F92/C92 -> #DIV/0! | I92: =K92/J92 -> #DIV/0! | M92: =L92/K92 -> #DIV/0! | O92: =N92/K92 -> #DIV/0! | S92: =(C92+J92)/($D$27+$K$27+$N$17+$E$17+$L$38+$L$47) -> 0 | T92: =J92/($K$27+$F$38+$F$47) -> 0 | U92: =C92/($D$27+$N$17+$L$38+$L$47) -> 0 | W92: =(D92*0.1)+(F92*6)+(L92*0.1)+(N92*6) -> 0 | X92: =(D92*0.1)+(F92*6)+(K92*1)+(L92*0.1)+(N92*6) -> 0 | Y92: =(D92*0.1)+(F92*6)+(K92*0.5)+(L92*0.1)+(N92*6) -> 0
E93: =D93/C93 -> #DIV/0! | G93: =F93/C93 -> #DIV/0! | I93: =K93/J93 -> #DIV/0! | M93: =L93/K93 -> #DIV/0! | O93: =N93/K93 -> #DIV/0! | S93: =(C93+J93)/($D$27+$K$27+$N$17+$E$17+$L$38+$L$47) -> 0 | T93: =J93/($K$27+$F$38+$F$47) -> 0 | U93: =C93/($D$27+$N$17+$L$38+$L$47) -> 0 | W93: =(D93*0.1)+(F93*6)+(L93*0.1)+(N93*6) -> 0 | X93: =(D93*0.1)+(F93*6)+(K93*1)+(L93*0.1)+(N93*6) -> 0 | Y93: =(D93*0.1)+(F93*6)+(K93*0.5)+(L93*0.1)+(N93*6) -> 0
E94: =D94/C94 -> #DIV/0! | G94: =F94/C94 -> #DIV/0! | I94: =K94/J94 -> #DIV/0! | M94: =L94/K94 -> #DIV/0! | O94: =N94/K94 -> #DIV/0! | S94: =(C94+J94)/($D$27+$K$27+$N$17+$E$17+$L$38+$L$47) -> 0 | T94: =J94/($K$27+$F$38+$F$47) -> 0 | U94: =C94/($D$27+$N$17+$L$38+$L$47) -> 0 | W94: =(D94*0.1)+(F94*6)+(L94*0.1)+(N94*6) -> 0 | X94: =(D94*0.1)+(F94*6)+(K94*1)+(L94*0.1)+(N94*6) -> 0 | Y94: =(D94*0.1)+(F94*6)+(K94*0.5)+(L94*0.1)+(N94*6) -> 0
E95: =D95/C95 -> #DIV/0! | G95: =F95/C95 -> #DIV/0! | I95: =K95/J95 -> #DIV/0! | M95: =L95/K95 -> #DIV/0! | O95: =N95/K95 -> #DIV/0! | S95: =(C95+J95)/($D$27+$K$27+$N$17+$E$17+$L$38+$L$47) -> 0 | T95: =J95/($K$27+$F$38+$F$47) -> 0 | U95: =C95/($D$27+$N$17+$L$38+$L$47) -> 0 | W95: =(D95*0.1)+(F95*6)+(L95*0.1)+(N95*6) -> 0 | X95: =(D95*0.1)+(F95*6)+(K95*1)+(L95*0.1)+(N95*6) -> 0 | Y95: =(D95*0.1)+(F95*6)+(K95*0.5)+(L95*0.1)+(N95*6) -> 0
E96: =D96/C96 -> #DIV/0! | G96: =F96/C96 -> #DIV/0! | I96: =K96/J96 -> #DIV/0! | M96: =L96/K96 -> #DIV/0! | O96: =N96/K96 -> #DIV/0! | S96: =(C96+J96)/($D$27+$K$27+$N$17+$E$17+$L$38+$L$47) -> 0 | T96: =J96/($K$27+$F$38+$F$47) -> 0 | U96: =C96/($D$27+$N$17+$L$38+$L$47) -> 0 | W96: =(D96*0.1)+(F96*6)+(L96*0.1)+(N96*6) -> 0 | X96: =(D96*0.1)+(F96*6)+(K96*1)+(L96*0.1)+(N96*6) -> 0 | Y96: =(D96*0.1)+(F96*6)+(K96*0.5)+(L96*0.1)+(N96*6) -> 0
A97: Total | C97: =SUM(C92:C96) -> 0 | D97: =SUM(D92:D96) -> 0 | F97: =SUM(F92:F96) -> 0 | J97: =SUM(J92:J96) -> 0 | K97: =SUM(K92:K96) -> 0 | L97: =SUM(L92:L96) -> 0 | N97: =SUM(N92:N96) -> 0
A100: Receiving | J100: Rushing | R100: Touches | V100: Fantasy Points
A101: WRs | B101: G | C101: Catch % | D101: Targets | E101: Rec | F101: Yds | G101: Yds/Rec | H101: TDs | I101: TDs/Rec | K101: Ratt | L101: Ryds | M101: Ryds/Att | N101: RTds | O101: TDs/Att | R101: WRs | S101: Touch % | T101: Pct Pass | U101: Pct Run | W101: Fpts | X101: PPR Fpts | Y101: .5PPR
C102: =E102/D102 -> #DIV/0! | G102: =F102/E102 -> #DIV/0! | I102: =H102/E102 -> #DIV/0! | M102: =L102/K102 -> #DIV/0! | N102: 0 | O102: =N102/K102 -> #DIV/0! | S102: =(D102+K102)/($D$27+$L$27+$N$17+$E$47+$L$47) -> 0 | T102: =D102/($E$17) -> 0 | U102: =K102/($N$17+$D$27+$L$38+$L$47) -> 0 | W102: =(F102*0.1)+(H102*6)+(L102*0.1)+(N102*6) -> 0 | X102: =(E102*1)+(F102*0.1)+(H102*6)+(L102*0.1)+(N102*6) -> 0 | Y102: =(E102*0.5)+(F102*0.1)+(H102*6)+(L102*0.1)+(N102*6) -> 0
C103: =E103/D103 -> #DIV/0! | G103: =F103/E103 -> #DIV/0! | I103: =H103/E103 -> #DIV/0! | M103: =L103/K103 -> #DIV/0! | O103: =N103/K103 -> #DIV/0! | S103: =(D103+K103)/($D$27+$L$27+$N$17+$E$47+$L$47) -> 0 | T103: =D103/($E$17) -> 0 | U103: =K103/($N$17+$D$27+$L$38+$L$47) -> 0 | W103: =(F103*0.1)+(H103*6)+(L103*0.1)+(N103*6) -> 0 | X103: =(E103*1)+(F103*0.1)+(H103*6)+(L103*0.1)+(N103*6) -> 0 | Y103: =(E103*0.5)+(F103*0.1)+(H103*6)+(L103*0.1)+(N103*6) -> 0
C104: =E104/D104 -> #DIV/0! | G104: =F104/E104 -> #DIV/0! | I104: =H104/E104 -> #DIV/0! | M104: =L104/K104 -> #DIV/0! | N104: 0 | O104: =N104/K104 -> #DIV/0! | S104: =(D104+K104)/($D$27+$L$27+$N$17+$E$47+$L$47) -> 0 | T104: =D104/($E$17) -> 0 | U104: =K104/($N$17+$D$27+$L$38+$L$47) -> 0 | W104: =(F104*0.1)+(H104*6)+(L104*0.1)+(N104*6) -> 0 | X104: =(E104*1)+(F104*0.1)+(H104*6)+(L104*0.1)+(N104*6) -> 0 | Y104: =(E104*0.5)+(F104*0.1)+(H104*6)+(L104*0.1)+(N104*6) -> 0
C105: =E105/D105 -> #DIV/0! | G105: =F105/E105 -> #DIV/0! | I105: =H105/E105 -> #DIV/0! | M105: =L105/K105 -> #DIV/0! | N105: 0 | O105: =N105/K105 -> #DIV/0! | S105: =(D105+K105)/($D$27+$L$27+$N$17+$E$47+$L$47) -> 0 | T105: =D105/($E$17) -> 0 | U105: =K105/($N$17+$D$27+$L$38+$L$47) -> 0 | W105: =(F105*0.1)+(H105*6)+(L105*0.1)+(N105*6) -> 0 | X105: =(E105*1)+(F105*0.1)+(H105*6)+(L105*0.1)+(N105*6) -> 0 | Y105: =(E105*0.5)+(F105*0.1)+(H105*6)+(L105*0.1)+(N105*6) -> 0
C106: =E106/D106 -> #DIV/0! | G106: =F106/E106 -> #DIV/0! | I106: =H106/E106 -> #DIV/0! | M106: =L106/K106 -> #DIV/0! | N106: 0 | O106: =N106/K106 -> #DIV/0! | S106: =(D106+K106)/($D$27+$L$27+$N$17+$E$47+$L$47) -> 0 | T106: =D106/($E$17) -> 0 | U106: =K106/($N$17+$D$27+$L$38+$L$47) -> 0 | W106: =(F106*0.1)+(H106*6)+(L106*0.1)+(N106*6) -> 0 | X106: =(E106*1)+(F106*0.1)+(H106*6)+(L106*0.1)+(N106*6) -> 0 | Y106: =(E106*0.5)+(F106*0.1)+(H106*6)+(L106*0.1)+(N106*6) -> 0
C107: =E107/D107 -> #DIV/0! | G107: =F107/E107 -> #DIV/0! | I107: =H107/E107 -> #DIV/0! | M107: =L107/K107 -> #DIV/0! | N107: 0 | O107: =N107/K107 -> #DIV/0! | S107: =(D107+K107)/($D$27+$L$27+$N$17+$E$47+$L$47) -> 0 | T107: =D107/($E$17) -> 0 | U107: =K107/($N$17+$D$27+$L$38+$L$47) -> 0 | W107: =(F107*0.1)+(H107*6)+(L107*0.1)+(N107*6) -> 0 | X107: =(E107*1)+(F107*0.1)+(H107*6)+(L107*0.1)+(N107*6) -> 0 | Y107: =(E107*0.5)+(F107*0.1)+(H107*6)+(L107*0.1)+(N107*6) -> 0
A108: Total | D108: =SUM(D102:D107) -> 0 | E108: =SUM(E102:E107) -> 0 | F108: =SUM(F102:F107) -> 0 | H108: =SUM(H102:H107) -> 0 | K108: =SUM(K102:K107) -> 0 | L108: =SUM(L102:L107) -> 0 | N108: =SUM(N102:N107) -> 0
A111: Receiving | J111: Rushing | R111: Touches | V111: Fantasy Points
A112: Tes | B112: G | C112: Catch % | D112: Targets | E112: Rec | F112: Yds | G112: Yds/Rec | H112: TDs | I112: TDs/Rec | K112: Ratt | L112: Ryds | M112: Ryds/Att | N112: RTDs | O112: TDs/Att | R112: Tes | S112: Touch % | T112: Pct Pass | U112: Pct Run | W112: Fpts | X112: PPR Fpts | Y112: .5 PPR
C113: =E113/D113 -> #DIV/0! | G113: =F113/E113 -> #DIV/0! | I113: =H113/E113 -> #DIV/0! | K113: 0 | L113: 0 | M113: 0 | N113: 0 | O113: =N113/K113 -> #DIV/0! | S113: =(D113+K113)/($E$47+$L$47+$E$38+$L$38+$K$27+$D$27+$N$17) -> 0 | T113: =D113/($E$47+$E$38+$K$27) -> 0 | U113: =K113/($L$47+$L$38+$D$27+$N$17) -> 0 | W113: =(F113*0.1)+(H113*6)+(L113*0.1)+(N113*6) -> 0 | X113: =(E113*1)+(F113*0.1)+(H113*6)+(L113*0.1)+(N113*6) -> 0 | Y113: =(E113*0.5)+(F113*0.1)+(H113*6)+(L113*0.1)+(N113*6) -> 0
C114: =E114/D114 -> #DIV/0! | G114: =F114/E114 -> #DIV/0! | I114: =H114/E114 -> #DIV/0! | K114: 0 | L114: 0 | M114: 0 | N114: 0 | O114: =N114/K114 -> #DIV/0! | S114: =(D114+K114)/($E$47+$L$47+$E$38+$L$38+$K$27+$D$27+$N$17) -> 0 | T114: =D114/($E$47+$E$38+$K$27) -> 0 | U114: =K114/($L$47+$L$38+$D$27+$N$17) -> 0 | W114: =(F114*0.1)+(H114*6)+(L114*0.1)+(N114*6) -> 0 | X114: =(E114*1)+(F114*0.1)+(H114*6)+(L114*0.1)+(N114*6) -> 0 | Y114: =(E114*0.5)+(F114*0.1)+(H114*6)+(L114*0.1)+(N114*6) -> 0
C115: =E115/D115 -> #DIV/0! | G115: =F115/E115 -> #DIV/0! | I115: =H115/E115 -> #DIV/0! | K115: 0 | L115: 0 | M115: 0 | N115: 0 | O115: =N115/K115 -> #DIV/0! | S115: =(D115+K115)/($E$47+$L$47+$E$38+$L$38+$K$27+$D$27+$N$17) -> 0 | T115: =D115/($E$47+$E$38+$K$27) -> 0 | U115: =K115/($L$47+$L$38+$D$27+$N$17) -> 0 | W115: =(F115*0.1)+(H115*6)+(L115*0.1)+(N115*6) -> 0 | X115: =(E115*1)+(F115*0.1)+(H115*6)+(L115*0.1)+(N115*6) -> 0 | Y115: =(E115*0.5)+(F115*0.1)+(H115*6)+(L115*0.1)+(N115*6) -> 0
C116: =E116/D116 -> #DIV/0! | G116: =F116/E116 -> #DIV/0! | I116: =H116/E116 -> #DIV/0! | K116: 0 | L116: 0 | M116: 0 | N116: 0 | O116: =N116/K116 -> #DIV/0! | S116: =(D116+K116)/($E$47+$L$47+$E$38+$L$38+$K$27+$D$27+$N$17) -> 0 | T116: =D116/($E$47+$E$38+$K$27) -> 0 | U116: =K116/($L$47+$L$38+$D$27+$N$17) -> 0 | W116: =(F116*0.1)+(H116*6)+(L116*0.1)+(N116*6) -> 0 | X116: =(E116*1)+(F116*0.1)+(H116*6)+(L116*0.1)+(N116*6) -> 0 | Y116: =(E116*0.5)+(F116*0.1)+(H116*6)+(L116*0.1)+(N116*6) -> 0
A117: Total | D117: =SUM(D113:D116) -> 0 | E117: =SUM(E113:E116) -> 0 | F117: =SUM(F113:F116) -> 0 | H117: =SUM(H113:H116) -> 0 | K117: =SUM(K113:K116) -> 0 | L117: =SUM(L113:L116) -> 0 | N117: =SUM(N113:N116) -> 0
A120: Team Totals and Splits | J120: Taxi Squad* | R120: Injured Reserve
B121: Targets | C121: Rec. | D121: Yds | E121: TDs | J121: Player | N121: Position | R121: Player | V121: Position
A122: Rec Totals | B122: =SUM(J92:J96,D102:D107,D113:D116) -> 0 | C122: =SUM(E113:E116,E102:E107,K92:K96) -> 0 | D122: =SUM(F113:F116,F102:F107,L92:L96) -> 0 | E122: =SUM(N92:N96,H102:H107,H113:H116) -> 0
A123: QB Totals | B123: =SUM(C87) -> 0 | C123: =SUM(D87) -> 0 | D123: =SUM(F87) -> 0 | E123: =SUM(H87) -> 0
A124: League Att Avg.
B126: Att | C126: Yards | D126: TDs
A127: Rush Totals | B127: =SUM(M84:M86,C92:C96,K102:K107,K113:K116) -> 0 | C127: =SUM(N84:N86,D92:D96,L102:L107,L113:L116) -> 0 | D127: =SUM(P84:P86,F92:F96,N102:N107,N113:N116) -> 0
A128: League Att Avg.
B130: Run | C130: Pass
A131: Run/Pass Pct | B131: =B127/(B123+B127) -> #DIV/0! | C131: =B123/(B123+B127) -> #DIV/0!
A132: League Average | J132: *Projected options during offseason/Actual options during the season.
A141: 2-Year Team Historical Performance
H143: RSP Projections: Year 1 | M143: Adjustable Projections: Year 1
H144: RSP Projections: Year 2
D147: Historical Production | P147: Touch Distribution
...

Sheet BUF
A1: Buffalo Bills
A3: Team Projections Menu | AC3: Team Projections Menu
H5: RSP Projections: Year 1 | M5: Adjustable Projections: Year 1 | S5: Offense Distribution | AJ5: RSP Projections: Year 1 | AO5: Adjustable Projections: Year 1
H6: RSP Projections: Year 2 | M6: Past Run/Pass Performances | S6: Run | T6: Pass | AJ6: RSP Projections: Year 2
S7: =(N17+D27+L38+L47)/(N17+D27+L38+D17) -> 0.50635386 | T7: =D17/(D17+N17+D27+L38+L47) -> 0.49364614
AC10: Adjustable Projections: Year 1
C12: Passing | N12: Rushing | T12: Touches | AG12: Passing | AP12: Rushing | AV12: Touches | AZ12: Fantasy Points
A13: QB | B13: Age | C13: G | D13: Att | E13: Comp | F13: Pct | G13: Yards | H13: Yds/Att | I13: TDs | J13: TDs/Att | K13: Int | L13: Int/Att | N13: Ratt | O13: Ryds | P13: Ryds/Att | Q13: TDs | R13: Tds/Att | T13: Touch % | U13: Pct Pass | V13: Pct Run | X13: Fpts | Y13: Adjusted | AD13: QB | AE13: G | AF13: Att | AG13: Comp | AH13: Pct | AI13: Yards | AJ13: Yds/Att | AK13: TDs | AL13: TDs/Att | AM13: Int | AN13: Int/Att | AP13: Ratt | AQ13: Ryds | AR13: Ryds/Att | AS13: TDs | AT13: Tds/Att | AV13: Touch % | AW13: Pct Pass | AX13: Pct Run | AZ13: Fpts | BA13: Adjusted
A14: QB*Allen, Josh - BUF | B14: 30 | C14: 17 | D14: 475 | E14: 339 | F14: =E14/D14 -> 0.71368421 | G14: 3900 | H14: =G14/D14 -> 8.2105263 | I14: 28 | J14: =I14/D14 -> 0.058947368 | K14: 12 | L14: =K14/D14 -> 0.025263158 | N14: 107 | O14: 550 | P14: =O14/N14 -> 5.1401869 | Q14: 13 | R14: =Q14/N14 -> 0.12149533 | T14: =(D14+N14)/($D$17+$N$17) -> 0.94480519 | U14: =D14/($D$17) -> 0.94059406 | V14: =N14/($N$17) -> 0.96396396 | X14: =($G14*('Scoring Format'!$B$2))+($I14*('Scoring Format'!$B$5))+($K14*('Scoring Format'!$B$8))+($O14*('Scoring Format'!$B$3))+($Q14*('Scoring Format'!$B$6)) -> 428 | Y14: =(($G14*('Scoring Format'!$B$2))+($I14*('Scoring Format'!$B$5))+($K14*('Scoring Format'!$B$8))+($O14*('Scoring Format'!$B$3))+($Q14*('Scoring Format'!$B$6)))*0.4 -> 171.2 | AD14: Murray, Kyler - ARI | AF14: 583 | AG14: 378 | AH14: =AG14/AF14 -> 0.6483705 | AI14: 4072 | AJ14: =AI14/AF14 -> 6.9845626 | AK14: 27 | AL14: =AK14/AF14 -> 0.046312178 | AM14: 11 | AN14: =AM14/AF14 -> 0.018867925 | AP14: 100 | AQ14: 590 | AR14: =AQ14/AP14 -> 5.9 | AS14: 5 | AT14: =AS14/AP14 -> 0.05 | AV14: =(AF14+AP14)/(AF17+AP17) -> 1 | AW14: =AF14/(AP14+AF14) -> 0.85358712 | AX14: =AP14/(AF14+AP14) -> 0.14641288 | AZ14: =((AI14*0.05)+(AK14*4)+(AM14*-1)+(AQ14*0.1)+(AS14*6))*0.55 -> 214.28 | BA14: =((AI14*0.05)+(AK14*4)+(AM14*-1)+(AQ14*0.1)+(AS14*6))*0.4 -> 155.84
A15: QB*Allen, Kyle - BUF | B15: 30 | C15: 17 | D15: 30 | E15: 18 | F15: =E15/D15 -> 0.6 | G15: 208 | H15: =G15/D15 -> 6.9333333 | I15: 1 | J15: =I15/D15 -> 0.033333333 | K15: 1 | L15: =K15/D15 -> 0.033333333 | N15: 4 | O15: 12 | P15: =O15/N15 -> 3 | Q15: 0 | R15: =Q15/N15 -> 0 | T15: =(D15+N15)/($D$17+$N$17) -> 0.055194805 | U15: =D15/($D$17) -> 0.059405941 | V15: =N15/($N$17) -> 0.036036036 | X15: =($G15*('Scoring Format'!$B$2))+($I15*('Scoring Format'!$B$5))+($K15*('Scoring Format'!$B$8))+($O15*('Scoring Format'!$B$3))+($Q15*('Scoring Format'!$B$6)) -> 14.6 | Y15: =(($G15*('Scoring Format'!$B$2))+($I15*('Scoring Format'!$B$5))+($K15*('Scoring Format'!$B$8))+($O15*('Scoring Format'!$B$3))+($Q15*('Scoring Format'!$B$6)))*0.4 -> 5.84 | AD15: McCoy, Colt - ARI | AF15: 0 | AG15: 0 | AH15: 0 | AI15: 0 | AK15: 0 | AL15: =AK15/AF15 -> #DIV/0! | AM15: 0 | AN15: =AM15/AF15 -> #DIV/0! | AP15: 0 | AQ15: 0 | AS15: 0 | AT15: =AS15/AP15 -> #DIV/0! | AV15: =(AF15+AP15)/(AD18+AN18) -> #DIV/0! | AW15: =AF15/(AP15+AF15) -> #DIV/0! | AX15: =AP15/(AF15+AP15) -> #DIV/0!
A16: QB*Buechele, Shane - BUF | B16: 28 | F16: =E16/D16 -> #DIV/0! | H16: =G16/D16 -> #DIV/0! | J16: =I16/D16 -> #DIV/0! | L16: =K16/D16 -> #DIV/0! | P16: =O16/N16 -> #DIV/0! | R16: =Q16/N16 -> #DIV/0! | T16: =(D16+N16)/($D$17+$N$17) -> 0 | U16: =D16/($D$17) -> 0 | V16: =N16/($N$17) -> 0 | X16: =($G16*('Scoring Format'!$B$2))+($I16*('Scoring Format'!$B$5))+($K16*('Scoring Format'!$B$8))+($O16*('Scoring Format'!$B$3))+($Q16*('Scoring Format'!$B$6)) -> 0 | Y16: =(($G16*('Scoring Format'!$B$2))+($I16*('Scoring Format'!$B$5))+($K16*('Scoring Format'!$B$8))+($O16*('Scoring Format'!$B$3))+($Q16*('Scoring Format'!$B$6)))*0.4 -> 0 | AD16: McDonald, Cole - ARI | AH16: =AG16/AF16 -> #DIV/0! | AJ16: =AI16/AF16 -> #DIV/0! | AL16: =AK16/AF16 -> #DIV/0! | AN16: =AM16/AF16 -> #DIV/0! | AR16: =AQ16/AP16 -> #DIV/0! | AT16: =AS16/AP16 -> #DIV/0! | AV16: =(AF16+AP16)/(AF20+AP20) -> #DIV/0! | AW16: =AF16/(AP16+AF16) -> #DIV/0! | AX16: =AP16/(AF16+AP16) -> #DIV/0! | AZ16: =((AI16*0.05)+(AK16*4)+(AM16*-1)+(AQ16*0.1)+(AS16*6))*0.55 -> 0 | BA16: =((AI16*0.05)+(AK16*4)+(AM16*-1)+(AQ16*0.1)+(AS16*6))*0.4 -> 0
A17: Total | D17: =SUM(D14:D16) -> 505 | E17: =SUM(E14:E16) -> 357 | G17: =SUM(G14:G16) -> 4108 | I17: =SUM(I14:I16) -> 29 | K17: =SUM(K14:K16) -> 13 | N17: =SUM(N14:N16) -> 111 | O17: =SUM(O14:O16) -> 562 | Q17: =SUM(Q14:Q16) -> 13 | T17: =T14+T15+T16 -> 1 | U17: =D17/(D17+N17) -> 0.81980519 | V17: =N17/(N17+D17) -> 0.18019481 | AD17: Total | AF17: =SUM(AF14:AF16) -> 583 | AG17: =SUM(AG14:AG16) -> 378 | AI17: =SUM(AI14:AI16) -> 4072 | AK17: =SUM(AK14:AK16) -> 27 | AM17: =SUM(AM14:AM16) -> 11 | AP17: =SUM(AP14:AP16) -> 100 | AQ17: =SUM(AQ14:AQ16) -> 590 | AS17: =SUM(AS14:AS16) -> 5 | AV17: =AV14+AV15+AV16 -> #DIV/0! | AW17: =AF17/(AF17+AP17) -> 0.85358712 | AX17: =AP17/(AP17+AF17) -> 0.14641288
A20: Rushing | H20: Receiving | R20: Touches | AE20: Rushing | AL20: Receiving | AV20: Touches | AZ20: Fantasy Points
A21: RB | B21: Age | C21: G | D21: Att | E21: Yards | F21: Yds/Att | G21: TDs | H21: TDs/Att | J21: Catch % | K21: Targets | L21: Rec | M21: Yds | N21: Yds/Rec | O21: TDs | P21: TDs/Rec | S21: RB | T21: Touch % | U21: Pct Pass | V21: Pct Run | X21: Fpts | Y21: PPR Fpts | Z21: .5 PPR | AD21: RB | AE21: G | AF21: Att | AG21: Yards | AH21: Yds/Att | AI21: TDs | AJ21: TDs/Att | AL21: Catch % | AM21: Targets | AN21: Rec | AO21: Yds | AP21: Yds/Rec | AQ21: TDs | AR21: TDs/Rec | AV21: Touch % | AW21: Pct Pass | AX21: Pct Run | AZ21: Fpts | BA21: PPR Fpts
A22: RB*Cook, James - BUF | B22: 27 | C22: 17 | D22: 270 | E22: 1500 | F22: =E22/D22 -> 5.5555556 | G22: 10 | H22: =G22/D22 -> 0.037037037 | J22: =L22/K22 -> 0.81481481 | K22: 54 | L22: 44 | M22: 399 | N22: =M22/L22 -> 9.0681818 | O22: 3 | P22: =O22/L22 -> 0.068181818 | S22: Cook, James - BUF | T22: =(D22+K22)/($D$27+$K$27+$N$17+$E$17+$L$38+$L$47) -> 0.33785193 | U22: =K22/($K$27+$F$38+$F$47) -> 0.14477212 | V22: =D22/($D$27+$N$17+$L$38+$L$47) -> 0.52123552 | X22: =($E22*('Scoring Format'!$B$3))+($G22*('Scoring Format'!$B$6))+($M22*('Scoring Format'!$B$4))+($O22*('Scoring Format'!$B$7)) -> 267.9 | Y22: =($E22*('Scoring Format'!$B$3))+($G22*('Scoring Format'!$B$6))+(L22*1)+($M22*('Scoring Format'!$B$4))+($O22*('Scoring Format'!$B$7)) -> 311.9 | Z22: =($E22*('Scoring Format'!$B$3))+($G22*('Scoring Format'!$B$6))+(L22*0.5)+($M22*('Scoring Format'!$B$4))+($O22*('Scoring Format'!$B$7)) -> 289.9 | AD22: Conner, James - ARI | AF22: 200 | AG22: 1040 | AH22: =AG22/AF22 -> 5.2 | AI22: 7 | AJ22: =AI22/AF22 -> 0.035 | AL22: =AN22/AM22 -> 0.8 | AM22: 70 | AN22: 56 | AO22: 364 | AP22: =AO22/AN22 -> 6.5 | AQ22: 2 | AR22: =AQ22/AN22 -> 0.035714286 | AV22: =(#REF!+AM22)/(#REF!+AM25) -> #REF! | AW22: =#REF!/(AM22+#REF!) -> #REF! | AX22: =AM22/(#REF!+AM22) -> #REF! | AZ22: =(#REF!*0.1)+(AF22*6)+(AL22*0.1)+(AN22*6) -> #REF! | BA22: =(#REF!*0.1)+(AF22*6)+(AK22*1)+(AL22*0.1)+(AN22*6) -> #REF!
A23: RB*Davis, Ray - BUF | B23: 27 | C23: 17 | D23: 92 | E23: 430 | F23: =E23/D23 -> 4.673913 | G23: 3 | H23: =G23/D23 -> 0.032608696 | J23: =L23/K23 -> 0.8 | K23: 10 | L23: 8 | M23: 64 | N23: =M23/L23 -> 8 | O23: 1 | P23: =O23/L23 -> 0.125 | S23: Davis, Ray - BUF | T23: =(D23+K23)/($D$27+$K$27+$N$17+$E$17+$L$38+$L$47) -> 0.10636079 | U23: =K23/($K$27+$F$38+$F$47) -> 0.026809651 | V23: =D23/($D$27+$N$17+$L$38+$L$47) -> 0.17760618 | X23: =($E23*('Scoring Format'!$B$3))+($G23*('Scoring Format'!$B$6))+($M23*('Scoring Format'!$B$4))+($O23*('Scoring Format'!$B$7)) -> 73.4 | Y23: =($E23*('Scoring Format'!$B$3))+($G23*('Scoring Format'!$B$6))+(L23*1)+($M23*('Scoring Format'!$B$4))+($O23*('Scoring Format'!$B$7)) -> 81.4 | Z23: =($E23*('Scoring Format'!$B$3))+($G23*('Scoring Format'!$B$6))+(L23*0.5)+($M23*('Scoring Format'!$B$4))+($O23*('Scoring Format'!$B$7)) -> 77.4 | AD23: Edmonds, Chase - ARI | AF23: 96 | AG23: 445 | AH23: =AG23/AF23 -> 4.6354167 | AI23: 6 | AJ23: =AI23/AF23 -> 0.0625 | AL23: =AN23/AM23 -> 0.58333333 | AM23: 24 | AN23: 14 | AO23: 110 | AP23: =AO23/AN23 -> 7.8571429 | AQ23: 2 | AR23: =AQ23/AN23 -> 0.14285714 | AV23: =(#REF!+AM23)/(#REF!+AM26) -> #REF! | AW23: =#REF!/(AM23+#REF!) -> #REF! | AX23: =AM23/(#REF!+AM23) -> #REF! | AZ23: =(#REF!*0.1)+(AF23*6)+(AL23*0.1)+(AN23*6) -> #REF! | BA23: =(#REF!*0.1)+(AF23*6)+(AK23*1)+(AL23*0.1)+(AN23*6) -> #REF!
A24: RB*Johnson, Ty - BUF | B24: 29 | C24: 17 | D24: 45 | E24: 185 | F24: =E24/D24 -> 4.1111111 | G24: 2 | H24: =G24/D24 -> 0.044444444 | J24: =L24/K24 -> 0.8 | K24: 20 | L24: 16 | M24: 176 | N24: =M24/L24 -> 11 | O24: 1 | P24: =O24/L24 -> 0.0625 | S24: Johnson, Ty - BUF | T24: =(D24+K24)/($D$27+$K$27+$N$17+$E$17+$L$38+$L$47) -> 0.067778936 | U24: =K24/($K$27+$F$38+$F$47) -> 0.053619303 | V24: =D24/($D$27+$N$17+$L$38+$L$47) -> 0.086872587 | X24: =($E24*('Scoring Format'!$B$3))+($G24*('Scoring Format'!$B$6))+($M24*('Scoring Format'!$B$4))+($O24*('Scoring Format'!$B$7)) -> 54.1 | Y24: =($E24*('Scoring Format'!$B$3))+($G24*('Scoring Format'!$B$6))+(L24*1)+($M24*('Scoring Format'!$B$4))+($O24*('Scoring Format'!$B$7)) -> 70.1 | Z24: =($E24*('Scoring Format'!$B$3))+($G24*('Scoring Format'!$B$6))+(L24*0.5)+($M24*('Scoring Format'!$B$4))+($O24*('Scoring Format'!$B$7)) -> 62.1 | AD24: Benjamin, Eno - ARI | AF24: 8 | AG24: 28 | AH24: =AG24/AF24 -> 3.5 | AI24: 0 | AJ24: =AI24/AF24 -> 0 | AL24: =AN24/AM24 -> 0.5 | AM24: 4 | AN24: 2 | AO24: 17 | AP24: =AO24/AN24 -> 8.5 | AQ24: 0 | AR24: =AQ24/AN24 -> 0 | AV24: =(#REF!+AM24)/(#REF!+AM30) -> #REF! | AW24: =#REF!/(AM24+#REF!) -> #REF! | AX24: =AM24/(#REF!+AM24) -> #REF! | AZ24: =(#REF!*0.1)+(AF24*6)+(AL24*0.1)+(AN24*6) -> #REF! | BA24: =(#REF!*0.1)+(AF24*6)+(AK24*1)+(AL24*0.1)+(AN24*6) -> #REF!
F25: =E25/D25 -> #DIV/0! | H25: =G25/D25 -> #DIV/0! | J25: =L25/K25 -> #DIV/0! | N25: =M25/L25 -> #DIV/0! | P25: =O25/L25 -> #DIV/0! | S25: Reid, Desmond - BUF | T25: =(D25+K25)/($D$27+$K$27+$N$17+$E$17+$L$38+$L$47) -> 0 | U25: =K25/($K$27+$F$38+$F$47) -> 0 | V25: =D25/($D$27+$N$17+$L$38+$L$47) -> 0 | X25: =($E25*('Scoring Format'!$B$3))+($G25*('Scoring Format'!$B$6))+($M25*('Scoring Format'!$B$4))+($O25*('Scoring Format'!$B$7)) -> 0 | Y25: =($E25*('Scoring Format'!$B$3))+($G25*('Scoring Format'!$B$6))+(L25*1)+($M25*('Scoring Format'!$B$4))+($O25*('Scoring Format'!$B$7)) -> 0 | Z25: =($E25*('Scoring Format'!$B$3))+($G25*('Scoring Format'!$B$6))+(L25*0.5)+($M25*('Scoring Format'!$B$4))+($O25*('Scoring Format'!$B$7)) -> 0 | AD25: Ward, Jonathan - ARI | AH25: =AG25/AF25 -> #DIV/0! | AI25: 0 | AJ25: =AI25/AF25 -> #DIV/0! | AL25: =AN25/AM25 -> #DIV/0! | AP25: =AO25/AN25 -> #DIV/0! | AQ25: 0 | AR25: =AQ25/AN25 -> #DIV/0! | AV25: =(#REF!+AM25)/(#REF!+AM31) -> #REF! | AW25: =#REF!/(AM25+#REF!) -> #REF! | AX25: =AM25/(#REF!+AM25) -> #REF! | AZ25: =(#REF!*0.1)+(AF25*6)+(AL25*0.1)+(AN25*6) -> #REF! | BA25: =(#REF!*0.1)+(AF25*6)+(AK25*1)+(AL25*0.1)+(AN25*6) -> #REF!
F26: =E26/D26 -> #DIV/0! | H26: =G26/D26 -> #DIV/0! | J26: =L26/K26 -> #DIV/0! | N26: =M26/L26 -> #DIV/0! | P26: =O26/L26 -> #DIV/0! | T26: =(D26+K26)/($D$27+$K$27+$N$17+$E$17+$L$38+$L$47) -> 0 | U26: =K26/($K$27+$F$38+$F$47) -> 0 | V26: =D26/($D$27+$N$17+$L$38+$L$47) -> 0 | X26: =($E26*('Scoring Format'!$B$3))+($G26*('Scoring Format'!$B$6))+($M26*('Scoring Format'!$B$4))+($O26*('Scoring Format'!$B$7)) -> 0 | Y26: =($E26*('Scoring Format'!$B$3))+($G26*('Scoring Format'!$B$6))+(L26*1)+($M26*('Scoring Format'!$B$4))+($O26*('Scoring Format'!$B$7)) -> 0 | Z26: =($E26*('Scoring Format'!$B$3))+($G26*('Scoring Format'!$B$6))+(L26*0.5)+($M26*('Scoring Format'!$B$4))+($O26*('Scoring Format'!$B$7)) -> 0 | AD26: Muhammad, Khalfani - ARI | AH26: =AG26/AF26 -> #DIV/0! | AJ26: =AI26/AF26 -> #DIV/0! | AL26: =AN26/AM26 -> #DIV/0! | AQ26: =(AG26*0.1)+(AI26*6)+(AN26*0.1)+(AP26*6) -> 0 | AR26: =AQ26/AN26 -> #DIV/0! | AV26: =(#REF!+AM26)/(#REF!+AM32) -> #REF! | AW26: =#REF!/(AM26+#REF!) -> #REF! | AX26: =AM26/(#REF!+AM26) -> #REF! | AZ26: =(#REF!*0.1)+(AF26*6)+(AJ26*1)+(AK26*0.1)+(AM26*6) -> #REF! | BA26: =(#REF!*0.1)+(AF26*6)+(AK26*1)+(AL26*0.1)+(AN26*6) -> #REF!
A27: Total | D27: =SUM(D22:D26) -> 407 | E27: =SUM(E22:E26) -> 2115 | G27: =SUM(G22:G26) -> 15 | K27: =SUM(K22:K26) -> 84 | L27: =SUM(L22:L26) -> 68 | M27: =SUM(M22:M26) -> 639 | O27: =SUM(O22:O26) -> 5 | AD27: Total | AF27: =SUM(AF22:AF26) -> 304 | AG27: =SUM(AG22:AG26) -> 1513 | AI27: =SUM(AI22:AI26) -> 13 | AM27: =SUM(AM22:AM26) -> 98 | AN27: =SUM(AN22:AN26) -> 72 | AO27: =SUM(AO22:AO26) -> 491 | AQ27: =SUM(AQ22:AQ26) -> 4
A30: Receiving | L30: Rushing | T30: Touches | AE30: Receiving | AN30: Rushing | AV30: Touches | AZ30: Fantasy Points
A31: WRs | B31: Age | C31: G | D31: Catch % | E31: Targets | F31: Rec | G31: Yds | H31: Yds/Rec | I31: TDs | J31: TDs/Rec | L31: Ratt | M31: Ryds | N31: Ryds/Att | O31: RTds | P31: TDs/Att | S31: WRs | T31: Touch % | U31: Pct Pass | V31: Pct Run | X31: Fpts | Y31: PPR Fpts | Z31: .5PPR | AD31: WRs | AE31: G | AF31: Catch % | AG31: Targets | AH31: Rec | AI31: Yds | AJ31: Yds/Rec | AK31: TDs | AL31: TDs/Rec | AN31: Ratt | AO31: Ryds | AP31: Ryds/Att | AQ31: RTds | AR31: TDs/Att | AV31: Touch % | AW31: Pct Pass | AX31: Pct Run | AZ31: Fpts | BA31: PPR Fpts
A32: WR*Coleman, Keon - BUF | B32: 23 | C32: 17 | D32: =F32/E32 -> 0.60416667 | E32: 48 | F32: 29 | G32: 401 | H32: =G32/F32 -> 13.827586 | I32: 3 | J32: =I32/F32 -> 0.10344828 | N32: =M32/L32 -> #DIV/0! | O32: 0 | P32: =O32/L32 -> #DIV/0! | S32: Coleman, Keon - BUF | T32: =(E32+L32)/($D$27+$L$27+$N$17+$E$47+$L$47) -> 0.067892504 | U32: =E32/($E$17) -> 0.13445378 | V32: =L32/($N$17+$D$27+$L$38+$L$47) -> 0 | X32: =($G32*('Scoring Format'!$B$4))+($I32*'Scoring Format'!$B$7)+($M32*('Scoring Format'!$B$3))+($O32*('Scoring Format'!$B$6)) -> 58.1 | Y32: =(F32*1)+(($G32*('Scoring Format'!$B$4))+($I32*'Scoring Format'!$B$7)+($M32*('Scoring Format'!$B$3))+($O32*('Scoring Format'!$B$6))) -> 87.1 | Z32: =(F32*0.5)+(($G32*('Scoring Format'!$B$4))+($I32*'Scoring Format'!$B$7)+($M32*('Scoring Format'!$B$3))+($O32*('Scoring Format'!$B$6))) -> 72.6 | AD32: Green, A.J. - ARI | AF32: =AH32/AG32 -> 0.60747664 | AG32: 107 | AH32: 65 | AI32: 710 | AJ32: =AI32/AH32 -> 10.923077 | AK32: 6 | AL32: =AK32/AH32 -> 0.092307692 | AN32: 0 | AO32: 0 | AP32: =AO32/AN32 -> #DIV/0! | AQ32: 0 | AR32: =AQ32/AN32 -> #DIV/0! | AV32: =(#REF!+AK32)/(#REF!+AK35) -> #REF! | AW32: =#REF!/(AK32+#REF!) -> #REF! | AX32: =AK32/(#REF!+AK32) -> #REF! | AZ32: =(AI32*0.1)+(AK32*6)+(AO32*0.1)+(AQ32*6) -> 107 | BA32: =(AH32*1)+(AI32*0.1)+(AK32*6)+(AO32*0.1)+(AQ32*6) -> 172
A33: WR*Shakir, Khalil - BUF | B33: 26 | C33: 17 | D33: =F33/E33 -> 0.77894737 | E33: 95 | F33: 74 | G33: 750 | H33: =G33/F33 -> 10.135135 | I33: 4 | J33: =I33/F33 -> 0.054054054 | N33: =M33/L33 -> #DIV/0! | O33: 0 | P33: =O33/L33 -> #DIV/0! | S33: Shakir, Khalil - BUF | T33: =(E33+L33)/($D$27+$L$27+$N$17+$E$47+$L$47) -> 0.13437058 | U33: =E33/($E$17) -> 0.26610644 | V33: =L33/($N$17+$D$27+$L$38+$L$47) -> 0 | X33: =($G33*('Scoring Format'!$B$4))+($I33*'Scoring Format'!$B$7)+($M33*('Scoring Format'!$B$3))+($O33*('Scoring Format'!$B$6)) -> 99 | Y33: =(F33*1)+(($G33*('Scoring Format'!$B$4))+($I33*'Scoring Format'!$B$7)+($M33*('Scoring Format'!$B$3))+($O33*('Scoring Format'!$B$6))) -> 173 | Z33: =(F33*0.5)+(($G33*('Scoring Format'!$B$4))+($I33*'Scoring Format'!$B$7)+($M33*('Scoring Format'!$B$3))+($O33*('Scoring Format'!$B$6))) -> 136 | AD33: Kirk, Christian- ARI | AF33: =AH33/AG33 -> 0.63333333 | AG33: 120 | AH33: 76 | AI33: 892 | AJ33: =AI33/AH33 -> 11.736842 | AK33: 5 | AL33: =AK33/AH33 -> 0.065789474 | AN33: 12 | AO33: 108 | AP33: =AO33/AN33 -> 9 | AQ33: 0 | AR33: =AQ33/AN33 -> 0 | AV33: =(#REF!+AK33)/(#REF!+AK36) -> #REF! | AW33: =#REF!/(AK33+#REF!) -> #REF! | AX33: =AK33/(#REF!+AK33) -> #REF! | AZ33: =(AI33*0.1)+(AK33*6)+(AO33*0.1)+(AQ33*6) -> 130 | BA33: =(AH33*1)+(AI33*0.1)+(AK33*6)+(AO33*0.1)+(AQ33*6) -> 206
A34: WR*Moore, DJ - BUF | B34: 29 | C34: 17 | D34: =F34/E34 -> 0.62280702 | E34: 114 | F34: 71 | G34: 860 | H34: =G34/F34 -> 12.112676 | I34: 6 | J34: =I34/F34 -> 0.084507042 | N34: =M34/L34 -> #DIV/0! | P34: =O34/L34 -> #DIV/0! | S34: Moore, DJ - BUF | T34: =(E34+L34)/($D$27+$L$27+$N$17+$E$47+$L$47) -> 0.1612447 | U34: =E34/($E$17) -> 0.31932773 | V34: =L34/($N$17+$D$27+$L$38+$L$47) -> 0 | X34: =($G34*('Scoring Format'!$B$4))+($I34*'Scoring Format'!$B$7)+($M34*('Scoring Format'!$B$3))+($O34*('Scoring Format'!$B$6)) -> 122 | Y34: =(F34*1)+(($G34*('Scoring Format'!$B$4))+($I34*'Scoring Format'!$B$7)+($M34*('Scoring Format'!$B$3))+($O34*('Scoring Format'!$B$6))) -> 193 | Z34: =(F34*0.5)+(($G34*('Scoring Format'!$B$4))+($I34*'Scoring Format'!$B$7)+($M34*('Scoring Format'!$B$3))+($O34*('Scoring Format'!$B$6))) -> 157.5 | AD34: Isabella, Andy - ARI | AF34: =AH34/AG34 -> 0.55 | AG34: 40 | AH34: 22 | AI34: 325 | AJ34: =AI34/AH34 -> 14.772727 | AK34: 2 | AL34: =AK34/AH34 -> 0.090909091 | AN34: 5 | AO34: 20 | AP34: =AO34/AN34 -> 4 | AQ34: 0 | AR34: =AQ34/AN34 -> 0 | AV34: =(#REF!+AK34)/(#REF!+AK37) -> #REF! | AW34: =#REF!/(AK34+#REF!) -> #REF! | AX34: =AK34/(#REF!+AK34) -> #REF! | AZ34: =(AI34*0.1)+(AK34*6)+(AO34*0.1)+(AQ34*6) -> 46.5 | BA34: =(AH34*1)+(AI34*0.1)+(AK34*6)+(AO34*0.1)+(AQ34*6) -> 68.5
A35: WR*Palmer, Joshua - BUF | B35: 27 | C35: 17 | D35: =F35/E35 -> 0.46153846 | E35: 13 | F35: 6 | G35: 71 | H35: =G35/F35 -> 11.833333 | I35: 0 | J35: =I35/F35 -> 0 | L35: 0 | M35: 0 | N35: =M35/L35 -> #DIV/0! | O35: 0 | P35: =O35/L35 -> #DIV/0! | S35: Palmer, Joshua - BUF | T35: =(E35+L35)/($D$27+$L$27+$N$17+$E$47+$L$47) -> 0.018387553 | U35: =E35/($E$17) -> 0.036414566 | V35: =L35/($N$17+$D$27+$L$38+$L$47) -> 0 | X35: =($G35*('Scoring Format'!$B$4))+($I35*'Scoring Format'!$B$7)+($M35*('Scoring Format'!$B$3))+($O35*('Scoring Format'!$B$6)) -> 7.1 | Y35: =(F35*1)+(($G35*('Scoring Format'!$B$4))+($I35*'Scoring Format'!$B$7)+($M35*('Scoring Format'!$B$3))+($O35*('Scoring Format'!$B$6))) -> 13.1 | Z35: =(F35*0.5)+(($G35*('Scoring Format'!$B$4))+($I35*'Scoring Format'!$B$7)+($M35*('Scoring Format'!$B$3))+($O35*('Scoring Format'!$B$6))) -> 10.1 | AD35: Hopkins, DeAndre - ARI | AF35: =AH35/AG35 -> 0.66206897 | AG35: 145 | AH35: 96 | AI35: 1098 | AJ35: =AI35/AH35 -> 11.4375 | AK35: 7 | AL35: =AK35/AH35 -> 0.072916667 | AN35: 0 | AO35: 0 | AP35: =AO35/AN35 -> #DIV/0! | AQ35: 0 | AR35: =AQ35/AN35 -> #DIV/0! | AV35: =(#REF!+AK35)/(#REF!+AK38) -> #REF! | AW35: =#REF!/(AK35+#REF!) -> #REF! | AX35: =AK35/(#REF!+AK35) -> #REF! | AZ35: =(AI35*0.1)+(AK35*6)+(AO35*0.1)+(AQ35*6) -> 151.8 | BA35: =(AH35*1)+(AI35*0.1)+(AK35*6)+(AO35*0.1)+(AQ35*6) -> 247.8
A36: WR*Bell, Skyler - BUF | B36: 23 | C36: 17 | D36: =F36/E36 -> 0.55 | E36: 20 | F36: 11 | G36: 180 | H36: =G36/F36 -> 16.363636 | I36: 2 | J36: =I36/F36 -> 0.18181818 | N36: =M36/L36 -> #DIV/0! | P36: =O36/L36 -> #DIV/0! | S36: Bell, Skyler - BUF | T36: =(E36+L36)/($D$27+$L$27+$N$17+$E$47+$L$47) -> 0.028288543 | U36: =E36/($E$17) -> 0.056022409 | V36: =L36/($N$17+$D$27+$L$38+$L$47) -> 0 | X36: =($G36*('Scoring Format'!$B$4))+($I36*'Scoring Format'!$B$7)+($M36*('Scoring Format'!$B$3))+($O36*('Scoring Format'!$B$6)) -> 30 | Y36: =(F36*1)+(($G36*('Scoring Format'!$B$4))+($I36*'Scoring Format'!$B$7)+($M36*('Scoring Format'!$B$3))+($O36*('Scoring Format'!$B$6))) -> 41 | Z36: =(F36*0.5)+(($G36*('Scoring Format'!$B$4))+($I36*'Scoring Format'!$B$7)+($M36*('Scoring Format'!$B$3))+($O36*('Scoring Format'!$B$6))) -> 35.5 | AD36: Johnson, KeeSean - ARI | AF36: =AH36/AG36 -> 0.6 | AG36: 10 | AH36: 6 | AI36: 100 | AJ36: =AI36/AH36 -> 16.666667 | AK36: 0 | AL36: =AK36/AH36 -> 0 | AN36: 0 | AO36: 0 | AP36: =AO36/AN36 -> #DIV/0! | AQ36: 0 | AR36: =AQ36/AN36 -> #DIV/0! | AV36: =(#REF!+AK36)/(#REF!+AK41) -> #REF! | AW36: =#REF!/(AK36+#REF!) -> #REF! | AX36: =AK36/(#REF!+AK36) -> #REF! | AZ36: =(AI36*0.1)+(AK36*6)+(AO36*0.1)+(AQ36*6) -> 10 | BA36: =(AH36*1)+(AI36*0.1)+(AK36*6)+(AO36*0.1)+(AQ36*6) -> 16
A37: WR*Shavers, Tyrell - BUF | B37: 28 | C37: 8 | D37: =F37/E37 -> 0.6 | E37: 10 | F37: 6 | G37: 85 | H37: =G37/F37 -> 14.166667 | I37: 0 | J37: =I37/F37 -> 0 | N37: =M37/L37 -> #DIV/0! | P37: =O37/L37 -> #DIV/0! | S37: Shavers, Tyrell - BUF | T37: =(E37+L37)/($D$27+$L$27+$N$17+$E$47+$L$47) -> 0.014144272 | U37: =E37/($E$17) -> 0.028011204 | V37: =L37/($N$17+$D$27+$L$38+$L$47) -> 0 | X37: =($G37*('Scoring Format'!$B$4))+($I37*'Scoring Format'!$B$7)+($M37*('Scoring Format'!$B$3))+($O37*('Scoring Format'!$B$6)) -> 8.5 | Y37: =(F37*1)+(($G37*('Scoring Format'!$B$4))+($I37*'Scoring Format'!$B$7)+($M37*('Scoring Format'!$B$3))+($O37*('Scoring Format'!$B$6))) -> 14.5 | Z37: =(F37*0.5)+(($G37*('Scoring Format'!$B$4))+($I37*'Scoring Format'!$B$7)+($M37*('Scoring Format'!$B$3))+($O37*('Scoring Format'!$B$6))) -> 11.5 | AD37: Moore, Rondale - ARI | AF37: =AH37/AG37 -> #DIV/0! | AL37: =AK37/AH37 -> #DIV/0! | AP37: =AO37/AN37 -> #DIV/0! | AR37: =AQ37/AN37 -> #DIV/0! | AV37: =(#REF!+AK37)/(#REF!+AK42) -> #REF! | AW37: =#REF!/(AK37+#REF!) -> #REF! | AX37: =AK37/(#REF!+AK37) -> #REF!
A38: Total | E38: =SUM(E32:E37) -> 300 | F38: =SUM(F32:F37) -> 197 | G38: =SUM(G32:G37) -> 2347 | I38: =SUM(I32:I37) -> 15 | L38: =SUM(L32:L37) -> 0 | M38: =SUM(M32:M37) -> 0 | O38: =SUM(O32:O37) -> 0 | AD38: Total | AG38: =SUM(AG32:AG37) -> 422 | AH38: =SUM(AH32:AH37) -> 265 | AI38: =SUM(AI32:AI37) -> 3125 | AK38: =SUM(AK32:AK37) -> 20 | AN38: =SUM(AN32:AN37) -> 17 | AO38: =SUM(AO32:AO37) -> 128 | AQ38: =SUM(AQ32:AQ37) -> 0
A41: Receiving | L41: Rushing | T41: Touches | AE41: Receiving | AN41: Rushing | AV41: Touches | AZ41: Fantasy Points
A42: Tes | B42: Age | C42: G | D42: Catch % | E42: Targets | F42: Rec | G42: Yds | H42: Yds/Rec | I42: TDs | J42: TDs/Rec | L42: Ratt | M42: Ryds | N42: Ryds/Att | O42: RTDs | P42: TDs/Att | S42: Tes | T42: Touch % | U42: Pct Pass | V42: Pct Run | X42: Fpts | Y42: PPR Fpts | Z42: .5 PPR | AD42: Tes | AE42: G | AF42: Catch % | AG42: Targets | AH42: Rec | AI42: Yds | AJ42: Yds/Rec | AK42: TDs | AL42: TDs/Rec | AN42: Ratt | AO42: Ryds | AP42: Ryds/Att | AQ42: RTDs | AR42: TDs/Att | AV42: Touch % | AW42: Pct Pass | AX42: Pct Run | AZ42: Fpts | BA42: PPR Fpts
A43: TE*Knox, Dawson - BUF | B43: 30 | C43: 17 | D43: =F43/E43 -> 0.53846154 | E43: 26 | F43: 14 | G43: 160 | H43: =G43/F43 -> 11.428571 | I43: 1 | J43: =I43/F43 -> 0.071428571 | L43: 0 | M43: 0 | N43: 0 | O43: 0 | P43: =O43/L43 -> #DIV/0! | S43: Knox, Dawson - BUF | T43: =(E43+L43)/($E$47+$L$47+$E$38+$L$38+$K$27+$D$27+$N$17) -> 0.025415445 | U43: =E43/($E$47+$E$38+$K$27) -> 0.051485149 | V43: =L43/($L$47+$L$38+$D$27+$N$17) -> 0 | X43: =($G43*('Scoring Format'!$B$4))+($I43*'Scoring Format'!$B$7)+($M43*('Scoring Format'!$B$3))+($O43*('Scoring Format'!$B$6)) -> 22 | Y43: =(F43*1)+(($G43*('Scoring Format'!$B$4))+($I43*'Scoring Format'!$B$7)+($M43*('Scoring Format'!$B$3))+($O43*('Scoring Format'!$B$6))) -> 36 | Z43: =(F43*0.5)+(($G43*('Scoring Format'!$B$4))+($I43*'Scoring Format'!$B$7)+($M43*('Scoring Format'!$B$3))+($O43*('Scoring Format'!$B$6))) -> 29 | AD43: Williams, Maxx - ARI | AF43: =AH43/AG43 -> 0.5625 | AG43: 16 | AH43: 9 | AI43: 108 | AJ43: =AI43/AH43 -> 12 | AK43: 1 | AL43: =AK43/AH43 -> 0.11111111 | AN43: 0 | AO43: 0 | AP43: 0 | AQ43: 0 | AR43: =AQ43/AN43 -> #DIV/0! | AV43: =(#REF!+AK43)/(#REF!+AK46) -> #REF! | AW43: =#REF!/(AK43+#REF!) -> #REF! | AX43: =AK43/(#REF!+AK43) -> #REF! | AZ43: =(AI43*0.1)+(AK43*6)+(AO43*0.1)+(AQ43*6) -> 16.8 | BA43: =(AH43*1)+(AI43*0.1)+(AK43*6)+(AO43*0.1)+(AQ43*6) -> 25.8
A44: TE*Kincaid, Dalton - BUF | B44: 27 | C44: 17 | D44: =F44/E44 -> 0.80555556 | E44: 72 | F44: 58 | G44: 740 | H44: =G44/F44 -> 12.758621 | I44: 6 | J44: =I44/F44 -> 0.10344828 | L44: 0 | M44: 0 | N44: 0 | O44: 0 | P44: =O44/L44 -> #DIV/0! | S44: Kincaid, Dalton - BUF | T44: =(E44+L44)/($E$47+$L$47+$E$38+$L$38+$K$27+$D$27+$N$17) -> 0.070381232 | U44: =E44/($E$47+$E$38+$K$27) -> 0.14257426 | V44: =L44/($L$47+$L$38+$D$27+$N$17) -> 0 | X44: =($G44*('Scoring Format'!$B$4))+($I44*'Scoring Format'!$B$7)+($M44*('Scoring Format'!$B$3))+($O44*('Scoring Format'!$B$6)) -> 110 | Y44: =(F44*1)+(($G44*('Scoring Format'!$B$4))+($I44*'Scoring Format'!$B$7)+($M44*('Scoring Format'!$B$3))+($O44*('Scoring Format'!$B$6))) -> 168 | Z44: =(F44*0.5)+(($G44*('Scoring Format'!$B$4))+($I44*'Scoring Format'!$B$7)+($M44*('Scoring Format'!$B$3))+($O44*('Scoring Format'!$B$6))) -> 139 | AD44: Daniels, Darenell - ARI | AF44: =AH44/AG44 -> 0.74285714 | AG44: 35 | AH44: 26 | AI44: 283 | AJ44: =AI44/AH44 -> 10.884615 | AK44: 2 | AL44: =AK44/AH44 -> 0.076923077 | AN44: 0 | AO44: 0 | AP44: 0 | AQ44: 0 | AR44: =AQ44/AN44 -> #DIV/0! | AV44: =(#REF!+AK44)/(#REF!+AK47) -> #REF! | AW44: =#REF!/(AK44+#REF!) -> #REF! | AX44: =AK44/(#REF!+AK44) -> #REF! | AZ44: =(AI44*0.1)+(AK44*6)+(AO44*0.1)+(AQ44*6) -> 40.3 | BA44: =(AH44*1)+(AI44*0.1)+(AK44*6)+(AO44*0.1)+(AQ44*6) -> 66.3
A45: TE*Hawes, Jackson - BUF | B45: 26 | C45: 17 | D45: =F45/E45 -> 0.86956522 | E45: 23 | F45: 20 | G45: 222 | H45: =G45/F45 -> 11.1 | I45: 2 | J45: =I45/F45 -> 0.1 | L45: 0 | M45: 0 | N45: 0 | O45: 0 | P45: =O45/L45 -> #DIV/0! | S45: Hawes, Jackson - BUF | T45: =(E45+L45)/($E$47+$L$47+$E$38+$L$38+$K$27+$D$27+$N$17) -> 0.022482893 | U45: =E45/($E$47+$E$38+$K$27) -> 0.045544554 | V45: =L45/($L$47+$L$38+$D$27+$N$17) -> 0 | X45: =($G45*('Scoring Format'!$B$4))+($I45*'Scoring Format'!$B$7)+($M45*('Scoring Format'!$B$3))+($O45*('Scoring Format'!$B$6)) -> 34.2 | Y45: =(F45*1)+(($G45*('Scoring Format'!$B$4))+($I45*'Scoring Format'!$B$7)+($M45*('Scoring Format'!$B$3))+($O45*('Scoring Format'!$B$6))) -> 54.2 | Z45: =(F45*0.5)+(($G45*('Scoring Format'!$B$4))+($I45*'Scoring Format'!$B$7)+($M45*('Scoring Format'!$B$3))+($O45*('Scoring Format'!$B$6))) -> 44.2 | AD45: Bunting, Ian - ARI | AF45: =AH45/AG45 -> 0.5 | AG45: 12 | AH45: 6 | AI45: 65 | AJ45: =AI45/AH45 -> 10.833333 | AK45: 0 | AL45: =AK45/AH45 -> 0 | AN45: 0 | AO45: 0 | AP45: 0 | AQ45: 0 | AR45: =AQ45/AN45 -> #DIV/0! | AV45: =(#REF!+AK45)/(#REF!+AI49) -> #REF! | AW45: =#REF!/(AK45+#REF!) -> #REF! | AX45: =AK45/(#REF!+AK45) -> #REF! | AZ45: =(AI45*0.1)+(AK45*6)+(AO45*0.1)+(AQ45*6) -> 6.5 | BA45: =(AH45*1)+(AI45*0.1)+(AK45*6)+(AO45*0.1)+(AQ45*6) -> 12.5
D46: =F46/E46 -> #DIV/0! | H46: =G46/F46 -> #DIV/0! | J46: =I46/F46 -> #DIV/0! | N46: 0 | O46: 0 | P46: =O46/L46 -> #DIV/0! | T46: =(E46+L46)/($E$47+$L$47+$E$38+$L$38+$K$27+$D$27+$N$17) -> 0 | U46: =E46/($E$47+$E$38+$K$27) -> 0 | V46: =L46/($L$47+$L$38+$D$27+$N$17) -> 0 | X46: =($G46*('Scoring Format'!$B$4))+($I46*'Scoring Format'!$B$7)+($M46*('Scoring Format'!$B$3))+($O46*('Scoring Format'!$B$6)) -> 0 | Y46: =(F46*1)+(($G46*('Scoring Format'!$B$4))+($I46*'Scoring Format'!$B$7)+($M46*('Scoring Format'!$B$3))+($O46*('Scoring Format'!$B$6))) -> 0 | Z46: =(F46*0.5)+(($G46*('Scoring Format'!$B$4))+($I46*'Scoring Format'!$B$7)+($M46*('Scoring Format'!$B$3))+($O46*('Scoring Format'!$B$6))) -> 0 | AF46: =AH46/AG46 -> #DIV/0! | AJ46: =AI46/AH46 -> #DIV/0! | AL46: =AK46/AH46 -> #DIV/0! | AQ46: 0 | AR46: =AQ46/AN46 -> #DIV/0! | AV46: =(#REF!+AK46)/(#REF!+AI50) -> #REF! | AW46: =#REF!/(AK46+#REF!) -> #REF! | AX46: =AK46/(#REF!+AK46) -> #REF! | AZ46: =(AI46*0.1)+(AK46*6)+(AO46*0.1)+(AQ46*6) -> 0 | BA46: =(AH46*1)+(AI46*0.1)+(AK46*6)+(AO46*0.1)+(AQ46*6) -> 0
A47: Total | E47: =SUM(E43:E46) -> 121 | F47: =SUM(F43:F46) -> 92 | G47: =SUM(G43:G46) -> 1122 | I47: =SUM(I43:I46) -> 9 | L47: =SUM(L43:L46) -> 0 | M47: =SUM(M43:M46) -> 0 | O47: =SUM(O43:O46) -> 0 | AD47: Total | AG47: =SUM(AG43:AG46) -> 63 | AH47: =SUM(AH43:AH46) -> 41 | AI47: =SUM(AI43:AI46) -> 456 | AK47: =SUM(AK43:AK46) -> 3 | AN47: =SUM(AN43:AN46) -> 0 | AO47: =SUM(AO43:AO46) -> 0 | AQ47: =SUM(AQ43:AQ46) -> 0
A50: Team Totals and Splits | J50: Taxi Squad* | R50: Injured Reserve | AC50: Team Totals and Splits | AL50: Taxi Squad* | AT50: Injured Reserve
B51: Targets | C51: Rec. | D51: Yds | E51: TDs | J51: Player | N51: Position | R51: Player | V51: Position | AD51: Targets | AE51: Rec. | AF51: Yds | AG51: TDs | AL51: Player | AP51: Position | AT51: Player | AX51: Position
A52: Rec Totals | B52: =SUM(K22:K26,E32:E37,E43:E46) -> 505 | C52: =SUM(F43:F46,F32:F37,L22:L26) -> 357 | D52: =SUM(G43:G46,G32:G37,M22:M26) -> 4108 | E52: =SUM(O22:O26,I32:I37,I43:I46) -> 29 | J52: Mecole Hardman | N52: WR | R52: Desmond Reid | V52: RB | AC52: Rec Totals | AD52: =SUM(AM22:AM26,AG32:AG37,AG43:AG46) -> 583 | AE52: =SUM(AH43:AH46,AH32:AH37,AM22:AM26) -> 404 | AF52: =SUM(AI43:AI46,AI32:AI37,AN22:AN26) -> 3653 | AG52: =SUM(AQ22:AQ26,AK32:AK37,AK43:AK46) -> 27
A53: QB Totals | B53: =SUM(D17) -> 505 | C53: =SUM(E17) -> 357 | D53: =SUM(G17) -> 4108 | E53: =SUM(I17) -> 29 | J53: Frank Gore, Jr. | N53: RB | AC53: QB Totals | AD53: =SUM(AF17) -> 583 | AE53: =SUM(AG17) -> 378 | AF53: =SUM(AI17) -> 4072 | AG53: =SUM(AK17) -> 27
A54: League Att Avg. | J54: Jalen Virgil | N54: WR | AC54: League Att Avg.
J55: Trent Sherfield | N55: WR
B56: Att | C56: Yards | D56: TDs | J56: Ja'Mori Maclin | N56: WR | AD56: Att | AE56: Yards | AF56: TDs
A57: Rush Totals | B57: =SUM(N14:N16,D22:D26,L32:L37,L43:L46) -> 518 | C57: =SUM(O14:O16,E22:E26,M32:M37,M43:M46) -> 2677 | D57: =SUM(Q14:Q16,G22:G26,O32:O37,O43:O46) -> 28 | J57: Shane Zylstra | N57: TE | AC57: Rush Totals | AD57: =SUM(AP14:AP16,AF22:AF26,AN32:AN37,AN43:AN46) -> 421 | AE57: =SUM(AQ14:AQ16,AG22:AG26,AO32:AO37,AO43:AO46) -> 2231 | AF57: =SUM(AS14:AS16,AI22:AI26,AQ32:AQ37,AQ43:AQ46) -> 18
A58: League Att Avg. | J58: Keleki Latu | N58: TE | AC58: League Att Avg.
J59: Ian Wheeler | N59: RB
B60: Run | C60: Pass | AD60: Run | AE60: Pass
A61: Run/Pass Pct | B61: =B57/(B53+B57) -> 0.50635386 | C61: =B53/(B53+B57) -> 0.49364614 | AC61: Run/Pass Pct | AD61: =AD57/(AD53+AD57) -> 0.41932271 | AE61: =AD53/(AD53+AD57) -> 0.58067729 | AL61: *Projected options during offseason/Actual options during the season.
A62: League Average | J62: *Projected options during offseason/Actual options during the season. | AC62: League Average
A73: Team Projections Menu
H75: RSP Projections: Year 1 | M75: Adjustable Projections: Year 1 | S75: Offense Distribution
H76: RSP Projections: Year 2 | M76: Past Run/Pass Performances | S76: Run | T76: Pass
S77: =(M87+C97+K108+K117)/(M87+C97+K108+C87) -> #DIV/0! | T77: =C87/(C87+M87+C97+K108+K117) -> #DIV/0!
A80: RSP Projections: Year 2
C81: Passing | L81: Rushing | R81: Touches | V81: Fantasy Points
A82: QB | B82: G | C82: Att | D82: Comp | E82: Pct | F82: Yards | G82: Yds/Att | H82: TDs | I82: TDs/Att | J82: Int | K82: Int/Att | M82: Ratt | N82: Ryds | O82: Ryds/Att | P82: TDs | Q82: Tds/Att | S82: Touch % | T82: Pct Pass | U82: Pct Run | W82: Fpts
E83: =D83/C83 -> #DIV/0! | G83: =F83/C83 -> #DIV/0! | I83: =H83/C83 -> #DIV/0! | K83: =J83/C83 -> #DIV/0! | O83: =N83/M83 -> #DIV/0! | Q83: =P83/M83 -> #DIV/0! | S83: =(C83+M83)/($D$17+$N$17) -> 0 | T83: =C83/($D$17) -> 0 | U83: =M83/($N$17) -> 0 | W83: =(F83*0.05)+(H83*4)+(J83*-1)+(N83*0.1)+(P83*6) -> 0 | X83: Adjusted
E84: =D84/C84 -> #DIV/0! | G84: =F84/C84 -> #DIV/0! | I84: =H84/C84 -> #DIV/0! | K84: =J84/C84 -> #DIV/0! | O84: =N84/M84 -> #DIV/0! | Q84: =P84/M84 -> #DIV/0! | S84: =(C84+M84)/($D$17+$N$17) -> 0 | T84: =C84/($D$17) -> 0 | U84: =M84/($N$17) -> 0 | W84: =(F84*0.05)+(H84*4)+(J84*-1)+(N84*0.1)+(P84*6) -> 0 | X84: =((F84*0.05)+(H84*4)+(J84*-1)+(N84*0.1)+(P84*6))*0.4 -> 0
E85: =D85/C85 -> #DIV/0! | G85: =F85/C85 -> #DIV/0! | I85: =H85/C85 -> #DIV/0! | K85: =J85/C85 -> #DIV/0! | O85: =N85/M85 -> #DIV/0! | Q85: =P85/M85 -> #DIV/0! | S85: =(C85+M85)/($D$17+$N$17) -> 0 | T85: =C85/($D$17) -> 0 | U85: =M85/($N$17) -> 0 | W85: =(F85*0.05)+(H85*4)+(J85*-1)+(N85*0.1)+(P85*6) -> 0 | X85: =((F85*0.05)+(H85*4)+(J85*-1)+(N85*0.1)+(P85*6))*0.4 -> 0
A86: Total | C86: =SUM(C83:C85) -> 0 | D86: =SUM(D83:D85) -> 0 | F86: =SUM(F83:F85) -> 0 | H86: =SUM(H83:H85) -> 0 | J86: =SUM(J83:J85) -> 0 | M86: =SUM(M83:M85) -> 0 | N86: =SUM(N83:N85) -> 0 | P86: =SUM(P83:P85) -> 0 | S86: =S83+S84+S85 -> 0 | T86: =C86/(C86+M86) -> #DIV/0! | U86: =M86/(M86+C86) -> #DIV/0! | X86: =((F86*0.05)+(H86*4)+(J86*-1)+(N86*0.1)+(P86*6))*0.4 -> 0
A89: Rushing | H89: Receiving | R89: Touches | V89: Fantasy Points
A90: RB | B90: G | C90: Att | D90: Yards | E90: Yds/Att | F90: TDs | G90: TDs/Att | I90: Catch % | J90: Targets | K90: Rec | L90: Yds | M90: Yds/Rec | N90: TDs | O90: TDs/Rec | R90: RB | S90: Touch % | T90: Pct Pass | U90: Pct Run | W90: Fpts
E91: =D91/C91 -> #DIV/0! | G91: =F91/C91 -> #DIV/0! | I91: =K91/J91 -> #DIV/0! | M91: =L91/K91 -> #DIV/0! | O91: =N91/K91 -> #DIV/0! | R91: Cook, James - BUF | S91: =(C91+J91)/($D$27+$K$27+$N$17+$E$17+$L$38+$L$47) -> 0 | T91: =J91/($K$27+$F$38+$F$47) -> 0 | U91: =C91/($D$27+$N$17+$L$38+$L$47) -> 0 | W91: =(D91*0.1)+(F91*6)+(L91*0.1)+(N91*6) -> 0 | X91: PPR Fpts | Y91: .5 PPR
E92: =D92/C92 -> #DIV/0! | G92: =F92/C92 -> #DIV/0! | I92: =K92/J92 -> #DIV/0! | M92: =L92/K92 -> #DIV/0! | O92: =N92/K92 -> #DIV/0! | S92: =(C92+J92)/($D$27+$K$27+$N$17+$E$17+$L$38+$L$47) -> 0 | T92: =J92/($K$27+$F$38+$F$47) -> 0 | U92: =C92/($D$27+$N$17+$L$38+$L$47) -> 0 | W92: =(D92*0.1)+(F92*6)+(L92*0.1)+(N92*6) -> 0 | X92: =(D92*0.1)+(F92*6)+(K92*1)+(L92*0.1)+(N92*6) -> 0 | Y92: =(D92*0.1)+(F92*6)+(K92*0.5)+(L92*0.1)+(N92*6) -> 0
E93: =D93/C93 -> #DIV/0! | G93: =F93/C93 -> #DIV/0! | I93: =K93/J93 -> #DIV/0! | M93: =L93/K93 -> #DIV/0! | O93: =N93/K93 -> #DIV/0! | R93: Harris, Damien - BUF | S93: =(C93+J93)/($D$27+$K$27+$N$17+$E$17+$L$38+$L$47) -> 0 | T93: =J93/($K$27+$F$38+$F$47) -> 0 | U93: =C93/($D$27+$N$17+$L$38+$L$47) -> 0 | W93: =(D93*0.1)+(F93*6)+(L93*0.1)+(N93*6) -> 0 | X93: =(D93*0.1)+(F93*6)+(K93*1)+(L93*0.1)+(N93*6) -> 0 | Y93: =(D93*0.1)+(F93*6)+(K93*0.5)+(L93*0.1)+(N93*6) -> 0
E94: =D94/C94 -> #DIV/0! | G94: =F94/C94 -> #DIV/0! | I94: =K94/J94 -> #DIV/0! | M94: =L94/K94 -> #DIV/0! | O94: =N94/K94 -> #DIV/0! | S94: =(C94+J94)/($D$27+$K$27+$N$17+$E$17+$L$38+$L$47) -> 0 | T94: =J94/($K$27+$F$38+$F$47) -> 0 | U94: =C94/($D$27+$N$17+$L$38+$L$47) -> 0 | W94: =(D94*0.1)+(F94*6)+(L94*0.1)+(N94*6) -> 0 | X94: =(D94*0.1)+(F94*6)+(K94*1)+(L94*0.1)+(N94*6) -> 0 | Y94: =(D94*0.1)+(F94*6)+(K94*0.5)+(L94*0.1)+(N94*6) -> 0
E95: =D95/C95 -> #DIV/0! | G95: =F95/C95 -> #DIV/0! | I95: =K95/J95 -> #DIV/0! | M95: =L95/K95 -> #DIV/0! | O95: =N95/K95 -> #DIV/0! | S95: =(C95+J95)/($D$27+$K$27+$N$17+$E$17+$L$38+$L$47) -> 0 | T95: =J95/($K$27+$F$38+$F$47) -> 0 | U95: =C95/($D$27+$N$17+$L$38+$L$47) -> 0 | W95: =(D95*0.1)+(F95*6)+(L95*0.1)+(N95*6) -> 0 | X95: =(D95*0.1)+(F95*6)+(K95*1)+(L95*0.1)+(N95*6) -> 0 | Y95: =(D95*0.1)+(F95*6)+(K95*0.5)+(L95*0.1)+(N95*6) -> 0
A96: Total | C96: =SUM(C91:C95) -> 0 | D96: =SUM(D91:D95) -> 0 | F96: =SUM(F91:F95) -> 0 | J96: =SUM(J91:J95) -> 0 | K96: =SUM(K91:K95) -> 0 | L96: =SUM(L91:L95) -> 0 | N96: =SUM(N91:N95) -> 0 | X96: =(D96*0.1)+(F96*6)+(K96*1)+(L96*0.1)+(N96*6) -> 0 | Y96: =(D96*0.1)+(F96*6)+(K96*0.5)+(L96*0.1)+(N96*6) -> 0
A99: Receiving | J99: Rushing | R99: Touches | V99: Fantasy Points
A100: WRs | B100: G | C100: Catch % | D100: Targets | E100: Rec | F100: Yds | G100: Yds/Rec | H100: TDs | I100: TDs/Rec | K100: Ratt | L100: Ryds | M100: Ryds/Att | N100: RTds | O100: TDs/Att | R100: WRs | S100: Touch % | T100: Pct Pass | U100: Pct Run | W100: Fpts
C101: =E101/D101 -> #DIV/0! | G101: =F101/E101 -> #DIV/0! | I101: =H101/E101 -> #DIV/0! | M101: =L101/K101 -> #DIV/0! | O101: =N101/K101 -> #DIV/0! | R101: Diggs, Stefon - BUF | S101: =(D101+K101)/($D$27+$L$27+$N$17+$E$47+$L$47) -> 0 | T101: =D101/($E$17) -> 0 | U101: =K101/($N$17+$D$27+$L$38+$L$47) -> 0 | W101: =(F101*0.1)+(H101*6)+(L101*0.1)+(N101*6) -> 0 | X101: PPR Fpts | Y101: .5PPR
C102: =E102/D102 -> #DIV/0! | G102: =F102/E102 -> #DIV/0! | I102: =H102/E102 -> #DIV/0! | M102: =L102/K102 -> #DIV/0! | O102: =N102/K102 -> #DIV/0! | R102: Shakir, Khalil - BUF | S102: =(D102+K102)/($D$27+$L$27+$N$17+$E$47+$L$47) -> 0 | T102: =D102/($E$17) -> 0 | U102: =K102/($N$17+$D$27+$L$38+$L$47) -> 0 | W102: =(F102*0.1)+(H102*6)+(L102*0.1)+(N102*6) -> 0 | X102: =(E102*1)+(F102*0.1)+(H102*6)+(L102*0.1)+(N102*6) -> 0 | Y102: =(E102*0.5)+(F102*0.1)+(H102*6)+(L102*0.1)+(N102*6) -> 0
C103: =E103/D103 -> #DIV/0! | G103: =F103/E103 -> #DIV/0! | I103: =H103/E103 -> #DIV/0! | M103: =L103/K103 -> #DIV/0! | O103: =N103/K103 -> #DIV/0! | S103: =(D103+K103)/($D$27+$L$27+$N$17+$E$47+$L$47) -> 0 | T103: =D103/($E$17) -> 0 | U103: =K103/($N$17+$D$27+$L$38+$L$47) -> 0 | W103: =(F103*0.1)+(H103*6)+(L103*0.1)+(N103*6) -> 0 | X103: =(E103*1)+(F103*0.1)+(H103*6)+(L103*0.1)+(N103*6) -> 0 | Y103: =(E103*0.5)+(F103*0.1)+(H103*6)+(L103*0.1)+(N103*6) -> 0
C104: =E104/D104 -> #DIV/0! | G104: =F104/E104 -> #DIV/0! | I104: =H104/E104 -> #DIV/0! | M104: =L104/K104 -> #DIV/0! | O104: =N104/K104 -> #DIV/0! | S104: =(D104+K104)/($D$27+$L$27+$N$17+$E$47+$L$47) -> 0 | T104: =D104/($E$17) -> 0 | U104: =K104/($N$17+$D$27+$L$38+$L$47) -> 0 | W104: =(F104*0.1)+(H104*6)+(L104*0.1)+(N104*6) -> 0 | X104: =(E104*1)+(F104*0.1)+(H104*6)+(L104*0.1)+(N104*6) -> 0 | Y104: =(E104*0.5)+(F104*0.1)+(H104*6)+(L104*0.1)+(N104*6) -> 0
C105: =E105/D105 -> #DIV/0! | G105: =F105/E105 -> #DIV/0! | I105: =H105/E105 -> #DIV/0! | M105: =L105/K105 -> #DIV/0! | O105: =N105/K105 -> #DIV/0! | R105: Harty, Deonte - BUF | S105: =(D105+K105)/($D$27+$L$27+$N$17+$E$47+$L$47) -> 0 | T105: =D105/($E$17) -> 0 | U105: =K105/($N$17+$D$27+$L$38+$L$47) -> 0 | W105: =(F105*0.1)+(H105*6)+(L105*0.1)+(N105*6) -> 0 | X105: =(E105*1)+(F105*0.1)+(H105*6)+(L105*0.1)+(N105*6) -> 0 | Y105: =(E105*0.5)+(F105*0.1)+(H105*6)+(L105*0.1)+(N105*6) -> 0
C106: =E106/D106 -> #DIV/0! | G106: =F106/E106 -> #DIV/0! | I106: =H106/E106 -> #DIV/0! | M106: =L106/K106 -> #DIV/0! | O106: =N106/K106 -> #DIV/0! | R106: Shorter, Justin - BUF | S106: =(D106+K106)/($D$27+$L$27+$N$17+$E$47+$L$47) -> 0 | T106: =D106/($E$17) -> 0 | U106: =K106/($N$17+$D$27+$L$38+$L$47) -> 0 | W106: =(F106*0.1)+(H106*6)+(L106*0.1)+(N106*6) -> 0 | X106: =(E106*1)+(F106*0.1)+(H106*6)+(L106*0.1)+(N106*6) -> 0 | Y106: =(E106*0.5)+(F106*0.1)+(H106*6)+(L106*0.1)+(N106*6) -> 0
A107: Total | D107: =SUM(D101:D106) -> 0 | E107: =SUM(E101:E106) -> 0 | F107: =SUM(F101:F106) -> 0 | H107: =SUM(H101:H106) -> 0 | K107: =SUM(K101:K106) -> 0 | L107: =SUM(L101:L106) -> 0 | N107: =SUM(N101:N106) -> 0 | X107: =(E107*1)+(F107*0.1)+(H107*6)+(L107*0.1)+(N107*6) -> 0 | Y107: =(E107*0.5)+(F107*0.1)+(H107*6)+(L107*0.1)+(N107*6) -> 0
A110: Receiving | J110: Rushing | R110: Touches | V110: Fantasy Points
A111: Tes | B111: G | C111: Catch % | D111: Targets | E111: Rec | F111: Yds | G111: Yds/Rec | H111: TDs | I111: TDs/Rec | K111: Ratt | L111: Ryds | M111: Ryds/Att | N111: RTDs | O111: TDs/Att | R111: Tes | S111: Touch % | T111: Pct Pass | U111: Pct Run | W111: Fpts
C112: =E112/D112 -> #DIV/0! | G112: =F112/E112 -> #DIV/0! | I112: =H112/E112 -> #DIV/0! | K112: 0 | L112: 0 | M112: 0 | N112: 0 | O112: =N112/K112 -> #DIV/0! | S112: =(D112+K112)/($E$47+$L$47+$E$38+$L$38+$K$27+$D$27+$N$17) -> 0 | T112: =D112/($E$47+$E$38+$K$27) -> 0 | U112: =K112/($L$47+$L$38+$D$27+$N$17) -> 0 | W112: =(F112*0.1)+(H112*6)+(L112*0.1)+(N112*6) -> 0 | X112: PPR Fpts | Y112: .5 PPR
C113: =E113/D113 -> #DIV/0! | G113: =F113/E113 -> #DIV/0! | I113: =H113/E113 -> #DIV/0! | K113: 0 | L113: 0 | M113: 0 | N113: 0 | O113: =N113/K113 -> #DIV/0! | S113: =(D113+K113)/($E$47+$L$47+$E$38+$L$38+$K$27+$D$27+$N$17) -> 0 | T113: =D113/($E$47+$E$38+$K$27) -> 0 | U113: =K113/($L$47+$L$38+$D$27+$N$17) -> 0 | W113: =(F113*0.1)+(H113*6)+(L113*0.1)+(N113*6) -> 0 | X113: =(E113*1)+(F113*0.1)+(H113*6)+(L113*0.1)+(N113*6) -> 0 | Y113: =(E113*0.5)+(F113*0.1)+(H113*6)+(L113*0.1)+(N113*6) -> 0
C114: =E114/D114 -> #DIV/0! | G114: =F114/E114 -> #DIV/0! | I114: =H114/E114 -> #DIV/0! | K114: 0 | L114: 0 | M114: 0 | N114: 0 | O114: =N114/K114 -> #DIV/0! | S114: =(D114+K114)/($E$47+$L$47+$E$38+$L$38+$K$27+$D$27+$N$17) -> 0 | T114: =D114/($E$47+$E$38+$K$27) -> 0 | U114: =K114/($L$47+$L$38+$D$27+$N$17) -> 0 | W114: =(F114*0.1)+(H114*6)+(L114*0.1)+(N114*6) -> 0 | X114: =(E114*1)+(F114*0.1)+(H114*6)+(L114*0.1)+(N114*6) -> 0 | Y114: =(E114*0.5)+(F114*0.1)+(H114*6)+(L114*0.1)+(N114*6) -> 0
C115: =E115/D115 -> #DIV/0! | G115: =F115/E115 -> #DIV/0! | I115: =H115/E115 -> #DIV/0! | M115: 0 | N115: 0 | O115: =N115/K115 -> #DIV/0! | S115: =(D115+K115)/($E$47+$L$47+$E$38+$L$38+$K$27+$D$27+$N$17) -> 0 | T115: =D115/($E$47+$E$38+$K$27) -> 0 | U115: =K115/($L$47+$L$38+$D$27+$N$17) -> 0 | W115: =(F115*0.1)+(H115*6)+(L115*0.1)+(N115*6) -> 0 | X115: =(E115*1)+(F115*0.1)+(H115*6)+(L115*0.1)+(N115*6) -> 0 | Y115: =(E115*0.5)+(F115*0.1)+(H115*6)+(L115*0.1)+(N115*6) -> 0
A116: Total | D116: =SUM(D112:D115) -> 0 | E116: =SUM(E112:E115) -> 0 | F116: =SUM(F112:F115) -> 0 | H116: =SUM(H112:H115) -> 0 | K116: =SUM(K112:K115) -> 0 | L116: =SUM(L112:L115) -> 0 | N116: =SUM(N112:N115) -> 0 | X116: =(E116*1)+(F116*0.1)+(H116*6)+(L116*0.1)+(N116*6) -> 0 | Y116: =(E116*0.5)+(F116*0.1)+(H116*6)+(L116*0.1)+(N116*6) -> 0
A119: Team Totals and Splits | J119: Taxi Squad* | R119: Injured Reserve
B120: Targets | C120: Rec. | D120: Yds | E120: TDs | J120: Player | N120: Position | R120: Player | V120: Position
A121: Rec Totals | B121: =SUM(J91:J95,D101:D106,D112:D115) -> 0 | C121: =SUM(E112:E115,E101:E106,K91:K95) -> 0 | D121: =SUM(F112:F115,F101:F106,L91:L95) -> 0 | E121: =SUM(N91:N95,H101:H106,H112:H115) -> 0
A122: QB Totals | B122: =SUM(C86) -> 0 | C122: =SUM(D86) -> 0 | D122: =SUM(F86) -> 0 | E122: =SUM(H86) -> 0
A123: League Att Avg.
B125: Att | C125: Yards | D125: TDs
A126: Rush Totals | B126: =SUM(M83:M85,C91:C95,K101:K106,K112:K115) -> 0 | C126: =SUM(N83:N85,D91:D95,L101:L106,L112:L115) -> 0 | D126: =SUM(P83:P85,F91:F95,N101:N106,N112:N115) -> 0
A127: League Att Avg.
B129: Run | C129: Pass
A130: Run/Pass Pct | B130: =B126/(B122+B126) -> #DIV/0! | C130: =B122/(B122+B126) -> #DIV/0! | J130: *Projected options during offseason/Actual options during the season.
A131: League Average
B132: Run | C132: Pass
A139: 2-Year Team Historical Performance
H141: RSP Projections: Year 1 | M141: Adjustable Projections: Year 1
H142: RSP Projections: Year 2
D145: Historical Production | P145: Touch Distribution
...

Sheet CAR
A1: Carolina Panthers
A3: Team Projections Menu | AC3: Team Projections Menu
H5: RSP Projections: Year 1 | M5: Adjustable Projections: Year 1 | S5: Offense Distribution | AJ5: RSP Projections: Year 1 | AO5: Adjustable Projections: Year 1
H6: RSP Projections: Year 2 | M6: Past Run/Pass Performances | S6: Run | T6: Pass | AJ6: RSP Projections: Year 2
S7: =(N17+D27+L38+L47)/(N17+D27+L38+D17) -> 0.46194503 | T7: =D17/(D17+N17+D27+L38+L47) -> 0.53805497
A10: RSP Projections: Year 1 | AC10: Adjustable Projections: Year 1
C12: Passing | L12: Rushing | R12: Touches | V12: Fantasy Points | AE12: Passing | AN12: Rushing | AT12: Touches | AX12: Fantasy Points
A13: QB | B13: Age | C13: G | D13: Att | E13: Comp | F13: Pct | G13: Yards | H13: Yds/Att | I13: TDs | J13: TDs/Att | K13: Int | L13: Int/Att | N13: Ratt | O13: Ryds | P13: Ryds/Att | Q13: TDs | R13: Tds/Att | T13: Touch % | U13: Pct Pass | V13: Pct Run | X13: Fpts | Y13: Adjusted | AD13: QB | AE13: G | AF13: Att | AG13: Comp | AH13: Pct | AI13: Yards | AJ13: Yds/Att | AK13: TDs | AL13: TDs/Att | AM13: Int | AN13: Int/Att | AP13: Ratt | AQ13: Ryds | AR13: Ryds/Att | AS13: TDs | AT13: Tds/Att | AV13: Touch % | AW13: Pct Pass | AX13: Pct Run | AZ13: Fpts | BA13: Adjusted
A14: QB*Young, Bryce - CAR | B14: 24 | C14: 17 | D14: 509 | E14: 335 | F14: =E14/D14 -> 0.65815324 | G14: 3541 | H14: =G14/D14 -> 6.956778 | I14: 27 | J14: =I14/D14 -> 0.053045187 | K14: 14 | L14: =K14/D14 -> 0.027504912 | N14: 59 | O14: 214 | P14: =O14/N14 -> 3.6271186 | Q14: 2 | R14: =Q14/N14 -> 0.033898305 | T14: =(D14+N14)/($D$17+$N$17) -> 1 | U14: =D14/($D$17) -> 1 | V14: =N14/($N$17) -> 1 | X14: =($G14*('Scoring Format'!$B$2))+($I14*('Scoring Format'!$B$5))+($K14*('Scoring Format'!$B$8))+($O14*('Scoring Format'!$B$3))+($Q14*('Scoring Format'!$B$6)) -> 304.45 | Y14: =(($G14*('Scoring Format'!$B$2))+($I14*('Scoring Format'!$B$5))+($K14*('Scoring Format'!$B$8))+($O14*('Scoring Format'!$B$3))+($Q14*('Scoring Format'!$B$6)))*0.4 -> 121.78 | AD14: Murray, Kyler - ARI | AF14: 583 | AG14: 378 | AH14: =AG14/AF14 -> 0.6483705 | AI14: 4072 | AJ14: =AI14/AF14 -> 6.9845626 | AK14: 27 | AL14: =AK14/AF14 -> 0.046312178 | AM14: 11 | AN14: =AM14/AF14 -> 0.018867925 | AP14: 100 | AQ14: 590 | AR14: =AQ14/AP14 -> 5.9 | AS14: 5 | AT14: =AS14/AP14 -> 0.05 | AV14: =(AF14+AP14)/(AF17+AP17) -> 1 | AW14: =AF14/(AP14+AF14) -> 0.85358712 | AX14: =AP14/(AF14+AP14) -> 0.14641288 | AZ14: =((AI14*0.05)+(AK14*4)+(AM14*-1)+(AQ14*0.1)+(AS14*6))*0.55 -> 214.28 | BA14: =((AI14*0.05)+(AK14*4)+(AM14*-1)+(AQ14*0.1)+(AS14*6))*0.4 -> 155.84
A15: QB*Pickett, Kenny - CAR | B15: 27 | F15: =E15/D15 -> #DIV/0! | H15: =G15/D15 -> #DIV/0! | J15: =I15/D15 -> #DIV/0! | L15: =K15/D15 -> #DIV/0! | P15: =O15/N15 -> #DIV/0! | R15: =Q15/N15 -> #DIV/0! | T15: =(D15+N15)/($D$17+$N$17) -> 0 | U15: =D15/($D$17) -> 0 | V15: =N15/($N$17) -> 0 | X15: =($G15*('Scoring Format'!$B$2))+($I15*('Scoring Format'!$B$5))+($K15*('Scoring Format'!$B$8))+($O15*('Scoring Format'!$B$3))+($Q15*('Scoring Format'!$B$6)) -> 0 | Y15: =(($G15*('Scoring Format'!$B$2))+($I15*('Scoring Format'!$B$5))+($K15*('Scoring Format'!$B$8))+($O15*('Scoring Format'!$B$3))+($Q15*('Scoring Format'!$B$6)))*0.4 -> 0 | AD15: McCoy, Colt - ARI | AF15: 0 | AG15: 0 | AH15: 0 | AI15: 0 | AK15: 0 | AL15: =AK15/AF15 -> #DIV/0! | AM15: 0 | AN15: =AM15/AF15 -> #DIV/0! | AP15: 0 | AQ15: 0 | AS15: 0 | AT15: =AS15/AP15 -> #DIV/0! | AV15: =(AF15+AP15)/(AD18+AN18) -> #DIV/0! | AW15: =AF15/(AP15+AF15) -> #DIV/0! | AX15: =AP15/(AF15+AP15) -> #DIV/0!
A16: QB*Grier, Will - CAR | B16: 31 | F16: =E16/D16 -> #DIV/0! | H16: =G16/D16 -> #DIV/0! | J16: =I16/D16 -> #DIV/0! | L16: =K16/D16 -> #DIV/0! | P16: =O16/N16 -> #DIV/0! | Q16: 0 | R16: =Q16/N16 -> #DIV/0! | T16: =(D16+N16)/($D$17+$N$17) -> 0 | U16: =D16/($D$17) -> 0 | V16: =N16/($N$17) -> 0 | X16: =($G16*('Scoring Format'!$B$2))+($I16*('Scoring Format'!$B$5))+($K16*('Scoring Format'!$B$8))+($O16*('Scoring Format'!$B$3))+($Q16*('Scoring Format'!$B$6)) -> 0 | Y16: =(($G16*('Scoring Format'!$B$2))+($I16*('Scoring Format'!$B$5))+($K16*('Scoring Format'!$B$8))+($O16*('Scoring Format'!$B$3))+($Q16*('Scoring Format'!$B$6)))*0.4 -> 0 | AD16: McDonald, Cole - ARI | AH16: =AG16/AF16 -> #DIV/0! | AJ16: =AI16/AF16 -> #DIV/0! | AL16: =AK16/AF16 -> #DIV/0! | AN16: =AM16/AF16 -> #DIV/0! | AR16: =AQ16/AP16 -> #DIV/0! | AT16: =AS16/AP16 -> #DIV/0! | AV16: =(AF16+AP16)/(AF20+AP20) -> #DIV/0! | AW16: =AF16/(AP16+AF16) -> #DIV/0! | AX16: =AP16/(AF16+AP16) -> #DIV/0! | AZ16: =((AI16*0.05)+(AK16*4)+(AM16*-1)+(AQ16*0.1)+(AS16*6))*0.55 -> 0 | BA16: =((AI16*0.05)+(AK16*4)+(AM16*-1)+(AQ16*0.1)+(AS16*6))*0.4 -> 0
A17: Total | D17: =SUM(D14:D16) -> 509 | E17: =SUM(E14:E16) -> 335 | G17: =SUM(G14:G16) -> 3541 | I17: =SUM(I14:I16) -> 27 | K17: =SUM(K14:K16) -> 14 | N17: =SUM(N14:N16) -> 59 | O17: =SUM(O14:O16) -> 214 | Q17: =SUM(Q14:Q16) -> 2 | T17: =T14+T15+T16 -> 1 | U17: =D17/(D17+N17) -> 0.89612676 | V17: =N17/(N17+D17) -> 0.10387324 | AD17: Total | AF17: =SUM(AF14:AF16) -> 583 | AG17: =SUM(AG14:AG16) -> 378 | AI17: =SUM(AI14:AI16) -> 4072 | AK17: =SUM(AK14:AK16) -> 27 | AM17: =SUM(AM14:AM16) -> 11 | AP17: =SUM(AP14:AP16) -> 100 | AQ17: =SUM(AQ14:AQ16) -> 590 | AS17: =SUM(AS14:AS16) -> 5 | AV17: =AV14+AV15+AV16 -> #DIV/0! | AW17: =AF17/(AF17+AP17) -> 0.85358712 | AX17: =AP17/(AP17+AF17) -> 0.14641288
A20: Rushing | H20: Receiving | T20: Touches | AE20: Rushing | AL20: Receiving | AV20: Touches | AZ20: Fantasy Points
A21: RB | B21: Age | C21: G | D21: Att | E21: Yards | F21: Yds/Att | G21: TDs | H21: TDs/Att | J21: Catch % | K21: Targets | L21: Rec | M21: Yds | N21: Yds/Rec | O21: TDs | P21: TDs/Rec | S21: RB | T21: Touch % | U21: Pct Pass | V21: Pct Run | X21: Fpts | Y21: PPR Fpts | Z21: .5 PPR | AD21: RB | AE21: G | AF21: Att | AG21: Yards | AH21: Yds/Att | AI21: TDs | AJ21: TDs/Att | AL21: Catch % | AM21: Targets | AN21: Rec | AO21: Yds | AP21: Yds/Rec | AQ21: TDs | AR21: TDs/Rec | AV21: Touch % | AW21: Pct Pass | AX21: Pct Run | AZ21: Fpts | BA21: PPR Fpts
A22: RB*Brooks, Jonathon - CAR | B22: 22 | C22: 17 | D22: 204 | E22: 867 | F22: =E22/D22 -> 4.25 | G22: 4 | H22: =G22/D22 -> 0.019607843 | J22: =L22/K22 -> 0.77272727 | K22: 44 | L22: 34 | M22: 215 | N22: =M22/L22 -> 6.3235294 | O22: 3 | P22: =O22/L22 -> 0.088235294 | S22: Brooks, Jonathon - CAR | T22: =(D22+K22)/($D$27+$K$27+$N$17+$E$17+$L$38+$L$47) -> 0.28770302 | U22: =K22/($K$27+$F$38+$F$47) -> 0.12359551 | V22: =D22/($D$27+$N$17+$L$38+$L$47) -> 0.46681922 | X22: =($E22*('Scoring Format'!$B$3))+($G22*('Scoring Format'!$B$6))+($M22*('Scoring Format'!$B$4))+($O22*('Scoring Format'!$B$7)) -> 150.2 | Y22: =($E22*('Scoring Format'!$B$3))+($G22*('Scoring Format'!$B$6))+(L22*1)+($M22*('Scoring Format'!$B$4))+($O22*('Scoring Format'!$B$7)) -> 184.2 | Z22: =($E22*('Scoring Format'!$B$3))+($G22*('Scoring Format'!$B$6))+(L22*0.5)+($M22*('Scoring Format'!$B$4))+($O22*('Scoring Format'!$B$7)) -> 167.2 | AD22: Conner, James - ARI | AF22: 200 | AG22: 1040 | AH22: =AG22/AF22 -> 5.2 | AI22: 7 | AJ22: =AI22/AF22 -> 0.035 | AL22: =AN22/AM22 -> 0.8 | AM22: 70 | AN22: 56 | AO22: 364 | AP22: =AO22/AN22 -> 6.5 | AQ22: 2 | AR22: =AQ22/AN22 -> 0.035714286 | AV22: =(#REF!+AM22)/(#REF!+AM25) -> #REF! | AW22: =#REF!/(AM22+#REF!) -> #REF! | AX22: =AM22/(#REF!+AM22) -> #REF! | AZ22: =(#REF!*0.1)+(AF22*6)+(AL22*0.1)+(AN22*6) -> #REF! | BA22: =(#REF!*0.1)+(AF22*6)+(AK22*1)+(AL22*0.1)+(AN22*6) -> #REF!
A23: RB*Hubbard, Chuba - CAR | B23: 27 | C23: 15 | D23: 123 | E23: 480 | F23: =E23/D23 -> 3.902439 | G23: 2 | H23: =G23/D23 -> 0.016260163 | J23: =L23/K23 -> 0.77142857 | K23: 35 | L23: 27 | M23: 171 | N23: =M23/L23 -> 6.3333333 | O23: 2 | P23: =O23/L23 -> 0.074074074 | S23: Hubbard, Chuba - CAR | T23: =(D23+K23)/($D$27+$K$27+$N$17+$E$17+$L$38+$L$47) -> 0.18329466 | U23: =K23/($K$27+$F$38+$F$47) -> 0.098314607 | V23: =D23/($D$27+$N$17+$L$38+$L$47) -> 0.28146453 | X23: =($E23*('Scoring Format'!$B$3))+($G23*('Scoring Format'!$B$6))+($M23*('Scoring Format'!$B$4))+($O23*('Scoring Format'!$B$7)) -> 89.1 | Y23: =($E23*('Scoring Format'!$B$3))+($G23*('Scoring Format'!$B$6))+(L23*1)+($M23*('Scoring Format'!$B$4))+($O23*('Scoring Format'!$B$7)) -> 116.1 | Z23: =($E23*('Scoring Format'!$B$3))+($G23*('Scoring Format'!$B$6))+(L23*0.5)+($M23*('Scoring Format'!$B$4))+($O23*('Scoring Format'!$B$7)) -> 102.6 | AD23: Edmonds, Chase - ARI | AF23: 96 | AG23: 445 | AH23: =AG23/AF23 -> 4.6354167 | AI23: 6 | AJ23: =AI23/AF23 -> 0.0625 | AL23: =AN23/AM23 -> 0.58333333 | AM23: 24 | AN23: 14 | AO23: 110 | AP23: =AO23/AN23 -> 7.8571429 | AQ23: 2 | AR23: =AQ23/AN23 -> 0.14285714 | AV23: =(#REF!+AM23)/(#REF!+AM26) -> #REF! | AW23: =#REF!/(AM23+#REF!) -> #REF! | AX23: =AM23/(#REF!+AM23) -> #REF! | AZ23: =(#REF!*0.1)+(AF23*6)+(AL23*0.1)+(AN23*6) -> #REF! | BA23: =(#REF!*0.1)+(AF23*6)+(AK23*1)+(AL23*0.1)+(AN23*6) -> #REF!
A24: RB*Etienne, Trevor - CAR | B24: 21 | C24: 17 | D24: 35 | E24: 155 | F24: =E24/D24 -> 4.4285714 | G24: 1 | H24: =G24/D24 -> 0.028571429 | J24: =L24/K24 -> 0.8 | K24: 10 | L24: 8 | M24: 41 | N24: =M24/L24 -> 5.125 | O24: 0 | P24: =O24/L24 -> 0 | S24: Etienne, Trevor - CAR | T24: =(D24+K24)/($D$27+$K$27+$N$17+$E$17+$L$38+$L$47) -> 0.052204176 | U24: =K24/($K$27+$F$38+$F$47) -> 0.028089888 | V24: =D24/($D$27+$N$17+$L$38+$L$47) -> 0.080091533 | X24: =($E24*('Scoring Format'!$B$3))+($G24*('Scoring Format'!$B$6))+($M24*('Scoring Format'!$B$4))+($O24*('Scoring Format'!$B$7)) -> 25.6 | Y24: =($E24*('Scoring Format'!$B$3))+($G24*('Scoring Format'!$B$6))+(L24*1)+($M24*('Scoring Format'!$B$4))+($O24*('Scoring Format'!$B$7)) -> 33.6 | Z24: =($E24*('Scoring Format'!$B$3))+($G24*('Scoring Format'!$B$6))+(L24*0.5)+($M24*('Scoring Format'!$B$4))+($O24*('Scoring Format'!$B$7)) -> 29.6 | AD24: Benjamin, Eno - ARI | AF24: 8 | AG24: 28 | AH24: =AG24/AF24 -> 3.5 | AI24: 0 | AJ24: =AI24/AF24 -> 0 | AL24: =AN24/AM24 -> 0.5 | AM24: 4 | AN24: 2 | AO24: 17 | AP24: =AO24/AN24 -> 8.5 | AQ24: 0 | AR24: =AQ24/AN24 -> 0 | AV24: =(#REF!+AM24)/(#REF!+AM30) -> #REF! | AW24: =#REF!/(AM24+#REF!) -> #REF! | AX24: =AM24/(#REF!+AM24) -> #REF! | AZ24: =(#REF!*0.1)+(AF24*6)+(AL24*0.1)+(AN24*6) -> #REF! | BA24: =(#REF!*0.1)+(AF24*6)+(AK24*1)+(AL24*0.1)+(AN24*6) -> #REF!
A25: RB*Dillon, AJ - CAR | B25: 28 | C25: 5 | D25: 7 | E25: 30 | F25: =E25/D25 -> 4.2857143 | G25: 0 | H25: =G25/D25 -> 0 | J25: =L25/K25 -> 0 | K25: 1 | L25: 0 | M25: 0 | N25: =M25/L25 -> #DIV/0! | O25: 0 | P25: =O25/L25 -> #DIV/0! | S25: Dillon, AJ - CAR | T25: =(D25+K25)/($D$27+$K$27+$N$17+$E$17+$L$38+$L$47) -> 0.0092807425 | U25: =K25/($K$27+$F$38+$F$47) -> 0.0028089888 | V25: =D25/($D$27+$N$17+$L$38+$L$47) -> 0.016018307 | X25: =($E25*('Scoring Format'!$B$3))+($G25*('Scoring Format'!$B$6))+($M25*('Scoring Format'!$B$4))+($O25*('Scoring Format'!$B$7)) -> 3 | Y25: =($E25*('Scoring Format'!$B$3))+($G25*('Scoring Format'!$B$6))+(L25*1)+($M25*('Scoring Format'!$B$4))+($O25*('Scoring Format'!$B$7)) -> 3 | Z25: =($E25*('Scoring Format'!$B$3))+($G25*('Scoring Format'!$B$6))+(L25*0.5)+($M25*('Scoring Format'!$B$4))+($O25*('Scoring Format'!$B$7)) -> 3 | AD25: Ward, Jonathan - ARI | AH25: =AG25/AF25 -> #DIV/0! | AI25: 0 | AJ25: =AI25/AF25 -> #DIV/0! | AL25: =AN25/AM25 -> #DIV/0! | AP25: =AO25/AN25 -> #DIV/0! | AQ25: 0 | AR25: =AQ25/AN25 -> #DIV/0! | AV25: =(#REF!+AM25)/(#REF!+AM31) -> #REF! | AW25: =#REF!/(AM25+#REF!) -> #REF! | AX25: =AM25/(#REF!+AM25) -> #REF! | AZ25: =(#REF!*0.1)+(AF25*6)+(AL25*0.1)+(AN25*6) -> #REF! | BA25: =(#REF!*0.1)+(AF25*6)+(AK25*1)+(AL25*0.1)+(AN25*6) -> #REF!
F26: =E26/D26 -> #DIV/0! | H26: =G26/D26 -> #DIV/0! | J26: =L26/K26 -> #DIV/0! | N26: =M26/L26 -> #DIV/0! | O26: 0 | P26: =O26/L26 -> #DIV/0! | T26: =(D26+K26)/($D$27+$K$27+$N$17+$E$17+$L$38+$L$47) -> 0 | U26: =K26/($K$27+$F$38+$F$47) -> 0 | V26: =D26/($D$27+$N$17+$L$38+$L$47) -> 0 | X26: =($E26*('Scoring Format'!$B$3))+($G26*('Scoring Format'!$B$6))+($M26*('Scoring Format'!$B$4))+($O26*('Scoring Format'!$B$7)) -> 0 | Y26: =($E26*('Scoring Format'!$B$3))+($G26*('Scoring Format'!$B$6))+(L26*1)+($M26*('Scoring Format'!$B$4))+($O26*('Scoring Format'!$B$7)) -> 0 | Z26: =($E26*('Scoring Format'!$B$3))+($G26*('Scoring Format'!$B$6))+(L26*0.5)+($M26*('Scoring Format'!$B$4))+($O26*('Scoring Format'!$B$7)) -> 0 | AD26: Muhammad, Khalfani - ARI | AH26: =AG26/AF26 -> #DIV/0! | AJ26: =AI26/AF26 -> #DIV/0! | AL26: =AN26/AM26 -> #DIV/0! | AQ26: =(AG26*0.1)+(AI26*6)+(AN26*0.1)+(AP26*6) -> 0 | AR26: =AQ26/AN26 -> #DIV/0! | AV26: =(#REF!+AM26)/(#REF!+AM32) -> #REF! | AW26: =#REF!/(AM26+#REF!) -> #REF! | AX26: =AM26/(#REF!+AM26) -> #REF! | AZ26: =(#REF!*0.1)+(AF26*6)+(AJ26*1)+(AK26*0.1)+(AM26*6) -> #REF! | BA26: =(#REF!*0.1)+(AF26*6)+(AK26*1)+(AL26*0.1)+(AN26*6) -> #REF!
A27: Total | D27: =SUM(D22:D26) -> 369 | E27: =SUM(E22:E26) -> 1532 | G27: =SUM(G22:G26) -> 7 | K27: =SUM(K22:K26) -> 90 | L27: =SUM(L22:L26) -> 69 | M27: =SUM(M22:M26) -> 427 | O27: =SUM(O22:O26) -> 5 | AD27: Total | AF27: =SUM(AF22:AF26) -> 304 | AG27: =SUM(AG22:AG26) -> 1513 | AI27: =SUM(AI22:AI26) -> 13 | AM27: =SUM(AM22:AM26) -> 98 | AN27: =SUM(AN22:AN26) -> 72 | AO27: =SUM(AO22:AO26) -> 491 | AQ27: =SUM(AQ22:AQ26) -> 4
A30: Receiving | L30: Rushing | T30: Touches | AE30: Receiving | AN30: Rushing | AV30: Touches | AZ30: Fantasy Points
A31: WRs | B31: Age | C31: G | D31: Catch % | E31: Targets | F31: Rec | G31: Yds | H31: Yds/Rec | I31: TDs | J31: TDs/Rec | L31: Ratt | M31: Ryds | N31: Ryds/Att | O31: RTds | P31: TDs/Att | S31: WRs | T31: Touch % | U31: Pct Pass | V31: Pct Run | X31: Fpts | Y31: PPR Fpts | Z31: .5PPR | AD31: WRs | AE31: G | AF31: Catch % | AG31: Targets | AH31: Rec | AI31: Yds | AJ31: Yds/Rec | AK31: TDs | AL31: TDs/Rec | AN31: Ratt | AO31: Ryds | AP31: Ryds/Att | AQ31: RTds | AR31: TDs/Att | AV31: Touch % | AW31: Pct Pass | AX31: Pct Run | AZ31: Fpts | BA31: PPR Fpts
D32: =F32/E32 -> #DIV/0! | H32: =G32/F32 -> #DIV/0! | J32: =I32/F32 -> #DIV/0! | L32: 0 | M32: 0 | N32: =M32/L32 -> #DIV/0! | O32: 0 | P32: =O32/L32 -> #DIV/0! | T32: =(E32+L32)/($D$27+$L$27+$N$17+$E$47+$L$47) -> 0 | U32: =E32/($E$17) -> 0 | V32: =L32/($N$17+$D$27+$L$38+$L$47) -> 0 | X32: =($G32*('Scoring Format'!$B$4))+($I32*'Scoring Format'!$B$7)+($M32*('Scoring Format'!$B$3))+($O32*('Scoring Format'!$B$6)) -> 0 | Y32: =(F32*1)+(($G32*('Scoring Format'!$B$4))+($I32*'Scoring Format'!$B$7)+($M32*('Scoring Format'!$B$3))+($O32*('Scoring Format'!$B$6))) -> 0 | Z32: =(F32*0.5)+(($G32*('Scoring Format'!$B$4))+($I32*'Scoring Format'!$B$7)+($M32*('Scoring Format'!$B$3))+($O32*('Scoring Format'!$B$6))) -> 0 | AD32: Green, A.J. - ARI | AF32: =AH32/AG32 -> 0.60747664 | AG32: 107 | AH32: 65 | AI32: 710 | AJ32: =AI32/AH32 -> 10.923077 | AK32: 6 | AL32: =AK32/AH32 -> 0.092307692 | AN32: 0 | AO32: 0 | AP32: =AO32/AN32 -> #DIV/0! | AQ32: 0 | AR32: =AQ32/AN32 -> #DIV/0! | AV32: =(#REF!+AK32)/(#REF!+AK35) -> #REF! | AW32: =#REF!/(AK32+#REF!) -> #REF! | AX32: =AK32/(#REF!+AK32) -> #REF! | AZ32: =(AI32*0.1)+(AK32*6)+(AO32*0.1)+(AQ32*6) -> 107 | BA32: =(AH32*1)+(AI32*0.1)+(AK32*6)+(AO32*0.1)+(AQ32*6) -> 172
A33: WR*McMillan, Tetairoa - CAR | B33: 23 | C33: 17 | D33: =F33/E33 -> 0.61029412 | E33: 136 | F33: 83 | G33: 1035 | H33: =G33/F33 -> 12.46988 | I33: 8 | J33: =I33/F33 -> 0.096385542 | L33: 0 | M33: 0 | N33: =M33/L33 -> #DIV/0! | O33: 0 | P33: =O33/L33 -> #DIV/0! | S33: McMillan, Tetairoa - CAR | T33: =(E33+L33)/($D$27+$L$27+$N$17+$E$47+$L$47) -> 0.23089983 | U33: =E33/($E$17) -> 0.40597015 | V33: =L33/($N$17+$D$27+$L$38+$L$47) -> 0 | X33: =($G33*('Scoring Format'!$B$4))+($I33*'Scoring Format'!$B$7)+($M33*('Scoring Format'!$B$3))+($O33*('Scoring Format'!$B$6)) -> 151.5 | Y33: =(F33*1)+(($G33*('Scoring Format'!$B$4))+($I33*'Scoring Format'!$B$7)+($M33*('Scoring Format'!$B$3))+($O33*('Scoring Format'!$B$6))) -> 234.5 | Z33: =(F33*0.5)+(($G33*('Scoring Format'!$B$4))+($I33*'Scoring Format'!$B$7)+($M33*('Scoring Format'!$B$3))+($O33*('Scoring Format'!$B$6))) -> 193 | AD33: Kirk, Christian- ARI | AF33: =AH33/AG33 -> 0.63333333 | AG33: 120 | AH33: 76 | AI33: 892 | AJ33: =AI33/AH33 -> 11.736842 | AK33: 5 | AL33: =AK33/AH33 -> 0.065789474 | AN33: 12 | AO33: 108 | AP33: =AO33/AN33 -> 9 | AQ33: 0 | AR33: =AQ33/AN33 -> 0 | AV33: =(#REF!+AK33)/(#REF!+AK36) -> #REF! | AW33: =#REF!/(AK33+#REF!) -> #REF! | AX33: =AK33/(#REF!+AK33) -> #REF! | AZ33: =(AI33*0.1)+(AK33*6)+(AO33*0.1)+(AQ33*6) -> 130 | BA33: =(AH33*1)+(AI33*0.1)+(AK33*6)+(AO33*0.1)+(AQ33*6) -> 206
A34: WR*Legette, Xavier - CAR | B34: 25 | D34: =F34/E34 -> 0.55813953 | E34: 43 | F34: 24 | G34: 226 | H34: =G34/F34 -> 9.4166667 | I34: 1 | J34: =I34/F34 -> 0.041666667 | N34: =M34/L34 -> #DIV/0! | O34: 0 | P34: =O34/L34 -> #DIV/0! | S34: Legette, Xavier - CAR | T34: =(E34+L34)/($D$27+$L$27+$N$17+$E$47+$L$47) -> 0.073005093 | U34: =E34/($E$17) -> 0.12835821 | V34: =L34/($N$17+$D$27+$L$38+$L$47) -> 0 | X34: =($G34*('Scoring Format'!$B$4))+($I34*'Scoring Format'!$B$7)+($M34*('Scoring Format'!$B$3))+($O34*('Scoring Format'!$B$6)) -> 28.6 | Y34: =(F34*1)+(($G34*('Scoring Format'!$B$4))+($I34*'Scoring Format'!$B$7)+($M34*('Scoring Format'!$B$3))+($O34*('Scoring Format'!$B$6))) -> 52.6 | Z34: =(F34*0.5)+(($G34*('Scoring Format'!$B$4))+($I34*'Scoring Format'!$B$7)+($M34*('Scoring Format'!$B$3))+($O34*('Scoring Format'!$B$6))) -> 40.6 | AD34: Isabella, Andy - ARI | AF34: =AH34/AG34 -> 0.55 | AG34: 40 | AH34: 22 | AI34: 325 | AJ34: =AI34/AH34 -> 14.772727 | AK34: 2 | AL34: =AK34/AH34 -> 0.090909091 | AN34: 5 | AO34: 20 | AP34: =AO34/AN34 -> 4 | AQ34: 0 | AR34: =AQ34/AN34 -> 0 | AV34: =(#REF!+AK34)/(#REF!+AK37) -> #REF! | AW34: =#REF!/(AK34+#REF!) -> #REF! | AX34: =AK34/(#REF!+AK34) -> #REF! | AZ34: =(AI34*0.1)+(AK34*6)+(AO34*0.1)+(AQ34*6) -> 46.5 | BA34: =(AH34*1)+(AI34*0.1)+(AK34*6)+(AO34*0.1)+(AQ34*6) -> 68.5
A35: WR*Horn, Jimmy - CAR | B35: 23 | D35: =F35/E35 -> 0.55555556 | E35: 36 | F35: 20 | G35: 301 | H35: =G35/F35 -> 15.05 | I35: 1 | J35: =I35/F35 -> 0.05 | L35: 9 | M35: 81 | N35: =M35/L35 -> 9 | O35: 1 | P35: =O35/L35 -> 0.11111111 | S35: Horn, Jimmy - CAR | T35: =(E35+L35)/($D$27+$L$27+$N$17+$E$47+$L$47) -> 0.076400679 | U35: =E35/($E$17) -> 0.10746269 | V35: =L35/($N$17+$D$27+$L$38+$L$47) -> 0.020594966 | X35: =($G35*('Scoring Format'!$B$4))+($I35*'Scoring Format'!$B$7)+($M35*('Scoring Format'!$B$3))+($O35*('Scoring Format'!$B$6)) -> 50.2 | Y35: =(F35*1)+(($G35*('Scoring Format'!$B$4))+($I35*'Scoring Format'!$B$7)+($M35*('Scoring Format'!$B$3))+($O35*('Scoring Format'!$B$6))) -> 70.2 | Z35: =(F35*0.5)+(($G35*('Scoring Format'!$B$4))+($I35*'Scoring Format'!$B$7)+($M35*('Scoring Format'!$B$3))+($O35*('Scoring Format'!$B$6))) -> 60.2 | AD35: Hopkins, DeAndre - ARI | AF35: =AH35/AG35 -> 0.66206897 | AG35: 145 | AH35: 96 | AI35: 1098 | AJ35: =AI35/AH35 -> 11.4375 | AK35: 7 | AL35: =AK35/AH35 -> 0.072916667 | AN35: 0 | AO35: 0 | AP35: =AO35/AN35 -> #DIV/0! | AQ35: 0 | AR35: =AQ35/AN35 -> #DIV/0! | AV35: =(#REF!+AK35)/(#REF!+AK38) -> #REF! | AW35: =#REF!/(AK35+#REF!) -> #REF! | AX35: =AK35/(#REF!+AK35) -> #REF! | AZ35: =(AI35*0.1)+(AK35*6)+(AO35*0.1)+(AQ35*6) -> 151.8 | BA35: =(AH35*1)+(AI35*0.1)+(AK35*6)+(AO35*0.1)+(AQ35*6) -> 247.8
A36: WR*Coker, Jalen - CAR | B36: 27 | C36: 17 | D36: =F36/E36 -> 0.68807339 | E36: 109 | F36: 75 | G36: 960 | H36: =G36/F36 -> 12.8 | I36: 8 | J36: =I36/F36 -> 0.10666667 | L36: 0 | M36: 0 | N36: =M36/L36 -> #DIV/0! | O36: 0 | P36: =O36/L36 -> #DIV/0! | S36: Coker, Jalen - CAR | T36: =(E36+L36)/($D$27+$L$27+$N$17+$E$47+$L$47) -> 0.18505942 | U36: =E36/($E$17) -> 0.32537313 | V36: =L36/($N$17+$D$27+$L$38+$L$47) -> 0 | X36: =($G36*('Scoring Format'!$B$4))+($I36*'Scoring Format'!$B$7)+($M36*('Scoring Format'!$B$3))+($O36*('Scoring Format'!$B$6)) -> 144 | Y36: =(F36*1)+(($G36*('Scoring Format'!$B$4))+($I36*'Scoring Format'!$B$7)+($M36*('Scoring Format'!$B$3))+($O36*('Scoring Format'!$B$6))) -> 219 | Z36: =(F36*0.5)+(($G36*('Scoring Format'!$B$4))+($I36*'Scoring Format'!$B$7)+($M36*('Scoring Format'!$B$3))+($O36*('Scoring Format'!$B$6))) -> 181.5 | AD36: Johnson, KeeSean - ARI | AF36: =AH36/AG36 -> 0.6 | AG36: 10 | AH36: 6 | AI36: 100 | AJ36: =AI36/AH36 -> 16.666667 | AK36: 0 | AL36: =AK36/AH36 -> 0 | AN36: 0 | AO36: 0 | AP36: =AO36/AN36 -> #DIV/0! | AQ36: 0 | AR36: =AQ36/AN36 -> #DIV/0! | AV36: =(#REF!+AK36)/(#REF!+AK41) -> #REF! | AW36: =#REF!/(AK36+#REF!) -> #REF! | AX36: =AK36/(#REF!+AK36) -> #REF! | AZ36: =(AI36*0.1)+(AK36*6)+(AO36*0.1)+(AQ36*6) -> 10 | BA36: =(AH36*1)+(AI36*0.1)+(AK36*6)+(AO36*0.1)+(AQ36*6) -> 16
A37: WR*Moore, David - CAR | B37: 31 | D37: =F37/E37 -> 0.33333333 | E37: 3 | F37: 1 | G37: 12 | H37: =G37/F37 -> 12 | I37: 0 | J37: =I37/F37 -> 0 | L37: 0 | M37: 0 | N37: =M37/L37 -> #DIV/0! | O37: 0 | P37: =O37/L37 -> #DIV/0! | S37: Moore, David - CAR | T37: =(E37+L37)/($D$27+$L$27+$N$17+$E$47+$L$47) -> 0.0050933786 | U37: =E37/($E$17) -> 0.0089552239 | V37: =L37/($N$17+$D$27+$L$38+$L$47) -> 0 | X37: =($G37*('Scoring Format'!$B$4))+($I37*'Scoring Format'!$B$7)+($M37*('Scoring Format'!$B$3))+($O37*('Scoring Format'!$B$6)) -> 1.2 | Y37: =(F37*1)+(($G37*('Scoring Format'!$B$4))+($I37*'Scoring Format'!$B$7)+($M37*('Scoring Format'!$B$3))+($O37*('Scoring Format'!$B$6))) -> 2.2 | Z37: =(F37*0.5)+(($G37*('Scoring Format'!$B$4))+($I37*'Scoring Format'!$B$7)+($M37*('Scoring Format'!$B$3))+($O37*('Scoring Format'!$B$6))) -> 1.7 | AD37: Moore, Rondale - ARI | AF37: =AH37/AG37 -> #DIV/0! | AL37: =AK37/AH37 -> #DIV/0! | AP37: =AO37/AN37 -> #DIV/0! | AR37: =AQ37/AN37 -> #DIV/0! | AV37: =(#REF!+AK37)/(#REF!+AK42) -> #REF! | AW37: =#REF!/(AK37+#REF!) -> #REF! | AX37: =AK37/(#REF!+AK37) -> #REF!
A38: Total | E38: =SUM(E32:E37) -> 327 | F38: =SUM(F32:F37) -> 203 | G38: =SUM(G32:G37) -> 2534 | I38: =SUM(I32:I37) -> 18 | L38: =SUM(L32:L37) -> 9 | M38: =SUM(M32:M37) -> 81 | O38: =SUM(O32:O37) -> 1 | AD38: Total | AG38: =SUM(AG32:AG37) -> 422 | AH38: =SUM(AH32:AH37) -> 265 | AI38: =SUM(AI32:AI37) -> 3125 | AK38: =SUM(AK32:AK37) -> 20 | AN38: =SUM(AN32:AN37) -> 17 | AO38: =SUM(AO32:AO37) -> 128 | AQ38: =SUM(AQ32:AQ37) -> 0
A41: Receiving | L41: Rushing | T41: Touches | AE41: Receiving | AN41: Rushing | AV41: Touches | AZ41: Fantasy Points
A42: Tes | B42: Age | C42: G | D42: Catch % | E42: Targets | F42: Rec | G42: Yds | H42: Yds/Rec | I42: TDs | J42: TDs/Rec | L42: Ratt | M42: Ryds | N42: Ryds/Att | O42: RTDs | P42: TDs/Att | S42: Tes | T42: Touch % | U42: Pct Pass | V42: Pct Run | X42: Fpts | Y42: PPR Fpts | Z42: .5 PPR | AD42: Tes | AE42: G | AF42: Catch % | AG42: Targets | AH42: Rec | AI42: Yds | AJ42: Yds/Rec | AK42: TDs | AL42: TDs/Rec | AN42: Ratt | AO42: Ryds | AP42: Ryds/Att | AQ42: RTDs | AR42: TDs/Att | AV42: Touch % | AW42: Pct Pass | AX42: Pct Run | AZ42: Fpts | BA42: PPR Fpts
A43: TE*Sanders, JaTavion - CAR | B43: 23 | C43: 17 | D43: =F43/E43 -> 0.65714286 | E43: 35 | F43: 23 | G43: 211 | H43: =G43/F43 -> 9.173913 | I43: 1 | J43: =I43/F43 -> 0.043478261 | N43: =M43/L43 -> #DIV/0! | P43: =O43/L43 -> #DIV/0! | S43: Sanders, JaTavion - CAR | T43: =(E43+L43)/($E$47+$L$47+$E$38+$L$38+$K$27+$D$27+$N$17) -> 0.036997886 | U43: =E43/($E$47+$E$38+$K$27) -> 0.068762279 | V43: =L43/($L$47+$L$38+$D$27+$N$17) -> 0 | X43: =($G43*('Scoring Format'!$B$4))+($I43*'Scoring Format'!$B$7)+($M43*('Scoring Format'!$B$3))+($O43*('Scoring Format'!$B$6)) -> 27.1 | Y43: =(F43*1)+(($G43*('Scoring Format'!$B$4))+($I43*'Scoring Format'!$B$7)+($M43*('Scoring Format'!$B$3))+($O43*('Scoring Format'!$B$6))) -> 50.1 | Z43: =(F43*0.5)+(($G43*('Scoring Format'!$B$4))+($I43*'Scoring Format'!$B$7)+($M43*('Scoring Format'!$B$3))+($O43*('Scoring Format'!$B$6))) -> 38.6 | AD43: Williams, Maxx - ARI | AF43: =AH43/AG43 -> 0.5625 | AG43: 16 | AH43: 9 | AI43: 108 | AJ43: =AI43/AH43 -> 12 | AK43: 1 | AL43: =AK43/AH43 -> 0.11111111 | AN43: 0 | AO43: 0 | AP43: 0 | AQ43: 0 | AR43: =AQ43/AN43 -> #DIV/0! | AV43: =(#REF!+AK43)/(#REF!+AK46) -> #REF! | AW43: =#REF!/(AK43+#REF!) -> #REF! | AX43: =AK43/(#REF!+AK43) -> #REF! | AZ43: =(AI43*0.1)+(AK43*6)+(AO43*0.1)+(AQ43*6) -> 16.8 | BA43: =(AH43*1)+(AI43*0.1)+(AK43*6)+(AO43*0.1)+(AQ43*6) -> 25.8
A44: TE*Evans, Mitchell - CAR | B44: 23 | C44: 17 | D44: =F44/E44 -> 0.69230769 | E44: 26 | F44: 18 | G44: 160 | H44: =G44/F44 -> 8.8888889 | I44: 1 | J44: =I44/F44 -> 0.055555556 | N44: =M44/L44 -> #DIV/0! | P44: =O44/L44 -> #DIV/0! | S44: Evans, Mitchell - CAR | T44: =(E44+L44)/($E$47+$L$47+$E$38+$L$38+$K$27+$D$27+$N$17) -> 0.027484144 | U44: =E44/($E$47+$E$38+$K$27) -> 0.05108055 | V44: =L44/($L$47+$L$38+$D$27+$N$17) -> 0 | X44: =($G44*('Scoring Format'!$B$4))+($I44*'Scoring Format'!$B$7)+($M44*('Scoring Format'!$B$3))+($O44*('Scoring Format'!$B$6)) -> 22 | Y44: =(F44*1)+(($G44*('Scoring Format'!$B$4))+($I44*'Scoring Format'!$B$7)+($M44*('Scoring Format'!$B$3))+($O44*('Scoring Format'!$B$6))) -> 40 | Z44: =(F44*0.5)+(($G44*('Scoring Format'!$B$4))+($I44*'Scoring Format'!$B$7)+($M44*('Scoring Format'!$B$3))+($O44*('Scoring Format'!$B$6))) -> 31 | AD44: Daniels, Darenell - ARI | AF44: =AH44/AG44 -> 0.74285714 | AG44: 35 | AH44: 26 | AI44: 283 | AJ44: =AI44/AH44 -> 10.884615 | AK44: 2 | AL44: =AK44/AH44 -> 0.076923077 | AN44: 0 | AO44: 0 | AP44: 0 | AQ44: 0 | AR44: =AQ44/AN44 -> #DIV/0! | AV44: =(#REF!+AK44)/(#REF!+AK47) -> #REF! | AW44: =#REF!/(AK44+#REF!) -> #REF! | AX44: =AK44/(#REF!+AK44) -> #REF! | AZ44: =(AI44*0.1)+(AK44*6)+(AO44*0.1)+(AQ44*6) -> 40.3 | BA44: =(AH44*1)+(AI44*0.1)+(AK44*6)+(AO44*0.1)+(AQ44*6) -> 66.3
A45: TE*Tremble, Tommy - CAR | B45: 26 | C45: 17 | D45: =F45/E45 -> 0.7 | E45: 30 | F45: 21 | G45: 201 | H45: =G45/F45 -> 9.5714286 | I45: 2 | J45: =I45/F45 -> 0.095238095 | N45: =M45/L45 -> #DIV/0! | P45: =O45/L45 -> #DIV/0! | S45: Tremble, Tommy - CAR | T45: =(E45+L45)/($E$47+$L$47+$E$38+$L$38+$K$27+$D$27+$N$17) -> 0.031712474 | U45: =E45/($E$47+$E$38+$K$27) -> 0.058939096 | V45: =L45/($L$47+$L$38+$D$27+$N$17) -> 0 | X45: =($G45*('Scoring Format'!$B$4))+($I45*'Scoring Format'!$B$7)+($M45*('Scoring Format'!$B$3))+($O45*('Scoring Format'!$B$6)) -> 32.1 | Y45: =(F45*1)+(($G45*('Scoring Format'!$B$4))+($I45*'Scoring Format'!$B$7)+($M45*('Scoring Format'!$B$3))+($O45*('Scoring Format'!$B$6))) -> 53.1 | Z45: =(F45*0.5)+(($G45*('Scoring Format'!$B$4))+($I45*'Scoring Format'!$B$7)+($M45*('Scoring Format'!$B$3))+($O45*('Scoring Format'!$B$6))) -> 42.6 | AD45: Bunting, Ian - ARI | AF45: =AH45/AG45 -> 0.5 | AG45: 12 | AH45: 6 | AI45: 65 | AJ45: =AI45/AH45 -> 10.833333 | AK45: 0 | AL45: =AK45/AH45 -> 0 | AN45: 0 | AO45: 0 | AP45: 0 | AQ45: 0 | AR45: =AQ45/AN45 -> #DIV/0! | AV45: =(#REF!+AK45)/(#REF!+AI49) -> #REF! | AW45: =#REF!/(AK45+#REF!) -> #REF! | AX45: =AK45/(#REF!+AK45) -> #REF! | AZ45: =(AI45*0.1)+(AK45*6)+(AO45*0.1)+(AQ45*6) -> 6.5 | BA45: =(AH45*1)+(AI45*0.1)+(AK45*6)+(AO45*0.1)+(AQ45*6) -> 12.5
A46: TE*Mitchell, James - CAR | B46: 26 | C46: 17 | D46: =F46/E46 -> 1 | E46: 1 | F46: 1 | G46: 8 | H46: =G46/F46 -> 8 | I46: 0 | J46: =I46/F46 -> 0 | N46: =M46/L46 -> #DIV/0! | P46: =O46/L46 -> #DIV/0! | S46: Mitchell, James - CAR | T46: =(E46+L46)/($E$47+$L$47+$E$38+$L$38+$K$27+$D$27+$N$17) -> 0.0010570825 | U46: =E46/($E$47+$E$38+$K$27) -> 0.0019646365 | V46: =L46/($L$47+$L$38+$D$27+$N$17) -> 0 | X46: =($G46*('Scoring Format'!$B$4))+($I46*'Scoring Format'!$B$7)+($M46*('Scoring Format'!$B$3))+($O46*('Scoring Format'!$B$6)) -> 0.8 | Y46: =(F46*1)+(($G46*('Scoring Format'!$B$4))+($I46*'Scoring Format'!$B$7)+($M46*('Scoring Format'!$B$3))+($O46*('Scoring Format'!$B$6))) -> 1.8 | Z46: =(F46*0.5)+(($G46*('Scoring Format'!$B$4))+($I46*'Scoring Format'!$B$7)+($M46*('Scoring Format'!$B$3))+($O46*('Scoring Format'!$B$6))) -> 1.3 | AF46: =AH46/AG46 -> #DIV/0! | AJ46: =AI46/AH46 -> #DIV/0! | AL46: =AK46/AH46 -> #DIV/0! | AQ46: 0 | AR46: =AQ46/AN46 -> #DIV/0! | AV46: =(#REF!+AK46)/(#REF!+AI50) -> #REF! | AW46: =#REF!/(AK46+#REF!) -> #REF! | AX46: =AK46/(#REF!+AK46) -> #REF! | AZ46: =(AI46*0.1)+(AK46*6)+(AO46*0.1)+(AQ46*6) -> 0 | BA46: =(AH46*1)+(AI46*0.1)+(AK46*6)+(AO46*0.1)+(AQ46*6) -> 0
A47: Total | E47: =SUM(E43:E46) -> 92 | F47: =SUM(F43:F46) -> 63 | G47: =SUM(G43:G46) -> 580 | I47: =SUM(I43:I46) -> 4 | L47: =SUM(L43:L46) -> 0 | M47: =SUM(M43:M46) -> 0 | O47: =SUM(O43:O46) -> 0 | AD47: Total | AG47: =SUM(AG43:AG46) -> 63 | AH47: =SUM(AH43:AH46) -> 41 | AI47: =SUM(AI43:AI46) -> 456 | AK47: =SUM(AK43:AK46) -> 3 | AN47: =SUM(AN43:AN46) -> 0 | AO47: =SUM(AO43:AO46) -> 0 | AQ47: =SUM(AQ43:AQ46) -> 0
A50: Team Totals and Splits | J50: Taxi Squad* | R50: Injured Reserve | AC50: Team Totals and Splits | AL50: Taxi Squad* | AT50: Injured Reserve
B51: Targets | C51: Rec. | D51: Yds | E51: TDs | J51: Player | N51: Position | R51: Player | V51: Position | AD51: Targets | AE51: Rec. | AF51: Yds | AG51: TDs | AL51: Player | AP51: Position | AT51: Player | AX51: Position
A52: Rec Totals* | B52: =SUM(K22:K26,E32:E37,E43:E46) -> 509 | C52: =SUM(F43:F46,F32:F37,L22:L26) -> 335 | D52: =SUM(G43:G46,G32:G37,M22:M26) -> 3541 | E52: =SUM(O22:O26,I32:I37,I43:I46) -> 27 | J52: Haynes King | N52: QB | R52: Chris Brazzell | V52: WR | AC52: Rec Totals | AD52: =SUM(AM22:AM26,AG32:AG37,AG43:AG46) -> 583 | AE52: =SUM(AH43:AH46,AH32:AH37,AM22:AM26) -> 404 | AF52: =SUM(AI43:AI46,AI32:AI37,AN22:AN26) -> 3653 | AG52: =SUM(AQ22:AQ26,AK32:AK37,AK43:AK46) -> 27
A53: QB Totals | B53: =SUM(D17) -> 509 | C53: =SUM(E17) -> 335 | D53: =SUM(G17) -> 3541 | E53: =SUM(I17) -> 27 | J53: Anthony Tyus | N53: RB | AC53: QB Totals | AD53: =SUM(AF17) -> 583 | AE53: =SUM(AG17) -> 378 | AF53: =SUM(AI17) -> 4072 | AG53: =SUM(AK17) -> 27
A54: League Att Avg. | J54: Miles Davis | N54: RB | AC54: League Att Avg.
J55: John Metchie | N55: WR
B56: Att | C56: Yards | D56: TDs | J56: Brycen Tremaine | N56: WR | AD56: Att | AE56: Yards | AF56: TDs
A57: Rush Totals | B57: =SUM(N14:N16,D22:D26,L32:L37,L43:L46) -> 437 | C57: =SUM(O14:O16,E22:E26,M32:M37,M43:M46) -> 1827 | D57: =SUM(Q14:Q16,G22:G26,O32:O37,O43:O46) -> 10 | J57: Dan Chisena | N57: WR | AC57: Rush Totals | AD57: =SUM(AP14:AP16,AF22:AF26,AN32:AN37,AN43:AN46) -> 421 | AE57: =SUM(AQ14:AQ16,AG22:AG26,AO32:AO37,AO43:AO46) -> 2231 | AF57: =SUM(AS14:AS16,AI22:AI26,AQ32:AQ37,AQ43:AQ46) -> 18
